Workbook
Name CALC_REMAINED: 'Inputs & Assuptions'!$B$13:$B$72

Sheet Inputs & Assuptions
B1: Channel 1 | C1: Channel 2 | D1: Channel 3 | E1: Assumption Explanation
A2: Average Monthly Premium | B2: 600 | C2: 600 | D2: 300 | E2: Growing by 5% per annnum in all channels
A3: Premium Increase(per annum) | B3: 0.05 | C3: 0.05 | D3: 0.05
A4: Monthly Sales | B4: 6000 | C4: 1500 | D4: 1000 | E4: Growing by 5% per annnum in all channels
A5: Sales Increase(per annum) | B5: 0.05 | C5: 0.05 | D5: 0.05
A6: Commission | B6: 4 times monthly premium per sale | C6: Tiered on-going commission structure First R300 - 25% of premium R300-R600 - 20% of premium R600-R1,200 - 15% of premium R1,200-R1,500 – 10% of premium Above R1,500 – 5% of premium | D6: 20% per sale on-going commission
A7: Expenses | B7: 0.25 | C7: 0.25 | D7: 0.25 | E7: Calculated on Gross Premium
A8: Gross Claim Ratio | B8: 0.4 | C8: 0.4 | D8: 0.4
A11: Duration | B11: Lapse Rates
A12: 0 | B12: 0.42 | C12: 0.22 | D12: 0.022
A13: 1 | B13: 0.105 | C13: 0.0525 | D13: 0.005
A14: 2 | B14: 0.08 | C14: 0.04 | D14: 0.0038
A15: 3 | B15: 0.055 | C15: 0.0275 | D15: 0.0025
A16: 4 | B16: 0.05 | C16: 0.025 | D16: 0.0023
A17: 5 | B17: 0.045 | C17: 0.0225 | D17: 0.002
A18: 6 | B18: 0.04 | C18: 0.02 | D18: 0.0018
A19: 7 | B19: 0.035 | C19: 0.0175 | D19: 0.0015
A20: 8 | B20: 0.03 | C20: 0.015 | D20: 0.0013
A21: 9 | B21: 0.025 | C21: 0.0125 | D21: 0.001
A22: 10 | B22: 0.02 | C22: 0.01 | D22: 0.0008
A23: 11 | B23: 0.01 | C23: 0.005 | D23: 0.0005
... A72: 60 | B72: 0.01 | C72: 0.005 | D72: 0.0005

Sheet Summary
A14: 5 YEAR INCOME STATEMENT
A15: Year | B15: Gross Premium | C15: Commission Paid | D15: Claims Incurred | E15: Operating Expenses | F15: Net Profit/loss
A16: 1 | B16: =+B28+B36+B44 -> 2.0055016e+08 | C16: =+C28+C36+C44 -> -1.1589929e+08 | D16: =+D28+D36+D44 -> -80220063 | E16: =+E28+E36+E44 -> -50137539 | F16: =+F28+F36+F44 -> -45706736
A17: =+A16+1 -> 2 | B17: =+B29+B37+B45 -> 5.3991146e+08 | C17: =+C29+C37+C45 -> -1.5453045e+08 | D17: =+D29+D37+D45 -> -2.1596458e+08 | E17: =+E29+E37+E45 -> -1.3497786e+08 | F17: =+F29+F37+F45 -> 34438559
A18: =+A17+1 -> 3 | B18: =+B30+B38+B46 -> 8.9646135e+08 | C18: =+C30+C38+C46 -> -1.9660784e+08 | D18: =+D30+D38+D46 -> -3.5858454e+08 | E18: =+E30+E38+E46 -> -2.2411534e+08 | F18: =+F30+F38+F46 -> 1.1715363e+08
A19: =+A18+1 -> 4 | B19: =+B31+B39+B47 -> 1.2785081e+09 | C19: =+C31+C39+C47 -> -2.426181e+08 | D19: =+D31+D39+D47 -> -5.1140324e+08 | E19: =+E31+E39+E47 -> -3.1962703e+08 | F19: =+F31+F39+F47 -> 2.0485974e+08
A20: =+A19+1 -> 5 | B20: =+B32+B40+B48 -> 1.689601e+09 | C20: =+C32+C40+C48 -> -2.9300312e+08 | D20: =+D32+D40+D48 -> -6.7584041e+08 | E20: =+E32+E40+E48 -> -4.2240026e+08 | F20: =+F32+F40+F48 -> 2.9835724e+08
A26: Channel 1
A27: Year | B27: Gross Premium | C27: Commission Paid | D27: Claims Incurred | E27: Operating Expenses | F27: Net Profit/loss
A28: 1 | B28: =+SUM(OFFSET('Channel 1_calculations'!$E$6,(ROW($A28)-28)*12,0,12,1)) -> 1.2836767e+08 | C28: =+SUM(OFFSET('Channel 1_calculations'!$F$6,(ROW($A28)-28)*12,0,12,1)) -> -1.00224e+08 | D28: =+SUM(OFFSET('Channel 1_calculations'!$H$6,(ROW($A28)-28)*12,0,12,1)) -> -51347069 | E28: =+SUM(OFFSET('Channel 1_calculations'!$G$6,(ROW($A28)-28)*12,0,12,1)) -> -32091918 | F28: =+SUM(OFFSET('Channel 1_calculations'!$I$6,(ROW($A28)-28)*12,0,12,1)) -> -55295314
A29: =+A28+1 -> 2 | B29: =+SUM(OFFSET('Channel 1_calculations'!$E$6,(ROW($A29)-28)*12,0,12,1)) -> 3.3443681e+08 | C29: =+SUM(OFFSET('Channel 1_calculations'!$F$6,(ROW($A29)-28)*12,0,12,1)) -> -1.1049696e+08 | D29: =+SUM(OFFSET('Channel 1_calculations'!$H$6,(ROW($A29)-28)*12,0,12,1)) -> -1.3377472e+08 | E29: =+SUM(OFFSET('Channel 1_calculations'!$G$6,(ROW($A29)-28)*12,0,12,1)) -> -83609202 | F29: =+SUM(OFFSET('Channel 1_calculations'!$I$6,(ROW($A29)-28)*12,0,12,1)) -> 6555923.3
A30: =+A29+1 -> 3 | B30: =+SUM(OFFSET('Channel 1_calculations'!$E$6,(ROW($A30)-28)*12,0,12,1)) -> 5.4348285e+08 | C30: =+SUM(OFFSET('Channel 1_calculations'!$F$6,(ROW($A30)-28)*12,0,12,1)) -> -1.218229e+08 | D30: =+SUM(OFFSET('Channel 1_calculations'!$H$6,(ROW($A30)-28)*12,0,12,1)) -> -2.1739314e+08 | E30: =+SUM(OFFSET('Channel 1_calculations'!$G$6,(ROW($A30)-28)*12,0,12,1)) -> -1.3587071e+08 | F30: =+SUM(OFFSET('Channel 1_calculations'!$I$6,(ROW($A30)-28)*12,0,12,1)) -> 68396101
A31: =+A30+1 -> 4 | B31: =+SUM(OFFSET('Channel 1_calculations'!$E$6,(ROW($A31)-28)*12,0,12,1)) -> 7.6184554e+08 | C31: =+SUM(OFFSET('Channel 1_calculations'!$F$6,(ROW($A31)-28)*12,0,12,1)) -> -1.3430975e+08 | D31: =+SUM(OFFSET('Channel 1_calculations'!$H$6,(ROW($A31)-28)*12,0,12,1)) -> -3.0473821e+08 | E31: =+SUM(OFFSET('Channel 1_calculations'!$G$6,(ROW($A31)-28)*12,0,12,1)) -> -1.9046138e+08 | F31: =+SUM(OFFSET('Channel 1_calculations'!$I$6,(ROW($A31)-28)*12,0,12,1)) -> 1.3233619e+08
A32: =+A31+1 -> 5 | B32: =+SUM(OFFSET('Channel 1_calculations'!$E$6,(ROW($A32)-28)*12,0,12,1)) -> 9.9131902e+08 | C32: =+SUM(OFFSET('Channel 1_calculations'!$F$6,(ROW($A32)-28)*12,0,12,1)) -> -1.4807649e+08 | D32: =+SUM(OFFSET('Channel 1_calculations'!$H$6,(ROW($A32)-28)*12,0,12,1)) -> -3.9652761e+08 | E32: =+SUM(OFFSET('Channel 1_calculations'!$G$6,(ROW($A32)-28)*12,0,12,1)) -> -2.4782976e+08 | F32: =+SUM(OFFSET('Channel 1_calculations'!$I$6,(ROW($A32)-28)*12,0,12,1)) -> 1.9888516e+08
A34: Channel 2
A35: Year | B35: Gross Premium | C35: Commission Paid | D35: Claims Incurred | E35: Operating Expenses | F35: Net Profit/loss
A36: 1 | B36: =+SUM(OFFSET('Channel 2_calculations'!$E$6,(ROW($A28)-28)*12,0,12,1)) -> 49551773 | C36: =+SUM(OFFSET('Channel 2_calculations'!$F$6,(ROW($A28)-28)*12,0,12,1)) -> -11149149 | D36: =+SUM(OFFSET('Channel 2_calculations'!$H$6,(ROW($A28)-28)*12,0,12,1)) -> -19820709 | E36: =+SUM(OFFSET('Channel 2_calculations'!$G$6,(ROW($A28)-28)*12,0,12,1)) -> -12387943 | F36: =+SUM(OFFSET('Channel 2_calculations'!$I$6,(ROW($A28)-28)*12,0,12,1)) -> 6193971.6
A37: =+A36+1 -> 2 | B37: =+SUM(OFFSET('Channel 2_calculations'!$E$6,(ROW($A29)-28)*12,0,12,1)) -> 1.3713287e+08 | C37: =+SUM(OFFSET('Channel 2_calculations'!$F$6,(ROW($A29)-28)*12,0,12,1)) -> -30365135 | D37: =+SUM(OFFSET('Channel 2_calculations'!$H$6,(ROW($A29)-28)*12,0,12,1)) -> -54853148 | E37: =+SUM(OFFSET('Channel 2_calculations'!$G$6,(ROW($A29)-28)*12,0,12,1)) -> -34283217 | F37: =+SUM(OFFSET('Channel 2_calculations'!$I$6,(ROW($A29)-28)*12,0,12,1)) -> 17631369
A38: =+A37+1 -> 3 | B38: =+SUM(OFFSET('Channel 2_calculations'!$E$6,(ROW($A30)-28)*12,0,12,1)) -> 2.3238432e+08 | C38: =+SUM(OFFSET('Channel 2_calculations'!$F$6,(ROW($A30)-28)*12,0,12,1)) -> -50666105 | D38: =+SUM(OFFSET('Channel 2_calculations'!$H$6,(ROW($A30)-28)*12,0,12,1)) -> -92953728 | E38: =+SUM(OFFSET('Channel 2_calculations'!$G$6,(ROW($A30)-28)*12,0,12,1)) -> -58096080 | F38: =+SUM(OFFSET('Channel 2_calculations'!$I$6,(ROW($A30)-28)*12,0,12,1)) -> 30668407
A39: =+A38+1 -> 4 | B39: =+SUM(OFFSET('Channel 2_calculations'!$E$6,(ROW($A31)-28)*12,0,12,1)) -> 3.3648203e+08 | C39: =+SUM(OFFSET('Channel 2_calculations'!$F$6,(ROW($A31)-28)*12,0,12,1)) -> -72272243 | D39: =+SUM(OFFSET('Channel 2_calculations'!$H$6,(ROW($A31)-28)*12,0,12,1)) -> -1.3459281e+08 | E39: =+SUM(OFFSET('Channel 2_calculations'!$G$6,(ROW($A31)-28)*12,0,12,1)) -> -84120509 | F39: =+SUM(OFFSET('Channel 2_calculations'!$I$6,(ROW($A31)-28)*12,0,12,1)) -> 45496469
A40: =+A39+1 -> 5 | B40: =+SUM(OFFSET('Channel 2_calculations'!$E$6,(ROW($A32)-28)*12,0,12,1)) -> 4.5034294e+08 | C40: =+SUM(OFFSET('Channel 2_calculations'!$F$6,(ROW($A32)-28)*12,0,12,1)) -> -95338809 | D40: =+SUM(OFFSET('Channel 2_calculations'!$H$6,(ROW($A32)-28)*12,0,12,1)) -> -1.8013717e+08 | E40: =+SUM(OFFSET('Channel 2_calculations'!$G$6,(ROW($A32)-28)*12,0,12,1)) -> -1.1258573e+08 | F40: =+SUM(OFFSET('Channel 2_calculations'!$I$6,(ROW($A32)-28)*12,0,12,1)) -> 62281219
A42: Chanel 3
A43: Year | B43: Gross Premium | C43: Commission Paid | D43: Claims Incurred | E43: Operating Expenses | F43: Net Profit/loss
A44: 1 | B44: =+SUM(OFFSET('Channel 3_calculations'!$E$6,(ROW($A28)-28)*12,0,12,1)) -> 22630712 | C44: =+SUM(OFFSET('Channel 3_calculations'!$F$6,(ROW($A28)-28)*12,0,12,1)) -> -4526142.3 | D44: =+SUM(OFFSET('Channel 3_calculations'!$H$6,(ROW($A28)-28)*12,0,12,1)) -> -9052284.6 | E44: =+SUM(OFFSET('Channel 3_calculations'!$G$6,(ROW($A28)-28)*12,0,12,1)) -> -5657677.9 | F44: =+SUM(OFFSET('Channel 3_calculations'!$I$6,(ROW($A28)-28)*12,0,12,1)) -> 3394606.7
A45: =+A44+1 -> 2 | B45: =+SUM(OFFSET('Channel 3_calculations'!$E$6,(ROW($A29)-28)*12,0,12,1)) -> 68341780 | C45: =+SUM(OFFSET('Channel 3_calculations'!$F$6,(ROW($A29)-28)*12,0,12,1)) -> -13668356 | D45: =+SUM(OFFSET('Channel 3_calculations'!$H$6,(ROW($A29)-28)*12,0,12,1)) -> -27336712 | E45: =+SUM(OFFSET('Channel 3_calculations'!$G$6,(ROW($A29)-28)*12,0,12,1)) -> -17085445 | F45: =+SUM(OFFSET('Channel 3_calculations'!$I$6,(ROW($A29)-28)*12,0,12,1)) -> 10251267
A46: =+A45+1 -> 3 | B46: =+SUM(OFFSET('Channel 3_calculations'!$E$6,(ROW($A30)-28)*12,0,12,1)) -> 1.2059418e+08 | C46: =+SUM(OFFSET('Channel 3_calculations'!$F$6,(ROW($A30)-28)*12,0,12,1)) -> -24118836 | D46: =+SUM(OFFSET('Channel 3_calculations'!$H$6,(ROW($A30)-28)*12,0,12,1)) -> -48237672 | E46: =+SUM(OFFSET('Channel 3_calculations'!$G$6,(ROW($A30)-28)*12,0,12,1)) -> -30148545 | F46: =+SUM(OFFSET('Channel 3_calculations'!$I$6,(ROW($A30)-28)*12,0,12,1)) -> 18089127
A47: =+A46+1 -> 4 | B47: =+SUM(OFFSET('Channel 3_calculations'!$E$6,(ROW($A31)-28)*12,0,12,1)) -> 1.8018054e+08 | C47: =+SUM(OFFSET('Channel 3_calculations'!$F$6,(ROW($A31)-28)*12,0,12,1)) -> -36036108 | D47: =+SUM(OFFSET('Channel 3_calculations'!$H$6,(ROW($A31)-28)*12,0,12,1)) -> -72072217 | E47: =+SUM(OFFSET('Channel 3_calculations'!$G$6,(ROW($A31)-28)*12,0,12,1)) -> -45045135 | F47: =+SUM(OFFSET('Channel 3_calculations'!$I$6,(ROW($A31)-28)*12,0,12,1)) -> 27027081
A48: =+A47+1 -> 5 | B48: =+SUM(OFFSET('Channel 3_calculations'!$E$6,(ROW($A32)-28)*12,0,12,1)) -> 2.4793908e+08 | C48: =+SUM(OFFSET('Channel 3_calculations'!$F$6,(ROW($A32)-28)*12,0,12,1)) -> -49587815 | D48: =+SUM(OFFSET('Channel 3_calculations'!$H$6,(ROW($A32)-28)*12,0,12,1)) -> -99175630 | E48: =+SUM(OFFSET('Channel 3_calculations'!$G$6,(ROW($A32)-28)*12,0,12,1)) -> -61984769 | F48: =+SUM(OFFSET('Channel 3_calculations'!$I$6,(ROW($A32)-28)*12,0,12,1)) -> 37190861

Sheet Visuals
A1: Cummulative Net Cashflow | Q1: Revenue Cashflow
A2: Months | B2: Channel 1 | C2: Channel 2 | D2: Channel 3 | E2: Total | Q2: Year | R2: Channel 1 | S2: Channel 2 | T2: Channel 3 | U2: Total_Revenue | V2: Net Profit/loss | W2: Margin
A3: 1 | B3: =+'Channel 1_calculations'!J6 -> -7621200 | C3: =+'Channel 2_calculations'!J6 -> 87750 | D3: =+'Channel 3_calculations'!J6 -> 44010 | E3: =+SUM(B3:D3) -> -7489440 | Q3: 1 | R3: =+SUM(OFFSET('Channel 1_calculations'!$E$6,(ROW(Visuals!Q3)-3)*12,0,12,1)) -> 1.2836767e+08 | S3: =+SUM(OFFSET('Channel 2_calculations'!$E$6,(ROW(Visuals!Q3)-3)*12,0,12,1)) -> 49551773 | T3: =+SUM(OFFSET('Channel 3_calculations'!$E$6,(ROW(Visuals!Q3)-3)*12,0,12,1)) -> 22630712 | U3: =+SUM(R3:T3) -> 2.0055016e+08 | V3: =+Summary!F16 -> -45706736
A4: =+A3+1 -> 2 | B4: =+'Channel 1_calculations'!J7 -> -14588334 | C4: =+'Channel 2_calculations'!J7 -> 258643.12 | D4: =+'Channel 3_calculations'!J7 -> 131809.95 | E4: =+SUM(B4:D4) -> -14197881 | Q4: =+Q3+1 -> 2 | R4: =+SUM(OFFSET('Channel 1_calculations'!$E$6,(ROW(Visuals!Q4)-3)*12,0,12,1)) -> 3.3443681e+08 | S4: =+SUM(OFFSET('Channel 2_calculations'!$E$6,(ROW(Visuals!Q4)-3)*12,0,12,1)) -> 1.3713287e+08 | T4: =+SUM(OFFSET('Channel 3_calculations'!$E$6,(ROW(Visuals!Q4)-3)*12,0,12,1)) -> 68341780 | U4: =+SUM(R4:T4) -> 5.3991146e+08 | V4: =+Summary!F17 -> 34438559
A5: =+A4+1 -> 3 | B5: =+'Channel 1_calculations'!J8 -> -20953727 | C5: =+'Channel 2_calculations'!J8 -> 509353.65 | D5: =+'Channel 3_calculations'!J8 -> 263233.45 | E5: =+SUM(B5:D5) -> -20181140 | Q5: =+Q4+1 -> 3 | R5: =+SUM(OFFSET('Channel 1_calculations'!$E$6,(ROW(Visuals!Q5)-3)*12,0,12,1)) -> 5.4348285e+08 | S5: =+SUM(OFFSET('Channel 2_calculations'!$E$6,(ROW(Visuals!Q5)-3)*12,0,12,1)) -> 2.3238432e+08 | T5: =+SUM(OFFSET('Channel 3_calculations'!$E$6,(ROW(Visuals!Q5)-3)*12,0,12,1)) -> 1.2059418e+08 | U5: =+SUM(R5:T5) -> 8.9646135e+08 | V5: =+Summary!F18 -> 1.1715363e+08
A6: =+A5+1 -> 4 | B6: =+'Channel 1_calculations'!J9 -> -26750476 | C6: =+'Channel 2_calculations'!J9 -> 925436.6 | D6: =+'Channel 3_calculations'!J9 -> 438171.44 | E6: =+SUM(B6:D6) -> -25386868 | Q6: =+Q5+1 -> 4 | R6: =+SUM(OFFSET('Channel 1_calculations'!$E$6,(ROW(Visuals!Q6)-3)*12,0,12,1)) -> 7.6184554e+08 | S6: =+SUM(OFFSET('Channel 2_calculations'!$E$6,(ROW(Visuals!Q6)-3)*12,0,12,1)) -> 3.3648203e+08 | T6: =+SUM(OFFSET('Channel 3_calculations'!$E$6,(ROW(Visuals!Q6)-3)*12,0,12,1)) -> 1.8018054e+08 | U6: =+SUM(R6:T6) -> 1.2785081e+09 | V6: =+Summary!F19 -> 2.0485974e+08
A7: =+A6+1 -> 5 | B7: =+'Channel 1_calculations'!J10 -> -32007011 | C7: =+'Channel 2_calculations'!J10 -> 1334058.3 | D7: =+'Channel 3_calculations'!J10 -> 656523.83 | E7: =+SUM(B7:D7) -> -30016429 | Q7: =+Q6+1 -> 5 | R7: =+SUM(OFFSET('Channel 1_calculations'!$E$6,(ROW(Visuals!Q7)-3)*12,0,12,1)) -> 9.9131902e+08 | S7: =+SUM(OFFSET('Channel 2_calculations'!$E$6,(ROW(Visuals!Q7)-3)*12,0,12,1)) -> 4.5034294e+08 | T7: =+SUM(OFFSET('Channel 3_calculations'!$E$6,(ROW(Visuals!Q7)-3)*12,0,12,1)) -> 2.4793908e+08 | U7: =+SUM(R7:T7) -> 1.689601e+09 | V7: =+Summary!F20 -> 2.9835724e+08 | W7: =+(V7/U7) -> 0.17658443
A8: =+A7+1 -> 6 | B8: =+'Channel 1_calculations'!J11 -> -36747644 | C8: =+'Channel 2_calculations'!J11 -> 1816474.7 | D8: =+'Channel 3_calculations'!J11 -> 918203.8 | E8: =+SUM(B8:D8) -> -34012965
A9: =+A8+1 -> 7 | B9: =+'Channel 1_calculations'!J12 -> -40993009 | C9: =+'Channel 2_calculations'!J12 -> 2371268.9 | D9: =+'Channel 3_calculations'!J12 -> 1223133.4 | E9: =+SUM(B9:D9) -> -37398607
A10: =+A9+1 -> 8 | B10: =+'Channel 1_calculations'!J13 -> -44760442 | C10: =+'Channel 2_calculations'!J13 -> 2997186.4 | D10: =+'Channel 3_calculations'!J13 -> 1571247.6 | E10: =+SUM(B10:D10) -> -40192008
A11: =+A10+1 -> 9 | B11: =+'Channel 1_calculations'!J14 -> -48064280 | C11: =+'Channel 2_calculations'!J14 -> 3693171.7 | D11: =+'Channel 3_calculations'!J14 -> 1962490.5 | E11: =+SUM(B11:D11) -> -42408617
A12: =+A11+1 -> 10 | B12: =+'Channel 1_calculations'!J15 -> -50916113 | C12: =+'Channel 2_calculations'!J15 -> 4458360.2 | D12: =+'Channel 3_calculations'!J15 -> 2396818.8 | E12: =+SUM(B12:D12) -> -44060934
A13: =+A12+1 -> 11 | B13: =+'Channel 1_calculations'!J16 -> -53324981 | C13: =+'Channel 2_calculations'!J16 -> 5292070.8 | D13: =+'Channel 3_calculations'!J16 -> 2874198 | E13: =+SUM(B13:D13) -> -45158712 | R13: =+ROW(Visuals!Q3) -> 3
A14: =+A13+1 -> 12 | B14: =+'Channel 1_calculations'!J17 -> -55295314 | C14: =+'Channel 2_calculations'!J17 -> 6193971.6 | D14: =+'Channel 3_calculations'!J17 -> 3394606.7 | E14: =+SUM(B14:D14) -> -45706736
A15: =+A14+1 -> 13 | B15: =+'Channel 1_calculations'!J18 -> -57308420 | C15: =+'Channel 2_calculations'!J18 -> 7246051.2 | D15: =+'Channel 3_calculations'!J18 -> 3988504.8 | E15: =+SUM(B15:D15) -> -46073864
A16: =+A15+1 -> 14 | B16: =+'Channel 1_calculations'!J19 -> -58835889 | C16: =+'Channel 2_calculations'!J19 -> 8375553.3 | D16: =+'Channel 3_calculations'!J19 -> 4629837.5 | E16: =+SUM(B16:D16) -> -45830498
A17: =+A16+1 -> 15 | B17: =+'Channel 1_calculations'!J20 -> -59884980 | C17: =+'Channel 2_calculations'!J20 -> 9581954.1 | D17: =+'Channel 3_calculations'!J20 -> 5318573.6 | E17: =+SUM(B17:D17) -> -44984453
A18: =+A17+1 -> 16 | B18: =+'Channel 1_calculations'!J21 -> -60461900 | C18: =+'Channel 2_calculations'!J21 -> 10864772 | D18: =+'Channel 3_calculations'!J21 -> 6054684.9 | E18: =+SUM(B18:D18) -> -43542443
A19: =+A18+1 -> 17 | B19: =+'Channel 1_calculations'!J22 -> -60572564 | C19: =+'Channel 2_calculations'!J22 -> 12223542 | D19: =+'Channel 3_calculations'!J22 -> 6838143.6 | E19: =+SUM(B19:D19) -> -41510879
A20: =+A19+1 -> 18 | B20: =+'Channel 1_calculations'!J23 -> -60222628 | C20: =+'Channel 2_calculations'!J23 -> 13657812 | D20: =+'Channel 3_calculations'!J23 -> 7668922.5 | E20: =+SUM(B20:D20) -> -38895893
A21: =+A20+1 -> 19 | B21: =+'Channel 1_calculations'!J24 -> -59417509 | C21: =+'Channel 2_calculations'!J24 -> 15167145 | D21: =+'Channel 3_calculations'!J24 -> 8546995 | E21: =+SUM(B21:D21) -> -35703370
A22: =+A21+1 -> 20 | B22: =+'Channel 1_calculations'!J25 -> -58162411 | C22: =+'Channel 2_calculations'!J25 -> 16751116 | D22: =+'Channel 3_calculations'!J25 -> 9472335.2 | E22: =+SUM(B22:D22) -> -31938960
A23: =+A22+1 -> 21 | B23: =+'Channel 1_calculations'!J26 -> -56462333 | C23: =+'Channel 2_calculations'!J26 -> 18409314 | D23: =+'Channel 3_calculations'!J26 -> 10444918 | E23: =+SUM(B23:D23) -> -27608102
A24: =+A23+1 -> 22 | B24: =+'Channel 1_calculations'!J27 -> -54322092 | C24: =+'Channel 2_calculations'!J27 -> 20141339 | D24: =+'Channel 3_calculations'!J27 -> 11464718 | E24: =+SUM(B24:D24) -> -22716036
A25: =+A24+1 -> 23 | B25: =+'Channel 1_calculations'!J28 -> -51746326 | C25: =+'Channel 2_calculations'!J28 -> 21946804 | D25: =+'Channel 3_calculations'!J28 -> 12531711 | E25: =+SUM(B25:D25) -> -17267812
... A62: =+A61+1 -> 60 | B62: =+'Channel 1_calculations'!J65 -> 3.5087807e+08 | C62: =+'Channel 2_calculations'!J65 -> 1.6227144e+08 | D62: =+'Channel 3_calculations'!J65 -> 95952943 | E62: =+SUM(B62:D62) -> 6.0910244e+08

Sheet Channel 1_calculations
B1: Monthly_premium | C1: =+'Inputs & Assuptions'!$B$2 -> 600 | E1: Commission_rate | F1: 4
B2: Premium_Increase | C2: =+'Inputs & Assuptions'!$B$3 -> 0.05 | E2: Expenses_rate | F2: =+'Inputs & Assuptions'!$B$7 -> 0.25
B3: Gross Claim Ratio | C3: =+'Inputs & Assuptions'!$B$8 -> 0.4
A5: Months | B5: New_sales | C5: Active Policies | D5: Premium | E5: Gross_Premium | F5: Commission | G5: Expenses | H5: Claims | I5: Net Gain/Loss | J5: CummulativeNet Gain/Loss
A6: 1 | B6: =+'Channel 1 Sales'!C6 -> 3480 | C6: {=+TRANSPOSE('Channel 1 Sales'!$F$67:$BM$67)} -> 3480 | D6: =IF(MOD($A6, 12) = 0, $C$1 * 1.05, $C$1) -> 600 | E6: =+C6*D6 -> 2088000 | F6: =-$F$1*B6*D6 -> -8352000 | G6: =-E6*$F$2 -> -522000 | H6: =-E6*$C$3 -> -835200 | I6: =+E6+F6+G6+H6 -> -7621200 | J6: =+I6 -> -7621200
A7: =+A6+1 -> 2 | B7: =+'Channel 1 Sales'!C7 -> 3480 | C7: 6594.6 | D7: =IF(MOD($A7-1, 12) = 0, D6 * 1.05, D6) -> 600 | E7: =+C7*D7 -> 3956760 | F7: =-$F$1*B7*D7 -> -8352000 | G7: =-E7*$F$2 -> -989190 | H7: =-E7*$C$3 -> -1582704 | I7: =+E7+F7+G7+H7 -> -6967134 | J7: =+J6+I7 -> -14588334
A8: =+A7+1 -> 3 | B8: =+'Channel 1 Sales'!C8 -> 3480 | C8: 9460.032 | D8: =IF(MOD($A8-1, 12) = 0, D7 * 1.05, D7) -> 600 | E8: =+C8*D8 -> 5676019.2 | F8: =-$F$1*B8*D8 -> -8352000 | G8: =-E8*$F$2 -> -1419004.8 | H8: =-E8*$C$3 -> -2270407.7 | I8: =+E8+F8+G8+H8 -> -6365393.3 | J8: =+J7+I8 -> -20953727
A9: =+A8+1 -> 4 | B9: =+'Channel 1 Sales'!C9 -> 3480 | C9: 12167.865 | D9: =IF(MOD($A9-1, 12) = 0, D8 * 1.05, D8) -> 600 | E9: =+C9*D9 -> 7300719.1 | F9: =-$F$1*B9*D9 -> -8352000 | G9: =-E9*$F$2 -> -1825179.8 | H9: =-E9*$C$3 -> -2920287.7 | I9: =+E9+F9+G9+H9 -> -5796748.3 | J9: =+J8+I9 -> -26750476
A10: =+A9+1 -> 5 | B10: =+'Channel 1 Sales'!C10 -> 3480 | C10: 14740.307 | D10: =IF(MOD($A10-1, 12) = 0, D9 * 1.05, D9) -> 600 | E10: =+C10*D10 -> 8844184.1 | F10: =-$F$1*B10*D10 -> -8352000 | G10: =-E10*$F$2 -> -2211046 | H10: =-E10*$C$3 -> -3537673.6 | I10: =+E10+F10+G10+H10 -> -5256535.6 | J10: =+J9+I10 -> -32007011
A11: =+A10+1 -> 6 | B11: =+'Channel 1 Sales'!C11 -> 3480 | C11: 17196.989 | D11: =IF(MOD($A11-1, 12) = 0, D10 * 1.05, D10) -> 600 | E11: =+C11*D11 -> 10318193 | F11: =-$F$1*B11*D11 -> -8352000 | G11: =-E11*$F$2 -> -2579548.3 | H11: =-E11*$C$3 -> -4127277.2 | I11: =+E11+F11+G11+H11 -> -4740632.4 | J11: =+J10+I11 -> -36747644
A12: =+A11+1 -> 7 | B12: =+'Channel 1 Sales'!C12 -> 3480 | C12: 19555.403 | D12: =IF(MOD($A12-1, 12) = 0, D11 * 1.05, D11) -> 600 | E12: =+C12*D12 -> 11733242 | F12: =-$F$1*B12*D12 -> -8352000 | G12: =-E12*$F$2 -> -2933310.4 | H12: =-E12*$C$3 -> -4693296.7 | I12: =+E12+F12+G12+H12 -> -4245365.4 | J12: =+J11+I12 -> -40993009
A13: =+A12+1 -> 8 | B13: =+'Channel 1 Sales'!C13 -> 3480 | C13: 21831.273 | D13: =IF(MOD($A13-1, 12) = 0, D12 * 1.05, D12) -> 600 | E13: =+C13*D13 -> 13098764 | F13: =-$F$1*B13*D13 -> -8352000 | G13: =-E13*$F$2 -> -3274690.9 | H13: =-E13*$C$3 -> -5239505.5 | I13: =+E13+F13+G13+H13 -> -3767432.7 | J13: =+J12+I13 -> -44760442
A14: =+A13+1 -> 9 | B14: =+'Channel 1 Sales'!C14 -> 3480 | C14: 24038.867 | D14: =IF(MOD($A14-1, 12) = 0, D13 * 1.05, D13) -> 600 | E14: =+C14*D14 -> 14423320 | F14: =-$F$1*B14*D14 -> -8352000 | G14: =-E14*$F$2 -> -3605830 | H14: =-E14*$C$3 -> -5769328 | I14: =+E14+F14+G14+H14 -> -3303838 | J14: =+J13+I14 -> -48064280
A15: =+A14+1 -> 10 | B15: =+'Channel 1 Sales'!C15 -> 3480 | C15: 26191.271 | D15: =IF(MOD($A15-1, 12) = 0, D14 * 1.05, D14) -> 600 | E15: =+C15*D15 -> 15714762 | F15: =-$F$1*B15*D15 -> -8352000 | G15: =-E15*$F$2 -> -3928690.6 | H15: =-E15*$C$3 -> -6285905 | I15: =+E15+F15+G15+H15 -> -2851833.1 | J15: =+J14+I15 -> -50916113
A16: =+A15+1 -> 11 | B16: =+'Channel 1 Sales'!C16 -> 3480 | C16: 28300.627 | D16: =IF(MOD($A16-1, 12) = 0, D15 * 1.05, D15) -> 600 | E16: =+C16*D16 -> 16980376 | F16: =-$F$1*B16*D16 -> -8352000 | G16: =-E16*$F$2 -> -4245094 | H16: =-E16*$C$3 -> -6792150.4 | I16: =+E16+F16+G16+H16 -> -2408868.4 | J16: =+J15+I16 -> -53324981
A17: =+A16+1 -> 12 | B17: =+'Channel 1 Sales'!C17 -> 3480 | C17: 30388.889 | D17: =IF(MOD($A17-1, 12) = 0, D16 * 1.05, D16) -> 600 | E17: =+C17*D17 -> 18233333 | F17: =-$F$1*B17*D17 -> -8352000 | G17: =-E17*$F$2 -> -4558333.3 | H17: =-E17*$C$3 -> -7293333.4 | I17: =+E17+F17+G17+H17 -> -1970333.3 | J17: =+J16+I17 -> -55295314
A18: =+A17+1 -> 13 | B18: =+'Channel 1 Sales'!C18 -> 3654 | C18: 32630.269 | D18: =IF(MOD($A18-1, 12) = 0, D17 * 1.05, D17) -> 630 | E18: =+C18*D18 -> 20557069 | F18: =-$F$1*B18*D18 -> -9208080 | G18: =-E18*$F$2 -> -5139267.3 | H18: =-E18*$C$3 -> -8222827.7 | I18: =+E18+F18+G18+H18 -> -2013105.7 | J18: =+J17+I18 -> -57308420
... A65: =+A64+1 -> 60 | B65: =+'Channel 1 Sales'!C65 -> 4229.9618 | C65: 122817.69 | D65: =IF(MOD($A65-1, 12) = 0, D64 * 1.05, D64) -> 729.30375 | E65: =+C65*D65 -> 89571403 | F65: =-$F$1*B65*D65 -> -12339708 | G65: =-E65*$F$2 -> -22392851 | H65: =-E65*$C$3 -> -35828561 | I65: =+E65+F65+G65+H65 -> 19010283 | J65: =+J64+I65 -> 3.5087807e+08

Sheet Channel 2_calculations
B1: Monthl_premium | C1: =+'Inputs & Assuptions'!$C$2 -> 600 | E1: Commission_rate | F1: Regressive Tiered | H1: =IF(MOD($A1, 12) = 0, $C$1 * 1.05, $C$1) -> 630
B2: Premium_Increase | C2: =+'Inputs & Assuptions'!$C$3 -> 0.05 | E2: Expenses_rate | F2: =+'Inputs & Assuptions'!$C$7 -> 0.25 | H2: =IF(MOD($A2-1, 12) = 0, H1 * 1.05, H1) -> 630
B3: Gross Claim Ratio | C3: =+'Inputs & Assuptions'!$C$8 -> 0.4
A5: Months | B5: New_sales | C5: Active Policies | D5: Premium | E5: Gross_Premium | F5: Commission | G5: Expenses | H5: Claims | I5: Net Gain/Loss | J5: CummulativeNet Gain/Loss
A6: 1 | B6: =+'Channel 2 Sales'!C6 -> 1170 | C6: {=+TRANSPOSE('Channel 2 Sales'!$F$67:$BM$67)} -> 1170 | D6: =IF(MOD($A6, 12) = 0, $C$1 * 1.05, $C$1) -> 600 | E6: =+C6*D6 -> 702000 | F6: =-((D6*25%)-(MAX(0,(D6-300))*5%)-(MAX(0,(D6-600))*5%)-(MAX(0,(D6-1200))*5%)-(MAX(0,(D6-1500))*5%))*C6 -> -157950 | G6: =-E6*$F$2 -> -175500 | H6: =-E6*$C$3 -> -280800 | I6: =+E6+F6+G6+H6 -> 87750 | J6: =+I6 -> 87750
A7: =+A6+1 -> 2 | B7: =+'Channel 2 Sales'!C7 -> 1170 | C7: 2278.575 | D7: =IF(MOD($A7-1, 12) = 0, D6 * 1.05, D6) -> 600 | E7: =+C7*D7 -> 1367145 | F7: =-((D7*25%)-(MAX(0,(D7-300))*5%)-(MAX(0,(D7-600))*5%)-(MAX(0,(D7-1200))*5%)-(MAX(0,(D7-1500))*5%))*C7 -> -307607.62 | G7: =-E7*$F$2 -> -341786.25 | H7: =-E7*$C$3 -> -546858 | I7: =+E7+F7+G7+H7 -> 170893.12 | J7: =+J6+I7 -> 258643.12
A8: =+A7+1 -> 3 | B8: =+'Channel 2 Sales'!C8 -> 1170 | C8: 3342.807 | D8: =IF(MOD($A8-1, 12) = 0, D7 * 1.05, D7) -> 600 | E8: =+C8*D8 -> 2005684.2 | F8: =-((D8*25%)-(MAX(0,(D8-300))*5%)-(MAX(0,(D8-600))*5%)-(MAX(0,(D8-1200))*5%)-(MAX(0,(D8-1500))*5%))*C8 -> -451278.94 | G8: =-E8*$F$2 -> -501421.05 | H8: =-E8*$C$3 -> -802273.68 | I8: =+E8+F8+G8+H8 -> 250710.52 | J8: =+J7+I8 -> 509353.65
A9: =+A8+1 -> 4 | B9: =+'Channel 2 Sales'!C9 -> 1170 | C9: 5547.7726 | D9: =IF(MOD($A9-1, 12) = 0, D8 * 1.05, D8) -> 600 | E9: =+C9*D9 -> 3328663.6 | F9: =-((D9*25%)-(MAX(0,(D9-300))*5%)-(MAX(0,(D9-600))*5%)-(MAX(0,(D9-1200))*5%)-(MAX(0,(D9-1500))*5%))*C9 -> -748949.3 | G9: =-E9*$F$2 -> -832165.89 | H9: =-E9*$C$3 -> -1331465.4 | I9: =+E9+F9+G9+H9 -> 416082.95 | J9: =+J8+I9 -> 925436.6
A10: =+A9+1 -> 5 | B10: =+'Channel 2 Sales'!C10 -> 1170 | C10: 5448.2891 | D10: =IF(MOD($A10-1, 12) = 0, D9 * 1.05, D9) -> 600 | E10: =+C10*D10 -> 3268973.5 | F10: =-((D10*25%)-(MAX(0,(D10-300))*5%)-(MAX(0,(D10-600))*5%)-(MAX(0,(D10-1200))*5%)-(MAX(0,(D10-1500))*5%))*C10 -> -735519.03 | G10: =-E10*$F$2 -> -817243.36 | H10: =-E10*$C$3 -> -1307589.4 | I10: =+E10+F10+G10+H10 -> 408621.68 | J10: =+J9+I10 -> 1334058.3
A11: =+A10+1 -> 6 | B11: =+'Channel 2 Sales'!C11 -> 1170 | C11: 6432.219 | D11: =IF(MOD($A11-1, 12) = 0, D10 * 1.05, D10) -> 600 | E11: =+C11*D11 -> 3859331.4 | F11: =-((D11*25%)-(MAX(0,(D11-300))*5%)-(MAX(0,(D11-600))*5%)-(MAX(0,(D11-1200))*5%)-(MAX(0,(D11-1500))*5%))*C11 -> -868349.57 | G11: =-E11*$F$2 -> -964832.85 | H11: =-E11*$C$3 -> -1543732.6 | I11: =+E11+F11+G11+H11 -> 482416.43 | J11: =+J10+I11 -> 1816474.7
A12: =+A11+1 -> 7 | B12: =+'Channel 2 Sales'!C12 -> 1170 | C12: 7397.2566 | D12: =IF(MOD($A12-1, 12) = 0, D11 * 1.05, D11) -> 600 | E12: =+C12*D12 -> 4438354 | F12: =-((D12*25%)-(MAX(0,(D12-300))*5%)-(MAX(0,(D12-600))*5%)-(MAX(0,(D12-1200))*5%)-(MAX(0,(D12-1500))*5%))*C12 -> -998629.64 | G12: =-E12*$F$2 -> -1109588.5 | H12: =-E12*$C$3 -> -1775341.6 | I12: =+E12+F12+G12+H12 -> 554794.24 | J12: =+J11+I12 -> 2371268.9
A13: =+A12+1 -> 8 | B13: =+'Channel 2 Sales'!C13 -> 1170 | C13: 8345.5656 | D13: =IF(MOD($A13-1, 12) = 0, D12 * 1.05, D12) -> 600 | E13: =+C13*D13 -> 5007339.3 | F13: =-((D13*25%)-(MAX(0,(D13-300))*5%)-(MAX(0,(D13-600))*5%)-(MAX(0,(D13-1200))*5%)-(MAX(0,(D13-1500))*5%))*C13 -> -1126651.4 | G13: =-E13*$F$2 -> -1251834.8 | H13: =-E13*$C$3 -> -2002935.7 | I13: =+E13+F13+G13+H13 -> 625917.42 | J13: =+J12+I13 -> 2997186.4
A14: =+A13+1 -> 9 | B14: =+'Channel 2 Sales'!C14 -> 1170 | C14: 9279.804 | D14: =IF(MOD($A14-1, 12) = 0, D13 * 1.05, D13) -> 600 | E14: =+C14*D14 -> 5567882.4 | F14: =-((D14*25%)-(MAX(0,(D14-300))*5%)-(MAX(0,(D14-600))*5%)-(MAX(0,(D14-1200))*5%)-(MAX(0,(D14-1500))*5%))*C14 -> -1252773.5 | G14: =-E14*$F$2 -> -1391970.6 | H14: =-E14*$C$3 -> -2227153 | I14: =+E14+F14+G14+H14 -> 695985.3 | J14: =+J13+I14 -> 3693171.7
A15: =+A14+1 -> 10 | B15: =+'Channel 2 Sales'!C15 -> 1170 | C15: 10202.514 | D15: =IF(MOD($A15-1, 12) = 0, D14 * 1.05, D14) -> 600 | E15: =+C15*D15 -> 6121508.2 | F15: =-((D15*25%)-(MAX(0,(D15-300))*5%)-(MAX(0,(D15-600))*5%)-(MAX(0,(D15-1200))*5%)-(MAX(0,(D15-1500))*5%))*C15 -> -1377339.4 | G15: =-E15*$F$2 -> -1530377.1 | H15: =-E15*$C$3 -> -2448603.3 | I15: =+E15+F15+G15+H15 -> 765188.53 | J15: =+J14+I15 -> 4458360.2
A16: =+A15+1 -> 11 | B16: =+'Channel 2 Sales'!C16 -> 1170 | C16: 11116.141 | D16: =IF(MOD($A16-1, 12) = 0, D15 * 1.05, D15) -> 600 | E16: =+C16*D16 -> 6669684.7 | F16: =-((D16*25%)-(MAX(0,(D16-300))*5%)-(MAX(0,(D16-600))*5%)-(MAX(0,(D16-1200))*5%)-(MAX(0,(D16-1500))*5%))*C16 -> -1500679.1 | G16: =-E16*$F$2 -> -1667421.2 | H16: =-E16*$C$3 -> -2667873.9 | I16: =+E16+F16+G16+H16 -> 833710.59 | J16: =+J15+I16 -> 5292070.8
A17: =+A16+1 -> 12 | B17: =+'Channel 2 Sales'!C17 -> 1170 | C17: 12025.344 | D17: =IF(MOD($A17-1, 12) = 0, D16 * 1.05, D16) -> 600 | E17: =+C17*D17 -> 7215206.3 | F17: =-((D17*25%)-(MAX(0,(D17-300))*5%)-(MAX(0,(D17-600))*5%)-(MAX(0,(D17-1200))*5%)-(MAX(0,(D17-1500))*5%))*C17 -> -1623421.4 | G17: =-E17*$F$2 -> -1803801.6 | H17: =-E17*$C$3 -> -2886082.5 | I17: =+E17+F17+G17+H17 -> 901900.78 | J17: =+J16+I17 -> 6193971.6
A18: =+A17+1 -> 13 | B18: =+'Channel 2 Sales'!C18 -> 1228.5 | C18: 12988.638 | D18: =IF(MOD($A18-1, 12) = 0, D17 * 1.05, D17) -> 630 | E18: =+C18*D18 -> 8182841.8 | F18: =-((D18*25%)-(MAX(0,(D18-300))*5%)-(MAX(0,(D18-600))*5%)-(MAX(0,(D18-1200))*5%)-(MAX(0,(D18-1500))*5%))*C18 -> -1811915 | G18: =-E18*$F$2 -> -2045710.5 | H18: =-E18*$C$3 -> -3273136.7 | I18: =+E18+F18+G18+H18 -> 1052079.7 | J18: =+J17+I18 -> 7246051.2
... A65: =+A64+1 -> 60 | B65: =+'Channel 2 Sales'!C65 -> 1422.1423 | C65: 56474.361 | D65: =IF(MOD($A65-1, 12) = 0, D64 * 1.05, D64) -> 729.30375 | E65: =+C65*D65 -> 41186963 | F65: =-((D65*25%)-(MAX(0,(D65-300))*5%)-(MAX(0,(D65-600))*5%)-(MAX(0,(D65-1200))*5%)-(MAX(0,(D65-1500))*5%))*C65 -> -8719390.7 | G65: =-E65*$F$2 -> -10296741 | H65: =-E65*$C$3 -> -16474785 | I65: =+E65+F65+G65+H65 -> 5696046.4 | J65: =+J64+I65 -> 1.6227144e+08

Sheet Channel 3_calculations
B1: Monthl_premium | C1: =+'Inputs & Assuptions'!$D$2 -> 300 | E1: Commission_rate | F1: 0.2
B2: Premium_Increase | C2: =+'Inputs & Assuptions'!$D$3 -> 0.05 | E2: Expenses_rate | F2: =+'Inputs & Assuptions'!$D$7 -> 0.25
B3: Gross Claim Ratio | C3: =+'Inputs & Assuptions'!$D$8 -> 0.4
A5: Months | B5: New_sales | C5: Active Policies | D5: Premium | E5: Gross_Premium | F5: Commission | G5: Expenses | H5: Claims | I5: Net Gain/Loss | J5: CummulativeNet Gain/Loss
A6: 1 | B6: =+'Channel 3 Sales'!C6 -> 978 | C6: {=+TRANSPOSE('Channel 3 Sales'!$F$67:$BM$67)} -> 978 | D6: =IF(MOD($A6, 12) = 0, $C$1 * 1.05, $C$1) -> 300 | E6: =+C6*D6 -> 293400 | F6: =-C6*D6*$F$1 -> -58680 | G6: =-E6*$F$2 -> -73350 | H6: =-E6*$C$3 -> -117360 | I6: =+E6+F6+G6+H6 -> 44010 | J6: =+I6 -> 44010
A7: =+A6+1 -> 2 | B7: =+'Channel 3 Sales'!C7 -> 978 | C7: 1951.11 | D7: =IF(MOD($A7-1, 12) = 0, D6 * 1.05, D6) -> 300 | E7: =+C7*D7 -> 585333 | F7: =-C7*D7*$F$1 -> -117066.6 | G7: =-E7*$F$2 -> -146333.25 | H7: =-E7*$C$3 -> -234133.2 | I7: =+E7+F7+G7+H7 -> 87799.95 | J7: =+J6+I7 -> 131809.95
A8: =+A7+1 -> 3 | B8: =+'Channel 3 Sales'!C8 -> 978 | C8: 2920.5222 | D8: =IF(MOD($A8-1, 12) = 0, D7 * 1.05, D7) -> 300 | E8: =+C8*D8 -> 876156.65 | F8: =-C8*D8*$F$1 -> -175231.33 | G8: =-E8*$F$2 -> -219039.16 | H8: =-E8*$C$3 -> -350462.66 | I8: =+E8+F8+G8+H8 -> 131423.5 | J8: =+J7+I8 -> 263233.45
A9: =+A8+1 -> 4 | B9: =+'Channel 3 Sales'!C9 -> 978 | C9: 3887.5108 | D9: =IF(MOD($A9-1, 12) = 0, D8 * 1.05, D8) -> 300 | E9: =+C9*D9 -> 1166253.3 | F9: =-C9*D9*$F$1 -> -233250.65 | G9: =-E9*$F$2 -> -291563.31 | H9: =-E9*$C$3 -> -466501.3 | I9: =+E9+F9+G9+H9 -> 174937.99 | J9: =+J8+I9 -> 438171.44
A10: =+A9+1 -> 5 | B10: =+'Channel 3 Sales'!C10 -> 978 | C10: 4852.2754 | D10: =IF(MOD($A10-1, 12) = 0, D9 * 1.05, D9) -> 300 | E10: =+C10*D10 -> 1455682.6 | F10: =-C10*D10*$F$1 -> -291136.52 | G10: =-E10*$F$2 -> -363920.66 | H10: =-E10*$C$3 -> -582273.05 | I10: =+E10+F10+G10+H10 -> 218352.39 | J10: =+J9+I10 -> 656523.83
A11: =+A10+1 -> 6 | B11: =+'Channel 3 Sales'!C11 -> 978 | C11: 5815.1105 | D11: =IF(MOD($A11-1, 12) = 0, D10 * 1.05, D10) -> 300 | E11: =+C11*D11 -> 1744533.1 | F11: =-C11*D11*$F$1 -> -348906.63 | G11: =-E11*$F$2 -> -436133.28 | H11: =-E11*$C$3 -> -697813.26 | I11: =+E11+F11+G11+H11 -> 261679.97 | J11: =+J10+I11 -> 918203.8
A12: =+A11+1 -> 7 | B12: =+'Channel 3 Sales'!C12 -> 978 | C12: 6776.2124 | D12: =IF(MOD($A12-1, 12) = 0, D11 * 1.05, D11) -> 300 | E12: =+C12*D12 -> 2032863.7 | F12: =-C12*D12*$F$1 -> -406572.74 | G12: =-E12*$F$2 -> -508215.93 | H12: =-E12*$C$3 -> -813145.49 | I12: =+E12+F12+G12+H12 -> 304929.56 | J12: =+J11+I12 -> 1223133.4
A13: =+A12+1 -> 8 | B13: =+'Channel 3 Sales'!C13 -> 978 | C13: 7735.8727 | D13: =IF(MOD($A13-1, 12) = 0, D12 * 1.05, D12) -> 300 | E13: =+C13*D13 -> 2320761.8 | F13: =-C13*D13*$F$1 -> -464152.36 | G13: =-E13*$F$2 -> -580190.45 | H13: =-E13*$C$3 -> -928304.72 | I13: =+E13+F13+G13+H13 -> 348114.27 | J13: =+J12+I13 -> 1571247.6
A14: =+A13+1 -> 9 | B14: =+'Channel 3 Sales'!C14 -> 978 | C14: 8694.2854 | D14: =IF(MOD($A14-1, 12) = 0, D13 * 1.05, D13) -> 300 | E14: =+C14*D14 -> 2608285.6 | F14: =-C14*D14*$F$1 -> -521657.13 | G14: =-E14*$F$2 -> -652071.41 | H14: =-E14*$C$3 -> -1043314.3 | I14: =+E14+F14+G14+H14 -> 391242.84 | J14: =+J13+I14 -> 1962490.5
A15: =+A14+1 -> 10 | B15: =+'Channel 3 Sales'!C15 -> 978 | C15: 9651.7398 | D15: =IF(MOD($A15-1, 12) = 0, D14 * 1.05, D14) -> 300 | E15: =+C15*D15 -> 2895521.9 | F15: =-C15*D15*$F$1 -> -579104.39 | G15: =-E15*$F$2 -> -723880.48 | H15: =-E15*$C$3 -> -1158208.8 | I15: =+E15+F15+G15+H15 -> 434328.29 | J15: =+J14+I15 -> 2396818.8
A16: =+A15+1 -> 11 | B16: =+'Channel 3 Sales'!C16 -> 978 | C16: 10608.428 | D16: =IF(MOD($A16-1, 12) = 0, D15 * 1.05, D15) -> 300 | E16: =+C16*D16 -> 3182528.4 | F16: =-C16*D16*$F$1 -> -636505.69 | G16: =-E16*$F$2 -> -795632.11 | H16: =-E16*$C$3 -> -1273011.4 | I16: =+E16+F16+G16+H16 -> 477379.26 | J16: =+J15+I16 -> 2874198
A17: =+A16+1 -> 12 | B17: =+'Channel 3 Sales'!C17 -> 978 | C17: 11564.638 | D17: =IF(MOD($A17-1, 12) = 0, D16 * 1.05, D16) -> 300 | E17: =+C17*D17 -> 3469391.4 | F17: =-C17*D17*$F$1 -> -693878.29 | G17: =-E17*$F$2 -> -867347.86 | H17: =-E17*$C$3 -> -1387756.6 | I17: =+E17+F17+G17+H17 -> 520408.72 | J17: =+J16+I17 -> 3394606.7
A18: =+A17+1 -> 13 | B18: =+'Channel 3 Sales'!C18 -> 1026.9 | C18: 12569.27 | D18: =IF(MOD($A18-1, 12) = 0, D17 * 1.05, D17) -> 315 | E18: =+C18*D18 -> 3959320.1 | F18: =-C18*D18*$F$1 -> -791864.01 | G18: =-E18*$F$2 -> -989830.02 | H18: =-E18*$C$3 -> -1583728 | I18: =+E18+F18+G18+H18 -> 593898.01 | J18: =+J17+I18 -> 3988504.8
... A65: =+A64+1 -> 60 | B65: =+'Channel 3 Sales'!C65 -> 1188.7651 | C65: 62930.252 | D65: =IF(MOD($A65-1, 12) = 0, D64 * 1.05, D64) -> 364.65188 | E65: =+C65*D65 -> 22947634 | F65: =-C65*D65*$F$1 -> -4589526.9 | G65: =-E65*$F$2 -> -5736908.6 | H65: =-E65*$C$3 -> -9179053.8 | I65: =+E65+F65+G65+H65 -> 3442145.2 | J65: =+J64+I65 -> 95952943

Sheet Channel 1 Sales
F2: New Sales | G2: =+'Inputs & Assuptions'!$B$4 -> 6000
F3: Sales Increase | G3: =+'Inputs & Assuptions'!$B$5 -> 0.05
B5: NEW_Monthly_Sales_Inc_NTU | C5: NEW_Monthly_Sales_Exc_NTU | E5: Duration | F5: 1 | G5: =+F5+1 -> 2 | H5: =+G5+1 -> 3 | I5: =+H5+1 -> 4 | J5: =+I5+1 -> 5 | K5: =+J5+1 -> 6 | L5: =+K5+1 -> 7 | M5: =+L5+1 -> 8 | N5: =+M5+1 -> 9 | ... BM5: =+BL5+1 -> 60
A6: 1 | B6: =IF(MOD($A6, 12) = 0, $G$2 * 1.05, $G$2) -> 6000 | C6: =$B6*(1-'Inputs & Assuptions'!$B$12) -> 3480 | E6: 1 | F6: =+$C6 -> 3480 | G6: {=IF(COLUMN() - ($E6 + 5) < 0, 0, IF(COLUMN() - ($E6 + 5) = 0, $F6, F6 * (1 - IFERROR(INDEX('Inputs & Assuptions'!$B$13:$B$72, COLUMN() - ($E6 + 5)), 0)) ) )} -> 3114.6 | H6: {=IF(COLUMN() - ($E6 + 5) < 0, 0, IF(COLUMN() - ($E6 + 5) = 0, $F6, G6 * (1 - IFERROR(INDEX('Inputs & Assuptions'!$B$13:$B$72, COLUMN() - ($E6 + 5)), 0)) ) )} -> 2865.432 | I6: {=IF(COLUMN() - ($E6 + 5) < 0, 0, IF(COLUMN() - ($E6 + 5) = 0, $F6, H6 * (1 - IFERROR(INDEX('Inputs & Assuptions'!$B$13:$B$72, COLUMN() - ($E6 + 5)), 0)) ) )} -> 2707.8332 | J6: {=IF(COLUMN() - ($E6 + 5) < 0, 0, IF(COLUMN() - ($E6 + 5) = 0, $F6, I6 * (1 - IFERROR(INDEX('Inputs & Assuptions'!$B$13:$B$72, COLUMN() - ($E6 + 5)), 0)) ) )} -> 2572.4416 | K6: {=IF(COLUMN() - ($E6 + 5) < 0, 0, IF(COLUMN() - ($E6 + 5) = 0, $F6, J6 * (1 - IFERROR(INDEX('Inputs & Assuptions'!$B$13:$B$72, COLUMN() - ($E6 + 5)), 0)) ) )} -> 2456.6817 | L6: {=IF(COLUMN() - ($E6 + 5) < 0, 0, IF(COLUMN() - ($E6 + 5) = 0, $F6, K6 * (1 - IFERROR(INDEX('Inputs & Assuptions'!$B$13:$B$72, COLUMN() - ($E6 + 5)), 0)) ) )} -> 2358.4144 | M6: {=IF(COLUMN() - ($E6 + 5) < 0, 0, IF(COLUMN() - ($E6 + 5) = 0, $F6, L6 * (1 - IFERROR(INDEX('Inputs & Assuptions'!$B$13:$B$72, COLUMN() - ($E6 + 5)), 0)) ) )} -> 2275.8699 | N6: {=IF(COLUMN() - ($E6 + 5) < 0, 0, IF(COLUMN() - ($E6 + 5) = 0, $F6, M6 * (1 - IFERROR(INDEX('Inputs & Assuptions'!$B$13:$B$72, COLUMN() - ($E6 + 5)), 0)) ) )} -> 2207.5938 | ... BM6: {=IF(COLUMN() - ($E6 + 5) < 0, 0, IF(COLUMN() - ($E6 + 5) = 0, $F6, BL6 * (1 - IFERROR(INDEX('Inputs & Assuptions'!$B$13:$B$72, COLUMN() - ($E6 + 5)), 0)) ) )} -> 1289.0638
A7: =A6+1 -> 2 | B7: =IF(MOD($A7-1, 12) = 0, $B6 * 1.05, $B6) -> 6000 | C7: =$B7*(1-'Inputs & Assuptions'!$B$12) -> 3480 | E7: =E6+1 -> 2 | G7: =+$C7 -> 3480 | H7: {=IF(COLUMN() - ($E7 + 5) < 0, 0, IF(COLUMN() - ($E7 + 5) = 0, $F7, G7 * (1 - IFERROR(INDEX('Inputs & Assuptions'!$B$13:$B$72, COLUMN() - ($E7 + 5)), 0)) ) )} -> 3114.6 | I7: {=IF(COLUMN() - ($E7 + 5) < 0, 0, IF(COLUMN() - ($E7 + 5) = 0, $F7, H7 * (1 - IFERROR(INDEX('Inputs & Assuptions'!$B$13:$B$72, COLUMN() - ($E7 + 5)), 0)) ) )} -> 2865.432 | J7: {=IF(COLUMN() - ($E7 + 5) < 0, 0, IF(COLUMN() - ($E7 + 5) = 0, $F7, I7 * (1 - IFERROR(INDEX('Inputs & Assuptions'!$B$13:$B$72, COLUMN() - ($E7 + 5)), 0)) ) )} -> 2707.8332 | K7: {=IF(COLUMN() - ($E7 + 5) < 0, 0, IF(COLUMN() - ($E7 + 5) = 0, $F7, J7 * (1 - IFERROR(INDEX('Inputs & Assuptions'!$B$13:$B$72, COLUMN() - ($E7 + 5)), 0)) ) )} -> 2572.4416 | L7: {=IF(COLUMN() - ($E7 + 5) < 0, 0, IF(COLUMN() - ($E7 + 5) = 0, $F7, K7 * (1 - IFERROR(INDEX('Inputs & Assuptions'!$B$13:$B$72, COLUMN() - ($E7 + 5)), 0)) ) )} -> 2456.6817 | M7: {=IF(COLUMN() - ($E7 + 5) < 0, 0, IF(COLUMN() - ($E7 + 5) = 0, $F7, L7 * (1 - IFERROR(INDEX('Inputs & Assuptions'!$B$13:$B$72, COLUMN() - ($E7 + 5)), 0)) ) )} -> 2358.4144 | N7: {=IF(COLUMN() - ($E7 + 5) < 0, 0, IF(COLUMN() - ($E7 + 5) = 0, $F7, M7 * (1 - IFERROR(INDEX('Inputs & Assuptions'!$B$13:$B$72, COLUMN() - ($E7 + 5)), 0)) ) )} -> 2275.8699 | O7: {=IF(COLUMN() - ($E7 + 5) < 0, 0, IF(COLUMN() - ($E7 + 5) = 0, $F7, N7 * (1 - IFERROR(INDEX('Inputs & Assuptions'!$B$13:$B$72, COLUMN() - ($E7 + 5)), 0)) ) )} -> 2207.5938 | ... BM7: {=IF(COLUMN() - ($E7 + 5) < 0, 0, IF(COLUMN() - ($E7 + 5) = 0, $F7, BL7 * (1 - IFERROR(INDEX('Inputs & Assuptions'!$B$13:$B$72, COLUMN() - ($E7 + 5)), 0)) ) )} -> 1302.0846
A8: =A7+1 -> 3 | B8: =IF(MOD($A8-1, 12) = 0, $B7 * 1.05, $B7) -> 6000 | C8: =$B8*(1-'Inputs & Assuptions'!$B$12) -> 3480 | E8: =E7+1 -> 3 | H8: =+$C8 -> 3480 | I8: {=IF(COLUMN() - ($E8 + 5) < 0, 0, IF(COLUMN() - ($E8 + 5) = 0, $F8, H8 * (1 - IFERROR(INDEX('Inputs & Assuptions'!$B$13:$B$72, COLUMN() - ($E8 + 5)), 0)) ) )} -> 3114.6 | J8: {=IF(COLUMN() - ($E8 + 5) < 0, 0, IF(COLUMN() - ($E8 + 5) = 0, $F8, I8 * (1 - IFERROR(INDEX('Inputs & Assuptions'!$B$13:$B$72, COLUMN() - ($E8 + 5)), 0)) ) )} -> 2865.432 | K8: {=IF(COLUMN() - ($E8 + 5) < 0, 0, IF(COLUMN() - ($E8 + 5) = 0, $F8, J8 * (1 - IFERROR(INDEX('Inputs & Assuptions'!$B$13:$B$72, COLUMN() - ($E8 + 5)), 0)) ) )} -> 2707.8332 | L8: {=IF(COLUMN() - ($E8 + 5) < 0, 0, IF(COLUMN() - ($E8 + 5) = 0, $F8, K8 * (1 - IFERROR(INDEX('Inputs & Assuptions'!$B$13:$B$72, COLUMN() - ($E8 + 5)), 0)) ) )} -> 2572.4416 | M8: {=IF(COLUMN() - ($E8 + 5) < 0, 0, IF(COLUMN() - ($E8 + 5) = 0, $F8, L8 * (1 - IFERROR(INDEX('Inputs & Assuptions'!$B$13:$B$72, COLUMN() - ($E8 + 5)), 0)) ) )} -> 2456.6817 | N8: {=IF(COLUMN() - ($E8 + 5) < 0, 0, IF(COLUMN() - ($E8 + 5) = 0, $F8, M8 * (1 - IFERROR(INDEX('Inputs & Assuptions'!$B$13:$B$72, COLUMN() - ($E8 + 5)), 0)) ) )} -> 2358.4144 | O8: {=IF(COLUMN() - ($E8 + 5) < 0, 0, IF(COLUMN() - ($E8 + 5) = 0, $F8, N8 * (1 - IFERROR(INDEX('Inputs & Assuptions'!$B$13:$B$72, COLUMN() - ($E8 + 5)), 0)) ) )} -> 2275.8699 | P8: {=IF(COLUMN() - ($E8 + 5) < 0, 0, IF(COLUMN() - ($E8 + 5) = 0, $F8, O8 * (1 - IFERROR(INDEX('Inputs & Assuptions'!$B$13:$B$72, COLUMN() - ($E8 + 5)), 0)) ) )} -> 2207.5938 | ... BM8: {=IF(COLUMN() - ($E8 + 5) < 0, 0, IF(COLUMN() - ($E8 + 5) = 0, $F8, BL8 * (1 - IFERROR(INDEX('Inputs & Assuptions'!$B$13:$B$72, COLUMN() - ($E8 + 5)), 0)) ) )} -> 1315.237
A9: =A8+1 -> 4 | B9: =IF(MOD($A9-1, 12) = 0, $B8 * 1.05, $B8) -> 6000 | C9: =$B9*(1-'Inputs & Assuptions'!$B$12) -> 3480 | E9: =E8+1 -> 4 | I9: =+$C9 -> 3480 | J9: {=IF(COLUMN() - ($E9 + 5) < 0, 0, IF(COLUMN() - ($E9 + 5) = 0, $F9, I9 * (1 - IFERROR(INDEX('Inputs & Assuptions'!$B$13:$B$72, COLUMN() - ($E9 + 5)), 0)) ) )} -> 3114.6 | K9: {=IF(COLUMN() - ($E9 + 5) < 0, 0, IF(COLUMN() - ($E9 + 5) = 0, $F9, J9 * (1 - IFERROR(INDEX('Inputs & Assuptions'!$B$13:$B$72, COLUMN() - ($E9 + 5)), 0)) ) )} -> 2865.432 | L9: {=IF(COLUMN() - ($E9 + 5) < 0, 0, IF(COLUMN() - ($E9 + 5) = 0, $F9, K9 * (1 - IFERROR(INDEX('Inputs & Assuptions'!$B$13:$B$72, COLUMN() - ($E9 + 5)), 0)) ) )} -> 2707.8332 | M9: {=IF(COLUMN() - ($E9 + 5) < 0, 0, IF(COLUMN() - ($E9 + 5) = 0, $F9, L9 * (1 - IFERROR(INDEX('Inputs & Assuptions'!$B$13:$B$72, COLUMN() - ($E9 + 5)), 0)) ) )} -> 2572.4416 | N9: {=IF(COLUMN() - ($E9 + 5) < 0, 0, IF(COLUMN() - ($E9 + 5) = 0, $F9, M9 * (1 - IFERROR(INDEX('Inputs & Assuptions'!$B$13:$B$72, COLUMN() - ($E9 + 5)), 0)) ) )} -> 2456.6817 | O9: {=IF(COLUMN() - ($E9 + 5) < 0, 0, IF(COLUMN() - ($E9 + 5) = 0, $F9, N9 * (1 - IFERROR(INDEX('Inputs & Assuptions'!$B$13:$B$72, COLUMN() - ($E9 + 5)), 0)) ) )} -> 2358.4144 | P9: {=IF(COLUMN() - ($E9 + 5) < 0, 0, IF(COLUMN() - ($E9 + 5) = 0, $F9, O9 * (1 - IFERROR(INDEX('Inputs & Assuptions'!$B$13:$B$72, COLUMN() - ($E9 + 5)), 0)) ) )} -> 2275.8699 | Q9: {=IF(COLUMN() - ($E9 + 5) < 0, 0, IF(COLUMN() - ($E9 + 5) = 0, $F9, P9 * (1 - IFERROR(INDEX('Inputs & Assuptions'!$B$13:$B$72, COLUMN() - ($E9 + 5)), 0)) ) )} -> 2207.5938 | ... BM9: {=IF(COLUMN() - ($E9 + 5) < 0, 0, IF(COLUMN() - ($E9 + 5) = 0, $F9, BL9 * (1 - IFERROR(INDEX('Inputs & Assuptions'!$B$13:$B$72, COLUMN() - ($E9 + 5)), 0)) ) )} -> 1328.5222
A10: =A9+1 -> 5 | B10: =IF(MOD($A10-1, 12) = 0, $B9 * 1.05, $B9) -> 6000 | C10: =$B10*(1-'Inputs & Assuptions'!$B$12) -> 3480 | E10: =E9+1 -> 5 | J10: =+$C10 -> 3480 | K10: {=IF(COLUMN() - ($E10 + 5) < 0, 0, IF(COLUMN() - ($E10 + 5) = 0, $F10, J10 * (1 - IFERROR(INDEX('Inputs & Assuptions'!$B$13:$B$72, COLUMN() - ($E10 + 5)), 0)) ) )} -> 3114.6 | L10: {=IF(COLUMN() - ($E10 + 5) < 0, 0, IF(COLUMN() - ($E10 + 5) = 0, $F10, K10 * (1 - IFERROR(INDEX('Inputs & Assuptions'!$B$13:$B$72, COLUMN() - ($E10 + 5)), 0)) ) )} -> 2865.432 | M10: {=IF(COLUMN() - ($E10 + 5) < 0, 0, IF(COLUMN() - ($E10 + 5) = 0, $F10, L10 * (1 - IFERROR(INDEX('Inputs & Assuptions'!$B$13:$B$72, COLUMN() - ($E10 + 5)), 0)) ) )} -> 2707.8332 | N10: {=IF(COLUMN() - ($E10 + 5) < 0, 0, IF(COLUMN() - ($E10 + 5) = 0, $F10, M10 * (1 - IFERROR(INDEX('Inputs & Assuptions'!$B$13:$B$72, COLUMN() - ($E10 + 5)), 0)) ) )} -> 2572.4416 | O10: {=IF(COLUMN() - ($E10 + 5) < 0, 0, IF(COLUMN() - ($E10 + 5) = 0, $F10, N10 * (1 - IFERROR(INDEX('Inputs & Assuptions'!$B$13:$B$72, COLUMN() - ($E10 + 5)), 0)) ) )} -> 2456.6817 | P10: {=IF(COLUMN() - ($E10 + 5) < 0, 0, IF(COLUMN() - ($E10 + 5) = 0, $F10, O10 * (1 - IFERROR(INDEX('Inputs & Assuptions'!$B$13:$B$72, COLUMN() - ($E10 + 5)), 0)) ) )} -> 2358.4144 | Q10: {=IF(COLUMN() - ($E10 + 5) < 0, 0, IF(COLUMN() - ($E10 + 5) = 0, $F10, P10 * (1 - IFERROR(INDEX('Inputs & Assuptions'!$B$13:$B$72, COLUMN() - ($E10 + 5)), 0)) ) )} -> 2275.8699 | R10: {=IF(COLUMN() - ($E10 + 5) < 0, 0, IF(COLUMN() - ($E10 + 5) = 0, $F10, Q10 * (1 - IFERROR(INDEX('Inputs & Assuptions'!$B$13:$B$72, COLUMN() - ($E10 + 5)), 0)) ) )} -> 2207.5938 | ... BM10: {=IF(COLUMN() - ($E10 + 5) < 0, 0, IF(COLUMN() - ($E10 + 5) = 0, $F10, BL10 * (1 - IFERROR(INDEX('Inputs & Assuptions'!$B$13:$B$72, COLUMN() - ($E10 + 5)), 0)) ) )} -> 1341.9416
A11: =A10+1 -> 6 | B11: =IF(MOD($A11-1, 12) = 0, $B10 * 1.05, $B10) -> 6000 | C11: =$B11*(1-'Inputs & Assuptions'!$B$12) -> 3480 | E11: =E10+1 -> 6 | K11: =+$C11 -> 3480 | L11: {=IF(COLUMN() - ($E11 + 5) < 0, 0, IF(COLUMN() - ($E11 + 5) = 0, $F11, K11 * (1 - IFERROR(INDEX('Inputs & Assuptions'!$B$13:$B$72, COLUMN() - ($E11 + 5)), 0)) ) )} -> 3114.6 | M11: {=IF(COLUMN() - ($E11 + 5) < 0, 0, IF(COLUMN() - ($E11 + 5) = 0, $F11, L11 * (1 - IFERROR(INDEX('Inputs & Assuptions'!$B$13:$B$72, COLUMN() - ($E11 + 5)), 0)) ) )} -> 2865.432 | N11: {=IF(COLUMN() - ($E11 + 5) < 0, 0, IF(COLUMN() - ($E11 + 5) = 0, $F11, M11 * (1 - IFERROR(INDEX('Inputs & Assuptions'!$B$13:$B$72, COLUMN() - ($E11 + 5)), 0)) ) )} -> 2707.8332 | O11: {=IF(COLUMN() - ($E11 + 5) < 0, 0, IF(COLUMN() - ($E11 + 5) = 0, $F11, N11 * (1 - IFERROR(INDEX('Inputs & Assuptions'!$B$13:$B$72, COLUMN() - ($E11 + 5)), 0)) ) )} -> 2572.4416 | P11: {=IF(COLUMN() - ($E11 + 5) < 0, 0, IF(COLUMN() - ($E11 + 5) = 0, $F11, O11 * (1 - IFERROR(INDEX('Inputs & Assuptions'!$B$13:$B$72, COLUMN() - ($E11 + 5)), 0)) ) )} -> 2456.6817 | Q11: {=IF(COLUMN() - ($E11 + 5) < 0, 0, IF(COLUMN() - ($E11 + 5) = 0, $F11, P11 * (1 - IFERROR(INDEX('Inputs & Assuptions'!$B$13:$B$72, COLUMN() - ($E11 + 5)), 0)) ) )} -> 2358.4144 | R11: {=IF(COLUMN() - ($E11 + 5) < 0, 0, IF(COLUMN() - ($E11 + 5) = 0, $F11, Q11 * (1 - IFERROR(INDEX('Inputs & Assuptions'!$B$13:$B$72, COLUMN() - ($E11 + 5)), 0)) ) )} -> 2275.8699 | S11: {=IF(COLUMN() - ($E11 + 5) < 0, 0, IF(COLUMN() - ($E11 + 5) = 0, $F11, R11 * (1 - IFERROR(INDEX('Inputs & Assuptions'!$B$13:$B$72, COLUMN() - ($E11 + 5)), 0)) ) )} -> 2207.5938 | ... BM11: {=IF(COLUMN() - ($E11 + 5) < 0, 0, IF(COLUMN() - ($E11 + 5) = 0, $F11, BL11 * (1 - IFERROR(INDEX('Inputs & Assuptions'!$B$13:$B$72, COLUMN() - ($E11 + 5)), 0)) ) )} -> 1355.4966
A12: =A11+1 -> 7 | B12: =IF(MOD($A12-1, 12) = 0, $B11 * 1.05, $B11) -> 6000 | C12: =$B12*(1-'Inputs & Assuptions'!$B$12) -> 3480 | E12: =E11+1 -> 7 | L12: =+$C12 -> 3480 | M12: {=IF(COLUMN() - ($E12 + 5) < 0, 0, IF(COLUMN() - ($E12 + 5) = 0, $F12, L12 * (1 - IFERROR(INDEX('Inputs & Assuptions'!$B$13:$B$72, COLUMN() - ($E12 + 5)), 0)) ) )} -> 3114.6 | N12: {=IF(COLUMN() - ($E12 + 5) < 0, 0, IF(COLUMN() - ($E12 + 5) = 0, $F12, M12 * (1 - IFERROR(INDEX('Inputs & Assuptions'!$B$13:$B$72, COLUMN() - ($E12 + 5)), 0)) ) )} -> 2865.432 | O12: {=IF(COLUMN() - ($E12 + 5) < 0, 0, IF(COLUMN() - ($E12 + 5) = 0, $F12, N12 * (1 - IFERROR(INDEX('Inputs & Assuptions'!$B$13:$B$72, COLUMN() - ($E12 + 5)), 0)) ) )} -> 2707.8332 | P12: {=IF(COLUMN() - ($E12 + 5) < 0, 0, IF(COLUMN() - ($E12 + 5) = 0, $F12, O12 * (1 - IFERROR(INDEX('Inputs & Assuptions'!$B$13:$B$72, COLUMN() - ($E12 + 5)), 0)) ) )} -> 2572.4416 | Q12: {=IF(COLUMN() - ($E12 + 5) < 0, 0, IF(COLUMN() - ($E12 + 5) = 0, $F12, P12 * (1 - IFERROR(INDEX('Inputs & Assuptions'!$B$13:$B$72, COLUMN() - ($E12 + 5)), 0)) ) )} -> 2456.6817 | R12: {=IF(COLUMN() - ($E12 + 5) < 0, 0, IF(COLUMN() - ($E12 + 5) = 0, $F12, Q12 * (1 - IFERROR(INDEX('Inputs & Assuptions'!$B$13:$B$72, COLUMN() - ($E12 + 5)), 0)) ) )} -> 2358.4144 | S12: {=IF(COLUMN() - ($E12 + 5) < 0, 0, IF(COLUMN() - ($E12 + 5) = 0, $F12, R12 * (1 - IFERROR(INDEX('Inputs & Assuptions'!$B$13:$B$72, COLUMN() - ($E12 + 5)), 0)) ) )} -> 2275.8699 | T12: {=IF(COLUMN() - ($E12 + 5) < 0, 0, IF(COLUMN() - ($E12 + 5) = 0, $F12, S12 * (1 - IFERROR(INDEX('Inputs & Assuptions'!$B$13:$B$72, COLUMN() - ($E12 + 5)), 0)) ) )} -> 2207.5938 | ... BM12: {=IF(COLUMN() - ($E12 + 5) < 0, 0, IF(COLUMN() - ($E12 + 5) = 0, $F12, BL12 * (1 - IFERROR(INDEX('Inputs & Assuptions'!$B$13:$B$72, COLUMN() - ($E12 + 5)), 0)) ) )} -> 1369.1885
A13: =A12+1 -> 8 | B13: =IF(MOD($A13-1, 12) = 0, $B12 * 1.05, $B12) -> 6000 | C13: =$B13*(1-'Inputs & Assuptions'!$B$12) -> 3480 | E13: =E12+1 -> 8 | M13: =+$C13 -> 3480 | N13: {=IF(COLUMN() - ($E13 + 5) < 0, 0, IF(COLUMN() - ($E13 + 5) = 0, $F13, M13 * (1 - IFERROR(INDEX('Inputs & Assuptions'!$B$13:$B$72, COLUMN() - ($E13 + 5)), 0)) ) )} -> 3114.6 | O13: {=IF(COLUMN() - ($E13 + 5) < 0, 0, IF(COLUMN() - ($E13 + 5) = 0, $F13, N13 * (1 - IFERROR(INDEX('Inputs & Assuptions'!$B$13:$B$72, COLUMN() - ($E13 + 5)), 0)) ) )} -> 2865.432 | P13: {=IF(COLUMN() - ($E13 + 5) < 0, 0, IF(COLUMN() - ($E13 + 5) = 0, $F13, O13 * (1 - IFERROR(INDEX('Inputs & Assuptions'!$B$13:$B$72, COLUMN() - ($E13 + 5)), 0)) ) )} -> 2707.8332 | Q13: {=IF(COLUMN() - ($E13 + 5) < 0, 0, IF(COLUMN() - ($E13 + 5) = 0, $F13, P13 * (1 - IFERROR(INDEX('Inputs & Assuptions'!$B$13:$B$72, COLUMN() - ($E13 + 5)), 0)) ) )} -> 2572.4416 | R13: {=IF(COLUMN() - ($E13 + 5) < 0, 0, IF(COLUMN() - ($E13 + 5) = 0, $F13, Q13 * (1 - IFERROR(INDEX('Inputs & Assuptions'!$B$13:$B$72, COLUMN() - ($E13 + 5)), 0)) ) )} -> 2456.6817 | S13: {=IF(COLUMN() - ($E13 + 5) < 0, 0, IF(COLUMN() - ($E13 + 5) = 0, $F13, R13 * (1 - IFERROR(INDEX('Inputs & Assuptions'!$B$13:$B$72, COLUMN() - ($E13 + 5)), 0)) ) )} -> 2358.4144 | T13: {=IF(COLUMN() - ($E13 + 5) < 0, 0, IF(COLUMN() - ($E13 + 5) = 0, $F13, S13 * (1 - IFERROR(INDEX('Inputs & Assuptions'!$B$13:$B$72, COLUMN() - ($E13 + 5)), 0)) ) )} -> 2275.8699 | U13: {=IF(COLUMN() - ($E13 + 5) < 0, 0, IF(COLUMN() - ($E13 + 5) = 0, $F13, T13 * (1 - IFERROR(INDEX('Inputs & Assuptions'!$B$13:$B$72, COLUMN() - ($E13 + 5)), 0)) ) )} -> 2207.5938 | ... BM13: {=IF(COLUMN() - ($E13 + 5) < 0, 0, IF(COLUMN() - ($E13 + 5) = 0, $F13, BL13 * (1 - IFERROR(INDEX('Inputs & Assuptions'!$B$13:$B$72, COLUMN() - ($E13 + 5)), 0)) ) )} -> 1383.0187
A14: =A13+1 -> 9 | B14: =IF(MOD($A14-1, 12) = 0, $B13 * 1.05, $B13) -> 6000 | C14: =$B14*(1-'Inputs & Assuptions'!$B$12) -> 3480 | E14: =E13+1 -> 9 | N14: =+$C14 -> 3480 | O14: {=IF(COLUMN() - ($E14 + 5) < 0, 0, IF(COLUMN() - ($E14 + 5) = 0, $F14, N14 * (1 - IFERROR(INDEX('Inputs & Assuptions'!$B$13:$B$72, COLUMN() - ($E14 + 5)), 0)) ) )} -> 3114.6 | P14: {=IF(COLUMN() - ($E14 + 5) < 0, 0, IF(COLUMN() - ($E14 + 5) = 0, $F14, O14 * (1 - IFERROR(INDEX('Inputs & Assuptions'!$B$13:$B$72, COLUMN() - ($E14 + 5)), 0)) ) )} -> 2865.432 | Q14: {=IF(COLUMN() - ($E14 + 5) < 0, 0, IF(COLUMN() - ($E14 + 5) = 0, $F14, P14 * (1 - IFERROR(INDEX('Inputs & Assuptions'!$B$13:$B$72, COLUMN() - ($E14 + 5)), 0)) ) )} -> 2707.8332 | R14: {=IF(COLUMN() - ($E14 + 5) < 0, 0, IF(COLUMN() - ($E14 + 5) = 0, $F14, Q14 * (1 - IFERROR(INDEX('Inputs & Assuptions'!$B$13:$B$72, COLUMN() - ($E14 + 5)), 0)) ) )} -> 2572.4416 | S14: {=IF(COLUMN() - ($E14 + 5) < 0, 0, IF(COLUMN() - ($E14 + 5) = 0, $F14, R14 * (1 - IFERROR(INDEX('Inputs & Assuptions'!$B$13:$B$72, COLUMN() - ($E14 + 5)), 0)) ) )} -> 2456.6817 | T14: {=IF(COLUMN() - ($E14 + 5) < 0, 0, IF(COLUMN() - ($E14 + 5) = 0, $F14, S14 * (1 - IFERROR(INDEX('Inputs & Assuptions'!$B$13:$B$72, COLUMN() - ($E14 + 5)), 0)) ) )} -> 2358.4144 | U14: {=IF(COLUMN() - ($E14 + 5) < 0, 0, IF(COLUMN() - ($E14 + 5) = 0, $F14, T14 * (1 - IFERROR(INDEX('Inputs & Assuptions'!$B$13:$B$72, COLUMN() - ($E14 + 5)), 0)) ) )} -> 2275.8699 | V14: {=IF(COLUMN() - ($E14 + 5) < 0, 0, IF(COLUMN() - ($E14 + 5) = 0, $F14, U14 * (1 - IFERROR(INDEX('Inputs & Assuptions'!$B$13:$B$72, COLUMN() - ($E14 + 5)), 0)) ) )} -> 2207.5938 | ... BM14: {=IF(COLUMN() - ($E14 + 5) < 0, 0, IF(COLUMN() - ($E14 + 5) = 0, $F14, BL14 * (1 - IFERROR(INDEX('Inputs & Assuptions'!$B$13:$B$72, COLUMN() - ($E14 + 5)), 0)) ) )} -> 1396.9885
A15: =A14+1 -> 10 | B15: =IF(MOD($A15-1, 12) = 0, $B14 * 1.05, $B14) -> 6000 | C15: =$B15*(1-'Inputs & Assuptions'!$B$12) -> 3480 | E15: =E14+1 -> 10 | O15: =+$C15 -> 3480 | P15: {=IF(COLUMN() - ($E15 + 5) < 0, 0, IF(COLUMN() - ($E15 + 5) = 0, $F15, O15 * (1 - IFERROR(INDEX('Inputs & Assuptions'!$B$13:$B$72, COLUMN() - ($E15 + 5)), 0)) ) )} -> 3114.6 | Q15: {=IF(COLUMN() - ($E15 + 5) < 0, 0, IF(COLUMN() - ($E15 + 5) = 0, $F15, P15 * (1 - IFERROR(INDEX('Inputs & Assuptions'!$B$13:$B$72, COLUMN() - ($E15 + 5)), 0)) ) )} -> 2865.432 | R15: {=IF(COLUMN() - ($E15 + 5) < 0, 0, IF(COLUMN() - ($E15 + 5) = 0, $F15, Q15 * (1 - IFERROR(INDEX('Inputs & Assuptions'!$B$13:$B$72, COLUMN() - ($E15 + 5)), 0)) ) )} -> 2707.8332 | S15: {=IF(COLUMN() - ($E15 + 5) < 0, 0, IF(COLUMN() - ($E15 + 5) = 0, $F15, R15 * (1 - IFERROR(INDEX('Inputs & Assuptions'!$B$13:$B$72, COLUMN() - ($E15 + 5)), 0)) ) )} -> 2572.4416 | T15: {=IF(COLUMN() - ($E15 + 5) < 0, 0, IF(COLUMN() - ($E15 + 5) = 0, $F15, S15 * (1 - IFERROR(INDEX('Inputs & Assuptions'!$B$13:$B$72, COLUMN() - ($E15 + 5)), 0)) ) )} -> 2456.6817 | U15: {=IF(COLUMN() - ($E15 + 5) < 0, 0, IF(COLUMN() - ($E15 + 5) = 0, $F15, T15 * (1 - IFERROR(INDEX('Inputs & Assuptions'!$B$13:$B$72, COLUMN() - ($E15 + 5)), 0)) ) )} -> 2358.4144 | V15: {=IF(COLUMN() - ($E15 + 5) < 0, 0, IF(COLUMN() - ($E15 + 5) = 0, $F15, U15 * (1 - IFERROR(INDEX('Inputs & Assuptions'!$B$13:$B$72, COLUMN() - ($E15 + 5)), 0)) ) )} -> 2275.8699 | W15: {=IF(COLUMN() - ($E15 + 5) < 0, 0, IF(COLUMN() - ($E15 + 5) = 0, $F15, V15 * (1 - IFERROR(INDEX('Inputs & Assuptions'!$B$13:$B$72, COLUMN() - ($E15 + 5)), 0)) ) )} -> 2207.5938 | ... BM15: {=IF(COLUMN() - ($E15 + 5) < 0, 0, IF(COLUMN() - ($E15 + 5) = 0, $F15, BL15 * (1 - IFERROR(INDEX('Inputs & Assuptions'!$B$13:$B$72, COLUMN() - ($E15 + 5)), 0)) ) )} -> 1411.0995
A16: =A15+1 -> 11 | B16: =IF(MOD($A16-1, 12) = 0, $B15 * 1.05, $B15) -> 6000 | C16: =$B16*(1-'Inputs & Assuptions'!$B$12) -> 3480 | E16: =E15+1 -> 11 | P16: =+$C16 -> 3480 | Q16: {=IF(COLUMN() - ($E16 + 5) < 0, 0, IF(COLUMN() - ($E16 + 5) = 0, $F16, P16 * (1 - IFERROR(INDEX('Inputs & Assuptions'!$B$13:$B$72, COLUMN() - ($E16 + 5)), 0)) ) )} -> 3114.6 | R16: {=IF(COLUMN() - ($E16 + 5) < 0, 0, IF(COLUMN() - ($E16 + 5) = 0, $F16, Q16 * (1 - IFERROR(INDEX('Inputs & Assuptions'!$B$13:$B$72, COLUMN() - ($E16 + 5)), 0)) ) )} -> 2865.432 | S16: {=IF(COLUMN() - ($E16 + 5) < 0, 0, IF(COLUMN() - ($E16 + 5) = 0, $F16, R16 * (1 - IFERROR(INDEX('Inputs & Assuptions'!$B$13:$B$72, COLUMN() - ($E16 + 5)), 0)) ) )} -> 2707.8332 | T16: {=IF(COLUMN() - ($E16 + 5) < 0, 0, IF(COLUMN() - ($E16 + 5) = 0, $F16, S16 * (1 - IFERROR(INDEX('Inputs & Assuptions'!$B$13:$B$72, COLUMN() - ($E16 + 5)), 0)) ) )} -> 2572.4416 | U16: {=IF(COLUMN() - ($E16 + 5) < 0, 0, IF(COLUMN() - ($E16 + 5) = 0, $F16, T16 * (1 - IFERROR(INDEX('Inputs & Assuptions'!$B$13:$B$72, COLUMN() - ($E16 + 5)), 0)) ) )} -> 2456.6817 | V16: {=IF(COLUMN() - ($E16 + 5) < 0, 0, IF(COLUMN() - ($E16 + 5) = 0, $F16, U16 * (1 - IFERROR(INDEX('Inputs & Assuptions'!$B$13:$B$72, COLUMN() - ($E16 + 5)), 0)) ) )} -> 2358.4144 | W16: {=IF(COLUMN() - ($E16 + 5) < 0, 0, IF(COLUMN() - ($E16 + 5) = 0, $F16, V16 * (1 - IFERROR(INDEX('Inputs & Assuptions'!$B$13:$B$72, COLUMN() - ($E16 + 5)), 0)) ) )} -> 2275.8699 | X16: {=IF(COLUMN() - ($E16 + 5) < 0, 0, IF(COLUMN() - ($E16 + 5) = 0, $F16, W16 * (1 - IFERROR(INDEX('Inputs & Assuptions'!$B$13:$B$72, COLUMN() - ($E16 + 5)), 0)) ) )} -> 2207.5938 | ... BM16: {=IF(COLUMN() - ($E16 + 5) < 0, 0, IF(COLUMN() - ($E16 + 5) = 0, $F16, BL16 * (1 - IFERROR(INDEX('Inputs & Assuptions'!$B$13:$B$72, COLUMN() - ($E16 + 5)), 0)) ) )} -> 1425.3531
A17: =A16+1 -> 12 | B17: =IF(MOD($A17-1, 12) = 0, $B16 * 1.05, $B16) -> 6000 | C17: =$B17*(1-'Inputs & Assuptions'!$B$12) -> 3480 | E17: =E16+1 -> 12 | Q17: =+$C17 -> 3480 | R17: {=IF(COLUMN() - ($E17 + 5) < 0, 0, IF(COLUMN() - ($E17 + 5) = 0, $F17, Q17 * (1 - IFERROR(INDEX('Inputs & Assuptions'!$B$13:$B$72, COLUMN() - ($E17 + 5)), 0)) ) )} -> 3114.6 | S17: {=IF(COLUMN() - ($E17 + 5) < 0, 0, IF(COLUMN() - ($E17 + 5) = 0, $F17, R17 * (1 - IFERROR(INDEX('Inputs & Assuptions'!$B$13:$B$72, COLUMN() - ($E17 + 5)), 0)) ) )} -> 2865.432 | T17: {=IF(COLUMN() - ($E17 + 5) < 0, 0, IF(COLUMN() - ($E17 + 5) = 0, $F17, S17 * (1 - IFERROR(INDEX('Inputs & Assuptions'!$B$13:$B$72, COLUMN() - ($E17 + 5)), 0)) ) )} -> 2707.8332 | U17: {=IF(COLUMN() - ($E17 + 5) < 0, 0, IF(COLUMN() - ($E17 + 5) = 0, $F17, T17 * (1 - IFERROR(INDEX('Inputs & Assuptions'!$B$13:$B$72, COLUMN() - ($E17 + 5)), 0)) ) )} -> 2572.4416 | V17: {=IF(COLUMN() - ($E17 + 5) < 0, 0, IF(COLUMN() - ($E17 + 5) = 0, $F17, U17 * (1 - IFERROR(INDEX('Inputs & Assuptions'!$B$13:$B$72, COLUMN() - ($E17 + 5)), 0)) ) )} -> 2456.6817 | W17: {=IF(COLUMN() - ($E17 + 5) < 0, 0, IF(COLUMN() - ($E17 + 5) = 0, $F17, V17 * (1 - IFERROR(INDEX('Inputs & Assuptions'!$B$13:$B$72, COLUMN() - ($E17 + 5)), 0)) ) )} -> 2358.4144 | X17: {=IF(COLUMN() - ($E17 + 5) < 0, 0, IF(COLUMN() - ($E17 + 5) = 0, $F17, W17 * (1 - IFERROR(INDEX('Inputs & Assuptions'!$B$13:$B$72, COLUMN() - ($E17 + 5)), 0)) ) )} -> 2275.8699 | Y17: {=IF(COLUMN() - ($E17 + 5) < 0, 0, IF(COLUMN() - ($E17 + 5) = 0, $F17, X17 * (1 - IFERROR(INDEX('Inputs & Assuptions'!$B$13:$B$72, COLUMN() - ($E17 + 5)), 0)) ) )} -> 2207.5938 | ... BM17: {=IF(COLUMN() - ($E17 + 5) < 0, 0, IF(COLUMN() - ($E17 + 5) = 0, $F17, BL17 * (1 - IFERROR(INDEX('Inputs & Assuptions'!$B$13:$B$72, COLUMN() - ($E17 + 5)), 0)) ) )} -> 1439.7506
A18: =A17+1 -> 13 | B18: =IF(MOD($A18-1, 12) = 0, $B17 * 1.05, $B17) -> 6300 | C18: =$B18*(1-'Inputs & Assuptions'!$B$12) -> 3654 | E18: =E17+1 -> 13 | R18: =+$C18 -> 3654 | S18: {=IF(COLUMN() - ($E18 + 5) < 0, 0, IF(COLUMN() - ($E18 + 5) = 0, $F18, R18 * (1 - IFERROR(INDEX('Inputs & Assuptions'!$B$13:$B$72, COLUMN() - ($E18 + 5)), 0)) ) )} -> 3270.33 | T18: {=IF(COLUMN() - ($E18 + 5) < 0, 0, IF(COLUMN() - ($E18 + 5) = 0, $F18, S18 * (1 - IFERROR(INDEX('Inputs & Assuptions'!$B$13:$B$72, COLUMN() - ($E18 + 5)), 0)) ) )} -> 3008.7036 | U18: {=IF(COLUMN() - ($E18 + 5) < 0, 0, IF(COLUMN() - ($E18 + 5) = 0, $F18, T18 * (1 - IFERROR(INDEX('Inputs & Assuptions'!$B$13:$B$72, COLUMN() - ($E18 + 5)), 0)) ) )} -> 2843.2249 | V18: {=IF(COLUMN() - ($E18 + 5) < 0, 0, IF(COLUMN() - ($E18 + 5) = 0, $F18, U18 * (1 - IFERROR(INDEX('Inputs & Assuptions'!$B$13:$B$72, COLUMN() - ($E18 + 5)), 0)) ) )} -> 2701.0637 | W18: {=IF(COLUMN() - ($E18 + 5) < 0, 0, IF(COLUMN() - ($E18 + 5) = 0, $F18, V18 * (1 - IFERROR(INDEX('Inputs & Assuptions'!$B$13:$B$72, COLUMN() - ($E18 + 5)), 0)) ) )} -> 2579.5158 | X18: {=IF(COLUMN() - ($E18 + 5) < 0, 0, IF(COLUMN() - ($E18 + 5) = 0, $F18, W18 * (1 - IFERROR(INDEX('Inputs & Assuptions'!$B$13:$B$72, COLUMN() - ($E18 + 5)), 0)) ) )} -> 2476.3352 | Y18: {=IF(COLUMN() - ($E18 + 5) < 0, 0, IF(COLUMN() - ($E18 + 5) = 0, $F18, X18 * (1 - IFERROR(INDEX('Inputs & Assuptions'!$B$13:$B$72, COLUMN() - ($E18 + 5)), 0)) ) )} -> 2389.6634 | Z18: {=IF(COLUMN() - ($E18 + 5) < 0, 0, IF(COLUMN() - ($E18 + 5) = 0, $F18, Y18 * (1 - IFERROR(INDEX('Inputs & Assuptions'!$B$13:$B$72, COLUMN() - ($E18 + 5)), 0)) ) )} -> 2317.9735 | ... BM18: {=IF(COLUMN() - ($E18 + 5) < 0, 0, IF(COLUMN() - ($E18 + 5) = 0, $F18, BL18 * (1 - IFERROR(INDEX('Inputs & Assuptions'!$B$13:$B$72, COLUMN() - ($E18 + 5)), 0)) ) )} -> 1527.0082
A19: =A18+1 -> 14 | B19: =IF(MOD($A19-1, 12) = 0, $B18 * 1.05, $B18) -> 6300 | C19: =$B19*(1-'Inputs & Assuptions'!$B$12) -> 3654 | E19: =E18+1 -> 14 | S19: =+$C19 -> 3654 | T19: {=IF(COLUMN() - ($E19 + 5) < 0, 0, IF(COLUMN() - ($E19 + 5) = 0, $F19, S19 * (1 - IFERROR(INDEX('Inputs & Assuptions'!$B$13:$B$72, COLUMN() - ($E19 + 5)), 0)) ) )} -> 3270.33 | U19: {=IF(COLUMN() - ($E19 + 5) < 0, 0, IF(COLUMN() - ($E19 + 5) = 0, $F19, T19 * (1 - IFERROR(INDEX('Inputs & Assuptions'!$B$13:$B$72, COLUMN() - ($E19 + 5)), 0)) ) )} -> 3008.7036 | V19: {=IF(COLUMN() - ($E19 + 5) < 0, 0, IF(COLUMN() - ($E19 + 5) = 0, $F19, U19 * (1 - IFERROR(INDEX('Inputs & Assuptions'!$B$13:$B$72, COLUMN() - ($E19 + 5)), 0)) ) )} -> 2843.2249 | W19: {=IF(COLUMN() - ($E19 + 5) < 0, 0, IF(COLUMN() - ($E19 + 5) = 0, $F19, V19 * (1 - IFERROR(INDEX('Inputs & Assuptions'!$B$13:$B$72, COLUMN() - ($E19 + 5)), 0)) ) )} -> 2701.0637 | X19: {=IF(COLUMN() - ($E19 + 5) < 0, 0, IF(COLUMN() - ($E19 + 5) = 0, $F19, W19 * (1 - IFERROR(INDEX('Inputs & Assuptions'!$B$13:$B$72, COLUMN() - ($E19 + 5)), 0)) ) )} -> 2579.5158 | Y19: {=IF(COLUMN() - ($E19 + 5) < 0, 0, IF(COLUMN() - ($E19 + 5) = 0, $F19, X19 * (1 - IFERROR(INDEX('Inputs & Assuptions'!$B$13:$B$72, COLUMN() - ($E19 + 5)), 0)) ) )} -> 2476.3352 | Z19: {=IF(COLUMN() - ($E19 + 5) < 0, 0, IF(COLUMN() - ($E19 + 5) = 0, $F19, Y19 * (1 - IFERROR(INDEX('Inputs & Assuptions'!$B$13:$B$72, COLUMN() - ($E19 + 5)), 0)) ) )} -> 2389.6634 | AA19: {=IF(COLUMN() - ($E19 + 5) < 0, 0, IF(COLUMN() - ($E19 + 5) = 0, $F19, Z19 * (1 - IFERROR(INDEX('Inputs & Assuptions'!$B$13:$B$72, COLUMN() - ($E19 + 5)), 0)) ) )} -> 2317.9735 | ... BM19: {=IF(COLUMN() - ($E19 + 5) < 0, 0, IF(COLUMN() - ($E19 + 5) = 0, $F19, BL19 * (1 - IFERROR(INDEX('Inputs & Assuptions'!$B$13:$B$72, COLUMN() - ($E19 + 5)), 0)) ) )} -> 1542.4325
A20: =A19+1 -> 15 | B20: =IF(MOD($A20-1, 12) = 0, $B19 * 1.05, $B19) -> 6300 | C20: =$B20*(1-'Inputs & Assuptions'!$B$12) -> 3654 | E20: =E19+1 -> 15 | T20: =+$C20 -> 3654 | U20: {=IF(COLUMN() - ($E20 + 5) < 0, 0, IF(COLUMN() - ($E20 + 5) = 0, $F20, T20 * (1 - IFERROR(INDEX('Inputs & Assuptions'!$B$13:$B$72, COLUMN() - ($E20 + 5)), 0)) ) )} -> 3270.33 | V20: {=IF(COLUMN() - ($E20 + 5) < 0, 0, IF(COLUMN() - ($E20 + 5) = 0, $F20, U20 * (1 - IFERROR(INDEX('Inputs & Assuptions'!$B$13:$B$72, COLUMN() - ($E20 + 5)), 0)) ) )} -> 3008.7036 | W20: {=IF(COLUMN() - ($E20 + 5) < 0, 0, IF(COLUMN() - ($E20 + 5) = 0, $F20, V20 * (1 - IFERROR(INDEX('Inputs & Assuptions'!$B$13:$B$72, COLUMN() - ($E20 + 5)), 0)) ) )} -> 2843.2249 | X20: {=IF(COLUMN() - ($E20 + 5) < 0, 0, IF(COLUMN() - ($E20 + 5) = 0, $F20, W20 * (1 - IFERROR(INDEX('Inputs & Assuptions'!$B$13:$B$72, COLUMN() - ($E20 + 5)), 0)) ) )} -> 2701.0637 | Y20: {=IF(COLUMN() - ($E20 + 5) < 0, 0, IF(COLUMN() - ($E20 + 5) = 0, $F20, X20 * (1 - IFERROR(INDEX('Inputs & Assuptions'!$B$13:$B$72, COLUMN() - ($E20 + 5)), 0)) ) )} -> 2579.5158 | Z20: {=IF(COLUMN() - ($E20 + 5) < 0, 0, IF(COLUMN() - ($E20 + 5) = 0, $F20, Y20 * (1 - IFERROR(INDEX('Inputs & Assuptions'!$B$13:$B$72, COLUMN() - ($E20 + 5)), 0)) ) )} -> 2476.3352 | AA20: {=IF(COLUMN() - ($E20 + 5) < 0, 0, IF(COLUMN() - ($E20 + 5) = 0, $F20, Z20 * (1 - IFERROR(INDEX('Inputs & Assuptions'!$B$13:$B$72, COLUMN() - ($E20 + 5)), 0)) ) )} -> 2389.6634 | AB20: {=IF(COLUMN() - ($E20 + 5) < 0, 0, IF(COLUMN() - ($E20 + 5) = 0, $F20, AA20 * (1 - IFERROR(INDEX('Inputs & Assuptions'!$B$13:$B$72, COLUMN() - ($E20 + 5)), 0)) ) )} -> 2317.9735 | ... BM20: {=IF(COLUMN() - ($E20 + 5) < 0, 0, IF(COLUMN() - ($E20 + 5) = 0, $F20, BL20 * (1 - IFERROR(INDEX('Inputs & Assuptions'!$B$13:$B$72, COLUMN() - ($E20 + 5)), 0)) ) )} -> 1558.0126
A21: =A20+1 -> 16 | B21: =IF(MOD($A21-1, 12) = 0, $B20 * 1.05, $B20) -> 6300 | C21: =$B21*(1-'Inputs & Assuptions'!$B$12) -> 3654 | E21: =E20+1 -> 16 | U21: =+$C21 -> 3654 | V21: {=IF(COLUMN() - ($E21 + 5) < 0, 0, IF(COLUMN() - ($E21 + 5) = 0, $F21, U21 * (1 - IFERROR(INDEX('Inputs & Assuptions'!$B$13:$B$72, COLUMN() - ($E21 + 5)), 0)) ) )} -> 3270.33 | W21: {=IF(COLUMN() - ($E21 + 5) < 0, 0, IF(COLUMN() - ($E21 + 5) = 0, $F21, V21 * (1 - IFERROR(INDEX('Inputs & Assuptions'!$B$13:$B$72, COLUMN() - ($E21 + 5)), 0)) ) )} -> 3008.7036 | X21: {=IF(COLUMN() - ($E21 + 5) < 0, 0, IF(COLUMN() - ($E21 + 5) = 0, $F21, W21 * (1 - IFERROR(INDEX('Inputs & Assuptions'!$B$13:$B$72, COLUMN() - ($E21 + 5)), 0)) ) )} -> 2843.2249 | Y21: {=IF(COLUMN() - ($E21 + 5) < 0, 0, IF(COLUMN() - ($E21 + 5) = 0, $F21, X21 * (1 - IFERROR(INDEX('Inputs & Assuptions'!$B$13:$B$72, COLUMN() - ($E21 + 5)), 0)) ) )} -> 2701.0637 | Z21: {=IF(COLUMN() - ($E21 + 5) < 0, 0, IF(COLUMN() - ($E21 + 5) = 0, $F21, Y21 * (1 - IFERROR(INDEX('Inputs & Assuptions'!$B$13:$B$72, COLUMN() - ($E21 + 5)), 0)) ) )} -> 2579.5158 | AA21: {=IF(COLUMN() - ($E21 + 5) < 0, 0, IF(COLUMN() - ($E21 + 5) = 0, $F21, Z21 * (1 - IFERROR(INDEX('Inputs & Assuptions'!$B$13:$B$72, COLUMN() - ($E21 + 5)), 0)) ) )} -> 2476.3352 | AB21: {=IF(COLUMN() - ($E21 + 5) < 0, 0, IF(COLUMN() - ($E21 + 5) = 0, $F21, AA21 * (1 - IFERROR(INDEX('Inputs & Assuptions'!$B$13:$B$72, COLUMN() - ($E21 + 5)), 0)) ) )} -> 2389.6634 | AC21: {=IF(COLUMN() - ($E21 + 5) < 0, 0, IF(COLUMN() - ($E21 + 5) = 0, $F21, AB21 * (1 - IFERROR(INDEX('Inputs & Assuptions'!$B$13:$B$72, COLUMN() - ($E21 + 5)), 0)) ) )} -> 2317.9735 | ... BM21: {=IF(COLUMN() - ($E21 + 5) < 0, 0, IF(COLUMN() - ($E21 + 5) = 0, $F21, BL21 * (1 - IFERROR(INDEX('Inputs & Assuptions'!$B$13:$B$72, COLUMN() - ($E21 + 5)), 0)) ) )} -> 1573.7501
A22: =A21+1 -> 17 | B22: =IF(MOD($A22-1, 12) = 0, $B21 * 1.05, $B21) -> 6300 | C22: =$B22*(1-'Inputs & Assuptions'!$B$12) -> 3654 | E22: =E21+1 -> 17 | V22: =+$C22 -> 3654 | W22: {=IF(COLUMN() - ($E22 + 5) < 0, 0, IF(COLUMN() - ($E22 + 5) = 0, $F22, V22 * (1 - IFERROR(INDEX('Inputs & Assuptions'!$B$13:$B$72, COLUMN() - ($E22 + 5)), 0)) ) )} -> 3270.33 | X22: {=IF(COLUMN() - ($E22 + 5) < 0, 0, IF(COLUMN() - ($E22 + 5) = 0, $F22, W22 * (1 - IFERROR(INDEX('Inputs & Assuptions'!$B$13:$B$72, COLUMN() - ($E22 + 5)), 0)) ) )} -> 3008.7036 | Y22: {=IF(COLUMN() - ($E22 + 5) < 0, 0, IF(COLUMN() - ($E22 + 5) = 0, $F22, X22 * (1 - IFERROR(INDEX('Inputs & Assuptions'!$B$13:$B$72, COLUMN() - ($E22 + 5)), 0)) ) )} -> 2843.2249 | Z22: {=IF(COLUMN() - ($E22 + 5) < 0, 0, IF(COLUMN() - ($E22 + 5) = 0, $F22, Y22 * (1 - IFERROR(INDEX('Inputs & Assuptions'!$B$13:$B$72, COLUMN() - ($E22 + 5)), 0)) ) )} -> 2701.0637 | AA22: {=IF(COLUMN() - ($E22 + 5) < 0, 0, IF(COLUMN() - ($E22 + 5) = 0, $F22, Z22 * (1 - IFERROR(INDEX('Inputs & Assuptions'!$B$13:$B$72, COLUMN() - ($E22 + 5)), 0)) ) )} -> 2579.5158 | AB22: {=IF(COLUMN() - ($E22 + 5) < 0, 0, IF(COLUMN() - ($E22 + 5) = 0, $F22, AA22 * (1 - IFERROR(INDEX('Inputs & Assuptions'!$B$13:$B$72, COLUMN() - ($E22 + 5)), 0)) ) )} -> 2476.3352 | AC22: {=IF(COLUMN() - ($E22 + 5) < 0, 0, IF(COLUMN() - ($E22 + 5) = 0, $F22, AB22 * (1 - IFERROR(INDEX('Inputs & Assuptions'!$B$13:$B$72, COLUMN() - ($E22 + 5)), 0)) ) )} -> 2389.6634 | AD22: {=IF(COLUMN() - ($E22 + 5) < 0, 0, IF(COLUMN() - ($E22 + 5) = 0, $F22, AC22 * (1 - IFERROR(INDEX('Inputs & Assuptions'!$B$13:$B$72, COLUMN() - ($E22 + 5)), 0)) ) )} -> 2317.9735 | ... BM22: {=IF(COLUMN() - ($E22 + 5) < 0, 0, IF(COLUMN() - ($E22 + 5) = 0, $F22, BL22 * (1 - IFERROR(INDEX('Inputs & Assuptions'!$B$13:$B$72, COLUMN() - ($E22 + 5)), 0)) ) )} -> 1589.6466
A23: =A22+1 -> 18 | B23: =IF(MOD($A23-1, 12) = 0, $B22 * 1.05, $B22) -> 6300 | C23: =$B23*(1-'Inputs & Assuptions'!$B$12) -> 3654 | E23: =E22+1 -> 18 | W23: =+$C23 -> 3654 | X23: {=IF(COLUMN() - ($E23 + 5) < 0, 0, IF(COLUMN() - ($E23 + 5) = 0, $F23, W23 * (1 - IFERROR(INDEX('Inputs & Assuptions'!$B$13:$B$72, COLUMN() - ($E23 + 5)), 0)) ) )} -> 3270.33 | Y23: {=IF(COLUMN() - ($E23 + 5) < 0, 0, IF(COLUMN() - ($E23 + 5) = 0, $F23, X23 * (1 - IFERROR(INDEX('Inputs & Assuptions'!$B$13:$B$72, COLUMN() - ($E23 + 5)), 0)) ) )} -> 3008.7036 | Z23: {=IF(COLUMN() - ($E23 + 5) < 0, 0, IF(COLUMN() - ($E23 + 5) = 0, $F23, Y23 * (1 - IFERROR(INDEX('Inputs & Assuptions'!$B$13:$B$72, COLUMN() - ($E23 + 5)), 0)) ) )} -> 2843.2249 | AA23: {=IF(COLUMN() - ($E23 + 5) < 0, 0, IF(COLUMN() - ($E23 + 5) = 0, $F23, Z23 * (1 - IFERROR(INDEX('Inputs & Assuptions'!$B$13:$B$72, COLUMN() - ($E23 + 5)), 0)) ) )} -> 2701.0637 | AB23: {=IF(COLUMN() - ($E23 + 5) < 0, 0, IF(COLUMN() - ($E23 + 5) = 0, $F23, AA23 * (1 - IFERROR(INDEX('Inputs & Assuptions'!$B$13:$B$72, COLUMN() - ($E23 + 5)), 0)) ) )} -> 2579.5158 | AC23: {=IF(COLUMN() - ($E23 + 5) < 0, 0, IF(COLUMN() - ($E23 + 5) = 0, $F23, AB23 * (1 - IFERROR(INDEX('Inputs & Assuptions'!$B$13:$B$72, COLUMN() - ($E23 + 5)), 0)) ) )} -> 2476.3352 | AD23: {=IF(COLUMN() - ($E23 + 5) < 0, 0, IF(COLUMN() - ($E23 + 5) = 0, $F23, AC23 * (1 - IFERROR(INDEX('Inputs & Assuptions'!$B$13:$B$72, COLUMN() - ($E23 + 5)), 0)) ) )} -> 2389.6634 | AE23: {=IF(COLUMN() - ($E23 + 5) < 0, 0, IF(COLUMN() - ($E23 + 5) = 0, $F23, AD23 * (1 - IFERROR(INDEX('Inputs & Assuptions'!$B$13:$B$72, COLUMN() - ($E23 + 5)), 0)) ) )} -> 2317.9735 | ... BM23: {=IF(COLUMN() - ($E23 + 5) < 0, 0, IF(COLUMN() - ($E23 + 5) = 0, $F23, BL23 * (1 - IFERROR(INDEX('Inputs & Assuptions'!$B$13:$B$72, COLUMN() - ($E23 + 5)), 0)) ) )} -> 1605.7036
A24: =A23+1 -> 19 | B24: =IF(MOD($A24-1, 12) = 0, $B23 * 1.05, $B23) -> 6300 | C24: =$B24*(1-'Inputs & Assuptions'!$B$12) -> 3654 | E24: =E23+1 -> 19 | X24: =+$C24 -> 3654 | Y24: {=IF(COLUMN() - ($E24 + 5) < 0, 0, IF(COLUMN() - ($E24 + 5) = 0, $F24, X24 * (1 - IFERROR(INDEX('Inputs & Assuptions'!$B$13:$B$72, COLUMN() - ($E24 + 5)), 0)) ) )} -> 3270.33 | Z24: {=IF(COLUMN() - ($E24 + 5) < 0, 0, IF(COLUMN() - ($E24 + 5) = 0, $F24, Y24 * (1 - IFERROR(INDEX('Inputs & Assuptions'!$B$13:$B$72, COLUMN() - ($E24 + 5)), 0)) ) )} -> 3008.7036 | AA24: {=IF(COLUMN() - ($E24 + 5) < 0, 0, IF(COLUMN() - ($E24 + 5) = 0, $F24, Z24 * (1 - IFERROR(INDEX('Inputs & Assuptions'!$B$13:$B$72, COLUMN() - ($E24 + 5)), 0)) ) )} -> 2843.2249 | AB24: {=IF(COLUMN() - ($E24 + 5) < 0, 0, IF(COLUMN() - ($E24 + 5) = 0, $F24, AA24 * (1 - IFERROR(INDEX('Inputs & Assuptions'!$B$13:$B$72, COLUMN() - ($E24 + 5)), 0)) ) )} -> 2701.0637 | AC24: {=IF(COLUMN() - ($E24 + 5) < 0, 0, IF(COLUMN() - ($E24 + 5) = 0, $F24, AB24 * (1 - IFERROR(INDEX('Inputs & Assuptions'!$B$13:$B$72, COLUMN() - ($E24 + 5)), 0)) ) )} -> 2579.5158 | AD24: {=IF(COLUMN() - ($E24 + 5) < 0, 0, IF(COLUMN() - ($E24 + 5) = 0, $F24, AC24 * (1 - IFERROR(INDEX('Inputs & Assuptions'!$B$13:$B$72, COLUMN() - ($E24 + 5)), 0)) ) )} -> 2476.3352 | AE24: {=IF(COLUMN() - ($E24 + 5) < 0, 0, IF(COLUMN() - ($E24 + 5) = 0, $F24, AD24 * (1 - IFERROR(INDEX('Inputs & Assuptions'!$B$13:$B$72, COLUMN() - ($E24 + 5)), 0)) ) )} -> 2389.6634 | AF24: {=IF(COLUMN() - ($E24 + 5) < 0, 0, IF(COLUMN() - ($E24 + 5) = 0, $F24, AE24 * (1 - IFERROR(INDEX('Inputs & Assuptions'!$B$13:$B$72, COLUMN() - ($E24 + 5)), 0)) ) )} -> 2317.9735 | ... BM24: {=IF(COLUMN() - ($E24 + 5) < 0, 0, IF(COLUMN() - ($E24 + 5) = 0, $F24, BL24 * (1 - IFERROR(INDEX('Inputs & Assuptions'!$B$13:$B$72, COLUMN() - ($E24 + 5)), 0)) ) )} -> 1621.9229
A25: =A24+1 -> 20 | B25: =IF(MOD($A25-1, 12) = 0, $B24 * 1.05, $B24) -> 6300 | C25: =$B25*(1-'Inputs & Assuptions'!$B$12) -> 3654 | E25: =E24+1 -> 20 | Y25: =+$C25 -> 3654 | Z25: {=IF(COLUMN() - ($E25 + 5) < 0, 0, IF(COLUMN() - ($E25 + 5) = 0, $F25, Y25 * (1 - IFERROR(INDEX('Inputs & Assuptions'!$B$13:$B$72, COLUMN() - ($E25 + 5)), 0)) ) )} -> 3270.33 | AA25: {=IF(COLUMN() - ($E25 + 5) < 0, 0, IF(COLUMN() - ($E25 + 5) = 0, $F25, Z25 * (1 - IFERROR(INDEX('Inputs & Assuptions'!$B$13:$B$72, COLUMN() - ($E25 + 5)), 0)) ) )} -> 3008.7036 | AB25: {=IF(COLUMN() - ($E25 + 5) < 0, 0, IF(COLUMN() - ($E25 + 5) = 0, $F25, AA25 * (1 - IFERROR(INDEX('Inputs & Assuptions'!$B$13:$B$72, COLUMN() - ($E25 + 5)), 0)) ) )} -> 2843.2249 | AC25: {=IF(COLUMN() - ($E25 + 5) < 0, 0, IF(COLUMN() - ($E25 + 5) = 0, $F25, AB25 * (1 - IFERROR(INDEX('Inputs & Assuptions'!$B$13:$B$72, COLUMN() - ($E25 + 5)), 0)) ) )} -> 2701.0637 | AD25: {=IF(COLUMN() - ($E25 + 5) < 0, 0, IF(COLUMN() - ($E25 + 5) = 0, $F25, AC25 * (1 - IFERROR(INDEX('Inputs & Assuptions'!$B$13:$B$72, COLUMN() - ($E25 + 5)), 0)) ) )} -> 2579.5158 | AE25: {=IF(COLUMN() - ($E25 + 5) < 0, 0, IF(COLUMN() - ($E25 + 5) = 0, $F25, AD25 * (1 - IFERROR(INDEX('Inputs & Assuptions'!$B$13:$B$72, COLUMN() - ($E25 + 5)), 0)) ) )} -> 2476.3352 | AF25: {=IF(COLUMN() - ($E25 + 5) < 0, 0, IF(COLUMN() - ($E25 + 5) = 0, $F25, AE25 * (1 - IFERROR(INDEX('Inputs & Assuptions'!$B$13:$B$72, COLUMN() - ($E25 + 5)), 0)) ) )} -> 2389.6634 | AG25: {=IF(COLUMN() - ($E25 + 5) < 0, 0, IF(COLUMN() - ($E25 + 5) = 0, $F25, AF25 * (1 - IFERROR(INDEX('Inputs & Assuptions'!$B$13:$B$72, COLUMN() - ($E25 + 5)), 0)) ) )} -> 2317.9735 | ... BM25: {=IF(COLUMN() - ($E25 + 5) < 0, 0, IF(COLUMN() - ($E25 + 5) = 0, $F25, BL25 * (1 - IFERROR(INDEX('Inputs & Assuptions'!$B$13:$B$72, COLUMN() - ($E25 + 5)), 0)) ) )} -> 1638.3059
A26: =A25+1 -> 21 | B26: =IF(MOD($A26-1, 12) = 0, $B25 * 1.05, $B25) -> 6300 | C26: =$B26*(1-'Inputs & Assuptions'!$B$12) -> 3654 | E26: =E25+1 -> 21 | Z26: =+$C26 -> 3654 | AA26: {=IF(COLUMN() - ($E26 + 5) < 0, 0, IF(COLUMN() - ($E26 + 5) = 0, $F26, Z26 * (1 - IFERROR(INDEX('Inputs & Assuptions'!$B$13:$B$72, COLUMN() - ($E26 + 5)), 0)) ) )} -> 3270.33 | AB26: {=IF(COLUMN() - ($E26 + 5) < 0, 0, IF(COLUMN() - ($E26 + 5) = 0, $F26, AA26 * (1 - IFERROR(INDEX('Inputs & Assuptions'!$B$13:$B$72, COLUMN() - ($E26 + 5)), 0)) ) )} -> 3008.7036 | AC26: {=IF(COLUMN() - ($E26 + 5) < 0, 0, IF(COLUMN() - ($E26 + 5) = 0, $F26, AB26 * (1 - IFERROR(INDEX('Inputs & Assuptions'!$B$13:$B$72, COLUMN() - ($E26 + 5)), 0)) ) )} -> 2843.2249 | AD26: {=IF(COLUMN() - ($E26 + 5) < 0, 0, IF(COLUMN() - ($E26 + 5) = 0, $F26, AC26 * (1 - IFERROR(INDEX('Inputs & Assuptions'!$B$13:$B$72, COLUMN() - ($E26 + 5)), 0)) ) )} -> 2701.0637 | AE26: {=IF(COLUMN() - ($E26 + 5) < 0, 0, IF(COLUMN() - ($E26 + 5) = 0, $F26, AD26 * (1 - IFERROR(INDEX('Inputs & Assuptions'!$B$13:$B$72, COLUMN() - ($E26 + 5)), 0)) ) )} -> 2579.5158 | AF26: {=IF(COLUMN() - ($E26 + 5) < 0, 0, IF(COLUMN() - ($E26 + 5) = 0, $F26, AE26 * (1 - IFERROR(INDEX('Inputs & Assuptions'!$B$13:$B$72, COLUMN() - ($E26 + 5)), 0)) ) )} -> 2476.3352 | AG26: {=IF(COLUMN() - ($E26 + 5) < 0, 0, IF(COLUMN() - ($E26 + 5) = 0, $F26, AF26 * (1 - IFERROR(INDEX('Inputs & Assuptions'!$B$13:$B$72, COLUMN() - ($E26 + 5)), 0)) ) )} -> 2389.6634 | AH26: {=IF(COLUMN() - ($E26 + 5) < 0, 0, IF(COLUMN() - ($E26 + 5) = 0, $F26, AG26 * (1 - IFERROR(INDEX('Inputs & Assuptions'!$B$13:$B$72, COLUMN() - ($E26 + 5)), 0)) ) )} -> 2317.9735 | ... BM26: {=IF(COLUMN() - ($E26 + 5) < 0, 0, IF(COLUMN() - ($E26 + 5) = 0, $F26, BL26 * (1 - IFERROR(INDEX('Inputs & Assuptions'!$B$13:$B$72, COLUMN() - ($E26 + 5)), 0)) ) )} -> 1654.8545
A27: =A26+1 -> 22 | B27: =IF(MOD($A27-1, 12) = 0, $B26 * 1.05, $B26) -> 6300 | C27: =$B27*(1-'Inputs & Assuptions'!$B$12) -> 3654 | E27: =E26+1 -> 22 | AA27: =+$C27 -> 3654 | AB27: {=IF(COLUMN() - ($E27 + 5) < 0, 0, IF(COLUMN() - ($E27 + 5) = 0, $F27, AA27 * (1 - IFERROR(INDEX('Inputs & Assuptions'!$B$13:$B$72, COLUMN() - ($E27 + 5)), 0)) ) )} -> 3270.33 | AC27: {=IF(COLUMN() - ($E27 + 5) < 0, 0, IF(COLUMN() - ($E27 + 5) = 0, $F27, AB27 * (1 - IFERROR(INDEX('Inputs & Assuptions'!$B$13:$B$72, COLUMN() - ($E27 + 5)), 0)) ) )} -> 3008.7036 | AD27: {=IF(COLUMN() - ($E27 + 5) < 0, 0, IF(COLUMN() - ($E27 + 5) = 0, $F27, AC27 * (1 - IFERROR(INDEX('Inputs & Assuptions'!$B$13:$B$72, COLUMN() - ($E27 + 5)), 0)) ) )} -> 2843.2249 | AE27: {=IF(COLUMN() - ($E27 + 5) < 0, 0, IF(COLUMN() - ($E27 + 5) = 0, $F27, AD27 * (1 - IFERROR(INDEX('Inputs & Assuptions'!$B$13:$B$72, COLUMN() - ($E27 + 5)), 0)) ) )} -> 2701.0637 | AF27: {=IF(COLUMN() - ($E27 + 5) < 0, 0, IF(COLUMN() - ($E27 + 5) = 0, $F27, AE27 * (1 - IFERROR(INDEX('Inputs & Assuptions'!$B$13:$B$72, COLUMN() - ($E27 + 5)), 0)) ) )} -> 2579.5158 | AG27: {=IF(COLUMN() - ($E27 + 5) < 0, 0, IF(COLUMN() - ($E27 + 5) = 0, $F27, AF27 * (1 - IFERROR(INDEX('Inputs & Assuptions'!$B$13:$B$72, COLUMN() - ($E27 + 5)), 0)) ) )} -> 2476.3352 | AH27: {=IF(COLUMN() - ($E27 + 5) < 0, 0, IF(COLUMN() - ($E27 + 5) = 0, $F27, AG27 * (1 - IFERROR(INDEX('Inputs & Assuptions'!$B$13:$B$72, COLUMN() - ($E27 + 5)), 0)) ) )} -> 2389.6634 | AI27: {=IF(COLUMN() - ($E27 + 5) < 0, 0, IF(COLUMN() - ($E27 + 5) = 0, $F27, AH27 * (1 - IFERROR(INDEX('Inputs & Assuptions'!$B$13:$B$72, COLUMN() - ($E27 + 5)), 0)) ) )} -> 2317.9735 | ... BM27: {=IF(COLUMN() - ($E27 + 5) < 0, 0, IF(COLUMN() - ($E27 + 5) = 0, $F27, BL27 * (1 - IFERROR(INDEX('Inputs & Assuptions'!$B$13:$B$72, COLUMN() - ($E27 + 5)), 0)) ) )} -> 1671.5702
A28: =A27+1 -> 23 | B28: =IF(MOD($A28-1, 12) = 0, $B27 * 1.05, $B27) -> 6300 | C28: =$B28*(1-'Inputs & Assuptions'!$B$12) -> 3654 | E28: =E27+1 -> 23 | AB28: =+$C28 -> 3654 | AC28: {=IF(COLUMN() - ($E28 + 5) < 0, 0, IF(COLUMN() - ($E28 + 5) = 0, $F28, AB28 * (1 - IFERROR(INDEX('Inputs & Assuptions'!$B$13:$B$72, COLUMN() - ($E28 + 5)), 0)) ) )} -> 3270.33 | AD28: {=IF(COLUMN() - ($E28 + 5) < 0, 0, IF(COLUMN() - ($E28 + 5) = 0, $F28, AC28 * (1 - IFERROR(INDEX('Inputs & Assuptions'!$B$13:$B$72, COLUMN() - ($E28 + 5)), 0)) ) )} -> 3008.7036 | AE28: {=IF(COLUMN() - ($E28 + 5) < 0, 0, IF(COLUMN() - ($E28 + 5) = 0, $F28, AD28 * (1 - IFERROR(INDEX('Inputs & Assuptions'!$B$13:$B$72, COLUMN() - ($E28 + 5)), 0)) ) )} -> 2843.2249 | AF28: {=IF(COLUMN() - ($E28 + 5) < 0, 0, IF(COLUMN() - ($E28 + 5) = 0, $F28, AE28 * (1 - IFERROR(INDEX('Inputs & Assuptions'!$B$13:$B$72, COLUMN() - ($E28 + 5)), 0)) ) )} -> 2701.0637 | AG28: {=IF(COLUMN() - ($E28 + 5) < 0, 0, IF(COLUMN() - ($E28 + 5) = 0, $F28, AF28 * (1 - IFERROR(INDEX('Inputs & Assuptions'!$B$13:$B$72, COLUMN() - ($E28 + 5)), 0)) ) )} -> 2579.5158 | AH28: {=IF(COLUMN() - ($E28 + 5) < 0, 0, IF(COLUMN() - ($E28 + 5) = 0, $F28, AG28 * (1 - IFERROR(INDEX('Inputs & Assuptions'!$B$13:$B$72, COLUMN() - ($E28 + 5)), 0)) ) )} -> 2476.3352 | AI28: {=IF(COLUMN() - ($E28 + 5) < 0, 0, IF(COLUMN() - ($E28 + 5) = 0, $F28, AH28 * (1 - IFERROR(INDEX('Inputs & Assuptions'!$B$13:$B$72, COLUMN() - ($E28 + 5)), 0)) ) )} -> 2389.6634 | AJ28: {=IF(COLUMN() - ($E28 + 5) < 0, 0, IF(COLUMN() - ($E28 + 5) = 0, $F28, AI28 * (1 - IFERROR(INDEX('Inputs & Assuptions'!$B$13:$B$72, COLUMN() - ($E28 + 5)), 0)) ) )} -> 2317.9735 | ... BM28: {=IF(COLUMN() - ($E28 + 5) < 0, 0, IF(COLUMN() - ($E28 + 5) = 0, $F28, BL28 * (1 - IFERROR(INDEX('Inputs & Assuptions'!$B$13:$B$72, COLUMN() - ($E28 + 5)), 0)) ) )} -> 1688.4547
A29: =A28+1 -> 24 | B29: =IF(MOD($A29-1, 12) = 0, $B28 * 1.05, $B28) -> 6300 | C29: =$B29*(1-'Inputs & Assuptions'!$B$12) -> 3654 | E29: =E28+1 -> 24 | AC29: =+$C29 -> 3654 | AD29: {=IF(COLUMN() - ($E29 + 5) < 0, 0, IF(COLUMN() - ($E29 + 5) = 0, $F29, AC29 * (1 - IFERROR(INDEX('Inputs & Assuptions'!$B$13:$B$72, COLUMN() - ($E29 + 5)), 0)) ) )} -> 3270.33 | AE29: {=IF(COLUMN() - ($E29 + 5) < 0, 0, IF(COLUMN() - ($E29 + 5) = 0, $F29, AD29 * (1 - IFERROR(INDEX('Inputs & Assuptions'!$B$13:$B$72, COLUMN() - ($E29 + 5)), 0)) ) )} -> 3008.7036 | AF29: {=IF(COLUMN() - ($E29 + 5) < 0, 0, IF(COLUMN() - ($E29 + 5) = 0, $F29, AE29 * (1 - IFERROR(INDEX('Inputs & Assuptions'!$B$13:$B$72, COLUMN() - ($E29 + 5)), 0)) ) )} -> 2843.2249 | AG29: {=IF(COLUMN() - ($E29 + 5) < 0, 0, IF(COLUMN() - ($E29 + 5) = 0, $F29, AF29 * (1 - IFERROR(INDEX('Inputs & Assuptions'!$B$13:$B$72, COLUMN() - ($E29 + 5)), 0)) ) )} -> 2701.0637 | AH29: {=IF(COLUMN() - ($E29 + 5) < 0, 0, IF(COLUMN() - ($E29 + 5) = 0, $F29, AG29 * (1 - IFERROR(INDEX('Inputs & Assuptions'!$B$13:$B$72, COLUMN() - ($E29 + 5)), 0)) ) )} -> 2579.5158 | AI29: {=IF(COLUMN() - ($E29 + 5) < 0, 0, IF(COLUMN() - ($E29 + 5) = 0, $F29, AH29 * (1 - IFERROR(INDEX('Inputs & Assuptions'!$B$13:$B$72, COLUMN() - ($E29 + 5)), 0)) ) )} -> 2476.3352 | AJ29: {=IF(COLUMN() - ($E29 + 5) < 0, 0, IF(COLUMN() - ($E29 + 5) = 0, $F29, AI29 * (1 - IFERROR(INDEX('Inputs & Assuptions'!$B$13:$B$72, COLUMN() - ($E29 + 5)), 0)) ) )} -> 2389.6634 | AK29: {=IF(COLUMN() - ($E29 + 5) < 0, 0, IF(COLUMN() - ($E29 + 5) = 0, $F29, AJ29 * (1 - IFERROR(INDEX('Inputs & Assuptions'!$B$13:$B$72, COLUMN() - ($E29 + 5)), 0)) ) )} -> 2317.9735 | ... BM29: {=IF(COLUMN() - ($E29 + 5) < 0, 0, IF(COLUMN() - ($E29 + 5) = 0, $F29, BL29 * (1 - IFERROR(INDEX('Inputs & Assuptions'!$B$13:$B$72, COLUMN() - ($E29 + 5)), 0)) ) )} -> 1705.5098
A30: =A29+1 -> 25 | B30: =IF(MOD($A30-1, 12) = 0, $B29 * 1.05, $B29) -> 6615 | C30: =$B30*(1-'Inputs & Assuptions'!$B$12) -> 3836.7 | E30: =E29+1 -> 25 | AD30: =+$C30 -> 3836.7 | AE30: {=IF(COLUMN() - ($E30 + 5) < 0, 0, IF(COLUMN() - ($E30 + 5) = 0, $F30, AD30 * (1 - IFERROR(INDEX('Inputs & Assuptions'!$B$13:$B$72, COLUMN() - ($E30 + 5)), 0)) ) )} -> 3433.8465 | AF30: {=IF(COLUMN() - ($E30 + 5) < 0, 0, IF(COLUMN() - ($E30 + 5) = 0, $F30, AE30 * (1 - IFERROR(INDEX('Inputs & Assuptions'!$B$13:$B$72, COLUMN() - ($E30 + 5)), 0)) ) )} -> 3159.1388 | AG30: {=IF(COLUMN() - ($E30 + 5) < 0, 0, IF(COLUMN() - ($E30 + 5) = 0, $F30, AF30 * (1 - IFERROR(INDEX('Inputs & Assuptions'!$B$13:$B$72, COLUMN() - ($E30 + 5)), 0)) ) )} -> 2985.3861 | AH30: {=IF(COLUMN() - ($E30 + 5) < 0, 0, IF(COLUMN() - ($E30 + 5) = 0, $F30, AG30 * (1 - IFERROR(INDEX('Inputs & Assuptions'!$B$13:$B$72, COLUMN() - ($E30 + 5)), 0)) ) )} -> 2836.1168 | AI30: {=IF(COLUMN() - ($E30 + 5) < 0, 0, IF(COLUMN() - ($E30 + 5) = 0, $F30, AH30 * (1 - IFERROR(INDEX('Inputs & Assuptions'!$B$13:$B$72, COLUMN() - ($E30 + 5)), 0)) ) )} -> 2708.4916 | AJ30: {=IF(COLUMN() - ($E30 + 5) < 0, 0, IF(COLUMN() - ($E30 + 5) = 0, $F30, AI30 * (1 - IFERROR(INDEX('Inputs & Assuptions'!$B$13:$B$72, COLUMN() - ($E30 + 5)), 0)) ) )} -> 2600.1519 | AK30: {=IF(COLUMN() - ($E30 + 5) < 0, 0, IF(COLUMN() - ($E30 + 5) = 0, $F30, AJ30 * (1 - IFERROR(INDEX('Inputs & Assuptions'!$B$13:$B$72, COLUMN() - ($E30 + 5)), 0)) ) )} -> 2509.1466 | AL30: {=IF(COLUMN() - ($E30 + 5) < 0, 0, IF(COLUMN() - ($E30 + 5) = 0, $F30, AK30 * (1 - IFERROR(INDEX('Inputs & Assuptions'!$B$13:$B$72, COLUMN() - ($E30 + 5)), 0)) ) )} -> 2433.8722 | ... BM30: {=IF(COLUMN() - ($E30 + 5) < 0, 0, IF(COLUMN() - ($E30 + 5) = 0, $F30, BL30 * (1 - IFERROR(INDEX('Inputs & Assuptions'!$B$13:$B$72, COLUMN() - ($E30 + 5)), 0)) ) )} -> 1808.874
A31: =A30+1 -> 26 | B31: =IF(MOD($A31-1, 12) = 0, $B30 * 1.05, $B30) -> 6615 | C31: =$B31*(1-'Inputs & Assuptions'!$B$12) -> 3836.7 | E31: =E30+1 -> 26 | AE31: =+$C31 -> 3836.7 | AF31: {=IF(COLUMN() - ($E31 + 5) < 0, 0, IF(COLUMN() - ($E31 + 5) = 0, $F31, AE31 * (1 - IFERROR(INDEX('Inputs & Assuptions'!$B$13:$B$72, COLUMN() - ($E31 + 5)), 0)) ) )} -> 3433.8465 | AG31: {=IF(COLUMN() - ($E31 + 5) < 0, 0, IF(COLUMN() - ($E31 + 5) = 0, $F31, AF31 * (1 - IFERROR(INDEX('Inputs & Assuptions'!$B$13:$B$72, COLUMN() - ($E31 + 5)), 0)) ) )} -> 3159.1388 | AH31: {=IF(COLUMN() - ($E31 + 5) < 0, 0, IF(COLUMN() - ($E31 + 5) = 0, $F31, AG31 * (1 - IFERROR(INDEX('Inputs & Assuptions'!$B$13:$B$72, COLUMN() - ($E31 + 5)), 0)) ) )} -> 2985.3861 | AI31: {=IF(COLUMN() - ($E31 + 5) < 0, 0, IF(COLUMN() - ($E31 + 5) = 0, $F31, AH31 * (1 - IFERROR(INDEX('Inputs & Assuptions'!$B$13:$B$72, COLUMN() - ($E31 + 5)), 0)) ) )} -> 2836.1168 | AJ31: {=IF(COLUMN() - ($E31 + 5) < 0, 0, IF(COLUMN() - ($E31 + 5) = 0, $F31, AI31 * (1 - IFERROR(INDEX('Inputs & Assuptions'!$B$13:$B$72, COLUMN() - ($E31 + 5)), 0)) ) )} -> 2708.4916 | AK31: {=IF(COLUMN() - ($E31 + 5) < 0, 0, IF(COLUMN() - ($E31 + 5) = 0, $F31, AJ31 * (1 - IFERROR(INDEX('Inputs & Assuptions'!$B$13:$B$72, COLUMN() - ($E31 + 5)), 0)) ) )} -> 2600.1519 | AL31: {=IF(COLUMN() - ($E31 + 5) < 0, 0, IF(COLUMN() - ($E31 + 5) = 0, $F31, AK31 * (1 - IFERROR(INDEX('Inputs & Assuptions'!$B$13:$B$72, COLUMN() - ($E31 + 5)), 0)) ) )} -> 2509.1466 | AM31: {=IF(COLUMN() - ($E31 + 5) < 0, 0, IF(COLUMN() - ($E31 + 5) = 0, $F31, AL31 * (1 - IFERROR(INDEX('Inputs & Assuptions'!$B$13:$B$72, COLUMN() - ($E31 + 5)), 0)) ) )} -> 2433.8722 | ... BM31: {=IF(COLUMN() - ($E31 + 5) < 0, 0, IF(COLUMN() - ($E31 + 5) = 0, $F31, BL31 * (1 - IFERROR(INDEX('Inputs & Assuptions'!$B$13:$B$72, COLUMN() - ($E31 + 5)), 0)) ) )} -> 1827.1455
A32: =A31+1 -> 27 | B32: =IF(MOD($A32-1, 12) = 0, $B31 * 1.05, $B31) -> 6615 | C32: =$B32*(1-'Inputs & Assuptions'!$B$12) -> 3836.7 | E32: =E31+1 -> 27 | AF32: =+$C32 -> 3836.7 | AG32: {=IF(COLUMN() - ($E32 + 5) < 0, 0, IF(COLUMN() - ($E32 + 5) = 0, $F32, AF32 * (1 - IFERROR(INDEX('Inputs & Assuptions'!$B$13:$B$72, COLUMN() - ($E32 + 5)), 0)) ) )} -> 3433.8465 | AH32: {=IF(COLUMN() - ($E32 + 5) < 0, 0, IF(COLUMN() - ($E32 + 5) = 0, $F32, AG32 * (1 - IFERROR(INDEX('Inputs & Assuptions'!$B$13:$B$72, COLUMN() - ($E32 + 5)), 0)) ) )} -> 3159.1388 | AI32: {=IF(COLUMN() - ($E32 + 5) < 0, 0, IF(COLUMN() - ($E32 + 5) = 0, $F32, AH32 * (1 - IFERROR(INDEX('Inputs & Assuptions'!$B$13:$B$72, COLUMN() - ($E32 + 5)), 0)) ) )} -> 2985.3861 | AJ32: {=IF(COLUMN() - ($E32 + 5) < 0, 0, IF(COLUMN() - ($E32 + 5) = 0, $F32, AI32 * (1 - IFERROR(INDEX('Inputs & Assuptions'!$B$13:$B$72, COLUMN() - ($E32 + 5)), 0)) ) )} -> 2836.1168 | AK32: {=IF(COLUMN() - ($E32 + 5) < 0, 0, IF(COLUMN() - ($E32 + 5) = 0, $F32, AJ32 * (1 - IFERROR(INDEX('Inputs & Assuptions'!$B$13:$B$72, COLUMN() - ($E32 + 5)), 0)) ) )} -> 2708.4916 | AL32: {=IF(COLUMN() - ($E32 + 5) < 0, 0, IF(COLUMN() - ($E32 + 5) = 0, $F32, AK32 * (1 - IFERROR(INDEX('Inputs & Assuptions'!$B$13:$B$72, COLUMN() - ($E32 + 5)), 0)) ) )} -> 2600.1519 | AM32: {=IF(COLUMN() - ($E32 + 5) < 0, 0, IF(COLUMN() - ($E32 + 5) = 0, $F32, AL32 * (1 - IFERROR(INDEX('Inputs & Assuptions'!$B$13:$B$72, COLUMN() - ($E32 + 5)), 0)) ) )} -> 2509.1466 | AN32: {=IF(COLUMN() - ($E32 + 5) < 0, 0, IF(COLUMN() - ($E32 + 5) = 0, $F32, AM32 * (1 - IFERROR(INDEX('Inputs & Assuptions'!$B$13:$B$72, COLUMN() - ($E32 + 5)), 0)) ) )} -> 2433.8722 | ... BM32: {=IF(COLUMN() - ($E32 + 5) < 0, 0, IF(COLUMN() - ($E32 + 5) = 0, $F32, BL32 * (1 - IFERROR(INDEX('Inputs & Assuptions'!$B$13:$B$72, COLUMN() - ($E32 + 5)), 0)) ) )} -> 1845.6015
A33: =A32+1 -> 28 | B33: =IF(MOD($A33-1, 12) = 0, $B32 * 1.05, $B32) -> 6615 | C33: =$B33*(1-'Inputs & Assuptions'!$B$12) -> 3836.7 | E33: =E32+1 -> 28 | AG33: =+$C33 -> 3836.7 | AH33: {=IF(COLUMN() - ($E33 + 5) < 0, 0, IF(COLUMN() - ($E33 + 5) = 0, $F33, AG33 * (1 - IFERROR(INDEX('Inputs & Assuptions'!$B$13:$B$72, COLUMN() - ($E33 + 5)), 0)) ) )} -> 3433.8465 | AI33: {=IF(COLUMN() - ($E33 + 5) < 0, 0, IF(COLUMN() - ($E33 + 5) = 0, $F33, AH33 * (1 - IFERROR(INDEX('Inputs & Assuptions'!$B$13:$B$72, COLUMN() - ($E33 + 5)), 0)) ) )} -> 3159.1388 | AJ33: {=IF(COLUMN() - ($E33 + 5) < 0, 0, IF(COLUMN() - ($E33 + 5) = 0, $F33, AI33 * (1 - IFERROR(INDEX('Inputs & Assuptions'!$B$13:$B$72, COLUMN() - ($E33 + 5)), 0)) ) )} -> 2985.3861 | AK33: {=IF(COLUMN() - ($E33 + 5) < 0, 0, IF(COLUMN() - ($E33 + 5) = 0, $F33, AJ33 * (1 - IFERROR(INDEX('Inputs & Assuptions'!$B$13:$B$72, COLUMN() - ($E33 + 5)), 0)) ) )} -> 2836.1168 | AL33: {=IF(COLUMN() - ($E33 + 5) < 0, 0, IF(COLUMN() - ($E33 + 5) = 0, $F33, AK33 * (1 - IFERROR(INDEX('Inputs & Assuptions'!$B$13:$B$72, COLUMN() - ($E33 + 5)), 0)) ) )} -> 2708.4916 | AM33: {=IF(COLUMN() - ($E33 + 5) < 0, 0, IF(COLUMN() - ($E33 + 5) = 0, $F33, AL33 * (1 - IFERROR(INDEX('Inputs & Assuptions'!$B$13:$B$72, COLUMN() - ($E33 + 5)), 0)) ) )} -> 2600.1519 | AN33: {=IF(COLUMN() - ($E33 + 5) < 0, 0, IF(COLUMN() - ($E33 + 5) = 0, $F33, AM33 * (1 - IFERROR(INDEX('Inputs & Assuptions'!$B$13:$B$72, COLUMN() - ($E33 + 5)), 0)) ) )} -> 2509.1466 | AO33: {=IF(COLUMN() - ($E33 + 5) < 0, 0, IF(COLUMN() - ($E33 + 5) = 0, $F33, AN33 * (1 - IFERROR(INDEX('Inputs & Assuptions'!$B$13:$B$72, COLUMN() - ($E33 + 5)), 0)) ) )} -> 2433.8722 | ... BM33: {=IF(COLUMN() - ($E33 + 5) < 0, 0, IF(COLUMN() - ($E33 + 5) = 0, $F33, BL33 * (1 - IFERROR(INDEX('Inputs & Assuptions'!$B$13:$B$72, COLUMN() - ($E33 + 5)), 0)) ) )} -> 1864.244
A34: =A33+1 -> 29 | B34: =IF(MOD($A34-1, 12) = 0, $B33 * 1.05, $B33) -> 6615 | C34: =$B34*(1-'Inputs & Assuptions'!$B$12) -> 3836.7 | E34: =E33+1 -> 29 | AH34: =+$C34 -> 3836.7 | AI34: {=IF(COLUMN() - ($E34 + 5) < 0, 0, IF(COLUMN() - ($E34 + 5) = 0, $F34, AH34 * (1 - IFERROR(INDEX('Inputs & Assuptions'!$B$13:$B$72, COLUMN() - ($E34 + 5)), 0)) ) )} -> 3433.8465 | AJ34: {=IF(COLUMN() - ($E34 + 5) < 0, 0, IF(COLUMN() - ($E34 + 5) = 0, $F34, AI34 * (1 - IFERROR(INDEX('Inputs & Assuptions'!$B$13:$B$72, COLUMN() - ($E34 + 5)), 0)) ) )} -> 3159.1388 | AK34: {=IF(COLUMN() - ($E34 + 5) < 0, 0, IF(COLUMN() - ($E34 + 5) = 0, $F34, AJ34 * (1 - IFERROR(INDEX('Inputs & Assuptions'!$B$13:$B$72, COLUMN() - ($E34 + 5)), 0)) ) )} -> 2985.3861 | AL34: {=IF(COLUMN() - ($E34 + 5) < 0, 0, IF(COLUMN() - ($E34 + 5) = 0, $F34, AK34 * (1 - IFERROR(INDEX('Inputs & Assuptions'!$B$13:$B$72, COLUMN() - ($E34 + 5)), 0)) ) )} -> 2836.1168 | AM34: {=IF(COLUMN() - ($E34 + 5) < 0, 0, IF(COLUMN() - ($E34 + 5) = 0, $F34, AL34 * (1 - IFERROR(INDEX('Inputs & Assuptions'!$B$13:$B$72, COLUMN() - ($E34 + 5)), 0)) ) )} -> 2708.4916 | AN34: {=IF(COLUMN() - ($E34 + 5) < 0, 0, IF(COLUMN() - ($E34 + 5) = 0, $F34, AM34 * (1 - IFERROR(INDEX('Inputs & Assuptions'!$B$13:$B$72, COLUMN() - ($E34 + 5)), 0)) ) )} -> 2600.1519 | AO34: {=IF(COLUMN() - ($E34 + 5) < 0, 0, IF(COLUMN() - ($E34 + 5) = 0, $F34, AN34 * (1 - IFERROR(INDEX('Inputs & Assuptions'!$B$13:$B$72, COLUMN() - ($E34 + 5)), 0)) ) )} -> 2509.1466 | AP34: {=IF(COLUMN() - ($E34 + 5) < 0, 0, IF(COLUMN() - ($E34 + 5) = 0, $F34, AO34 * (1 - IFERROR(INDEX('Inputs & Assuptions'!$B$13:$B$72, COLUMN() - ($E34 + 5)), 0)) ) )} -> 2433.8722 | ... BM34: {=IF(COLUMN() - ($E34 + 5) < 0, 0, IF(COLUMN() - ($E34 + 5) = 0, $F34, BL34 * (1 - IFERROR(INDEX('Inputs & Assuptions'!$B$13:$B$72, COLUMN() - ($E34 + 5)), 0)) ) )} -> 1883.0747
A35: =A34+1 -> 30 | B35: =IF(MOD($A35-1, 12) = 0, $B34 * 1.05, $B34) -> 6615 | C35: =$B35*(1-'Inputs & Assuptions'!$B$12) -> 3836.7 | E35: =E34+1 -> 30 | AI35: =+$C35 -> 3836.7 | AJ35: {=IF(COLUMN() - ($E35 + 5) < 0, 0, IF(COLUMN() - ($E35 + 5) = 0, $F35, AI35 * (1 - IFERROR(INDEX('Inputs & Assuptions'!$B$13:$B$72, COLUMN() - ($E35 + 5)), 0)) ) )} -> 3433.8465 | AK35: {=IF(COLUMN() - ($E35 + 5) < 0, 0, IF(COLUMN() - ($E35 + 5) = 0, $F35, AJ35 * (1 - IFERROR(INDEX('Inputs & Assuptions'!$B$13:$B$72, COLUMN() - ($E35 + 5)), 0)) ) )} -> 3159.1388 | AL35: {=IF(COLUMN() - ($E35 + 5) < 0, 0, IF(COLUMN() - ($E35 + 5) = 0, $F35, AK35 * (1 - IFERROR(INDEX('Inputs & Assuptions'!$B$13:$B$72, COLUMN() - ($E35 + 5)), 0)) ) )} -> 2985.3861 | AM35: {=IF(COLUMN() - ($E35 + 5) < 0, 0, IF(COLUMN() - ($E35 + 5) = 0, $F35, AL35 * (1 - IFERROR(INDEX('Inputs & Assuptions'!$B$13:$B$72, COLUMN() - ($E35 + 5)), 0)) ) )} -> 2836.1168 | AN35: {=IF(COLUMN() - ($E35 + 5) < 0, 0, IF(COLUMN() - ($E35 + 5) = 0, $F35, AM35 * (1 - IFERROR(INDEX('Inputs & Assuptions'!$B$13:$B$72, COLUMN() - ($E35 + 5)), 0)) ) )} -> 2708.4916 | AO35: {=IF(COLUMN() - ($E35 + 5) < 0, 0, IF(COLUMN() - ($E35 + 5) = 0, $F35, AN35 * (1 - IFERROR(INDEX('Inputs & Assuptions'!$B$13:$B$72, COLUMN() - ($E35 + 5)), 0)) ) )} -> 2600.1519 | AP35: {=IF(COLUMN() - ($E35 + 5) < 0, 0, IF(COLUMN() - ($E35 + 5) = 0, $F35, AO35 * (1 - IFERROR(INDEX('Inputs & Assuptions'!$B$13:$B$72, COLUMN() - ($E35 + 5)), 0)) ) )} -> 2509.1466 | AQ35: {=IF(COLUMN() - ($E35 + 5) < 0, 0, IF(COLUMN() - ($E35 + 5) = 0, $F35, AP35 * (1 - IFERROR(INDEX('Inputs & Assuptions'!$B$13:$B$72, COLUMN() - ($E35 + 5)), 0)) ) )} -> 2433.8722 | ... BM35: {=IF(COLUMN() - ($E35 + 5) < 0, 0, IF(COLUMN() - ($E35 + 5) = 0, $F35, BL35 * (1 - IFERROR(INDEX('Inputs & Assuptions'!$B$13:$B$72, COLUMN() - ($E35 + 5)), 0)) ) )} -> 1902.0957
A36: =A35+1 -> 31 | B36: =IF(MOD($A36-1, 12) = 0, $B35 * 1.05, $B35) -> 6615 | C36: =$B36*(1-'Inputs & Assuptions'!$B$12) -> 3836.7 | E36: =E35+1 -> 31 | AJ36: =+$C36 -> 3836.7 | AK36: {=IF(COLUMN() - ($E36 + 5) < 0, 0, IF(COLUMN() - ($E36 + 5) = 0, $F36, AJ36 * (1 - IFERROR(INDEX('Inputs & Assuptions'!$B$13:$B$72, COLUMN() - ($E36 + 5)), 0)) ) )} -> 3433.8465 | AL36: {=IF(COLUMN() - ($E36 + 5) < 0, 0, IF(COLUMN() - ($E36 + 5) = 0, $F36, AK36 * (1 - IFERROR(INDEX('Inputs & Assuptions'!$B$13:$B$72, COLUMN() - ($E36 + 5)), 0)) ) )} -> 3159.1388 | AM36: {=IF(COLUMN() - ($E36 + 5) < 0, 0, IF(COLUMN() - ($E36 + 5) = 0, $F36, AL36 * (1 - IFERROR(INDEX('Inputs & Assuptions'!$B$13:$B$72, COLUMN() - ($E36 + 5)), 0)) ) )} -> 2985.3861 | AN36: {=IF(COLUMN() - ($E36 + 5) < 0, 0, IF(COLUMN() - ($E36 + 5) = 0, $F36, AM36 * (1 - IFERROR(INDEX('Inputs & Assuptions'!$B$13:$B$72, COLUMN() - ($E36 + 5)), 0)) ) )} -> 2836.1168 | AO36: {=IF(COLUMN() - ($E36 + 5) < 0, 0, IF(COLUMN() - ($E36 + 5) = 0, $F36, AN36 * (1 - IFERROR(INDEX('Inputs & Assuptions'!$B$13:$B$72, COLUMN() - ($E36 + 5)), 0)) ) )} -> 2708.4916 | AP36: {=IF(COLUMN() - ($E36 + 5) < 0, 0, IF(COLUMN() - ($E36 + 5) = 0, $F36, AO36 * (1 - IFERROR(INDEX('Inputs & Assuptions'!$B$13:$B$72, COLUMN() - ($E36 + 5)), 0)) ) )} -> 2600.1519 | AQ36: {=IF(COLUMN() - ($E36 + 5) < 0, 0, IF(COLUMN() - ($E36 + 5) = 0, $F36, AP36 * (1 - IFERROR(INDEX('Inputs & Assuptions'!$B$13:$B$72, COLUMN() - ($E36 + 5)), 0)) ) )} -> 2509.1466 | AR36: {=IF(COLUMN() - ($E36 + 5) < 0, 0, IF(COLUMN() - ($E36 + 5) = 0, $F36, AQ36 * (1 - IFERROR(INDEX('Inputs & Assuptions'!$B$13:$B$72, COLUMN() - ($E36 + 5)), 0)) ) )} -> 2433.8722 | ... BM36: {=IF(COLUMN() - ($E36 + 5) < 0, 0, IF(COLUMN() - ($E36 + 5) = 0, $F36, BL36 * (1 - IFERROR(INDEX('Inputs & Assuptions'!$B$13:$B$72, COLUMN() - ($E36 + 5)), 0)) ) )} -> 1921.3087
A37: =A36+1 -> 32 | B37: =IF(MOD($A37-1, 12) = 0, $B36 * 1.05, $B36) -> 6615 | C37: =$B37*(1-'Inputs & Assuptions'!$B$12) -> 3836.7 | E37: =E36+1 -> 32 | AK37: =+$C37 -> 3836.7 | AL37: {=IF(COLUMN() - ($E37 + 5) < 0, 0, IF(COLUMN() - ($E37 + 5) = 0, $F37, AK37 * (1 - IFERROR(INDEX('Inputs & Assuptions'!$B$13:$B$72, COLUMN() - ($E37 + 5)), 0)) ) )} -> 3433.8465 | AM37: {=IF(COLUMN() - ($E37 + 5) < 0, 0, IF(COLUMN() - ($E37 + 5) = 0, $F37, AL37 * (1 - IFERROR(INDEX('Inputs & Assuptions'!$B$13:$B$72, COLUMN() - ($E37 + 5)), 0)) ) )} -> 3159.1388 | AN37: {=IF(COLUMN() - ($E37 + 5) < 0, 0, IF(COLUMN() - ($E37 + 5) = 0, $F37, AM37 * (1 - IFERROR(INDEX('Inputs & Assuptions'!$B$13:$B$72, COLUMN() - ($E37 + 5)), 0)) ) )} -> 2985.3861 | AO37: {=IF(COLUMN() - ($E37 + 5) < 0, 0, IF(COLUMN() - ($E37 + 5) = 0, $F37, AN37 * (1 - IFERROR(INDEX('Inputs & Assuptions'!$B$13:$B$72, COLUMN() - ($E37 + 5)), 0)) ) )} -> 2836.1168 | AP37: {=IF(COLUMN() - ($E37 + 5) < 0, 0, IF(COLUMN() - ($E37 + 5) = 0, $F37, AO37 * (1 - IFERROR(INDEX('Inputs & Assuptions'!$B$13:$B$72, COLUMN() - ($E37 + 5)), 0)) ) )} -> 2708.4916 | AQ37: {=IF(COLUMN() - ($E37 + 5) < 0, 0, IF(COLUMN() - ($E37 + 5) = 0, $F37, AP37 * (1 - IFERROR(INDEX('Inputs & Assuptions'!$B$13:$B$72, COLUMN() - ($E37 + 5)), 0)) ) )} -> 2600.1519 | AR37: {=IF(COLUMN() - ($E37 + 5) < 0, 0, IF(COLUMN() - ($E37 + 5) = 0, $F37, AQ37 * (1 - IFERROR(INDEX('Inputs & Assuptions'!$B$13:$B$72, COLUMN() - ($E37 + 5)), 0)) ) )} -> 2509.1466 | AS37: {=IF(COLUMN() - ($E37 + 5) < 0, 0, IF(COLUMN() - ($E37 + 5) = 0, $F37, AR37 * (1 - IFERROR(INDEX('Inputs & Assuptions'!$B$13:$B$72, COLUMN() - ($E37 + 5)), 0)) ) )} -> 2433.8722 | ... BM37: {=IF(COLUMN() - ($E37 + 5) < 0, 0, IF(COLUMN() - ($E37 + 5) = 0, $F37, BL37 * (1 - IFERROR(INDEX('Inputs & Assuptions'!$B$13:$B$72, COLUMN() - ($E37 + 5)), 0)) ) )} -> 1940.7159
A38: =A37+1 -> 33 | B38: =IF(MOD($A38-1, 12) = 0, $B37 * 1.05, $B37) -> 6615 | C38: =$B38*(1-'Inputs & Assuptions'!$B$12) -> 3836.7 | E38: =E37+1 -> 33 | AL38: =+$C38 -> 3836.7 | AM38: {=IF(COLUMN() - ($E38 + 5) < 0, 0, IF(COLUMN() - ($E38 + 5) = 0, $F38, AL38 * (1 - IFERROR(INDEX('Inputs & Assuptions'!$B$13:$B$72, COLUMN() - ($E38 + 5)), 0)) ) )} -> 3433.8465 | AN38: {=IF(COLUMN() - ($E38 + 5) < 0, 0, IF(COLUMN() - ($E38 + 5) = 0, $F38, AM38 * (1 - IFERROR(INDEX('Inputs & Assuptions'!$B$13:$B$72, COLUMN() - ($E38 + 5)), 0)) ) )} -> 3159.1388 | AO38: {=IF(COLUMN() - ($E38 + 5) < 0, 0, IF(COLUMN() - ($E38 + 5) = 0, $F38, AN38 * (1 - IFERROR(INDEX('Inputs & Assuptions'!$B$13:$B$72, COLUMN() - ($E38 + 5)), 0)) ) )} -> 2985.3861 | AP38: {=IF(COLUMN() - ($E38 + 5) < 0, 0, IF(COLUMN() - ($E38 + 5) = 0, $F38, AO38 * (1 - IFERROR(INDEX('Inputs & Assuptions'!$B$13:$B$72, COLUMN() - ($E38 + 5)), 0)) ) )} -> 2836.1168 | AQ38: {=IF(COLUMN() - ($E38 + 5) < 0, 0, IF(COLUMN() - ($E38 + 5) = 0, $F38, AP38 * (1 - IFERROR(INDEX('Inputs & Assuptions'!$B$13:$B$72, COLUMN() - ($E38 + 5)), 0)) ) )} -> 2708.4916 | AR38: {=IF(COLUMN() - ($E38 + 5) < 0, 0, IF(COLUMN() - ($E38 + 5) = 0, $F38, AQ38 * (1 - IFERROR(INDEX('Inputs & Assuptions'!$B$13:$B$72, COLUMN() - ($E38 + 5)), 0)) ) )} -> 2600.1519 | AS38: {=IF(COLUMN() - ($E38 + 5) < 0, 0, IF(COLUMN() - ($E38 + 5) = 0, $F38, AR38 * (1 - IFERROR(INDEX('Inputs & Assuptions'!$B$13:$B$72, COLUMN() - ($E38 + 5)), 0)) ) )} -> 2509.1466 | AT38: {=IF(COLUMN() - ($E38 + 5) < 0, 0, IF(COLUMN() - ($E38 + 5) = 0, $F38, AS38 * (1 - IFERROR(INDEX('Inputs & Assuptions'!$B$13:$B$72, COLUMN() - ($E38 + 5)), 0)) ) )} -> 2433.8722 | ... BM38: {=IF(COLUMN() - ($E38 + 5) < 0, 0, IF(COLUMN() - ($E38 + 5) = 0, $F38, BL38 * (1 - IFERROR(INDEX('Inputs & Assuptions'!$B$13:$B$72, COLUMN() - ($E38 + 5)), 0)) ) )} -> 1960.3191
A39: =A38+1 -> 34 | B39: =IF(MOD($A39-1, 12) = 0, $B38 * 1.05, $B38) -> 6615 | C39: =$B39*(1-'Inputs & Assuptions'!$B$12) -> 3836.7 | E39: =E38+1 -> 34 | AM39: =+$C39 -> 3836.7 | AN39: {=IF(COLUMN() - ($E39 + 5) < 0, 0, IF(COLUMN() - ($E39 + 5) = 0, $F39, AM39 * (1 - IFERROR(INDEX('Inputs & Assuptions'!$B$13:$B$72, COLUMN() - ($E39 + 5)), 0)) ) )} -> 3433.8465 | AO39: {=IF(COLUMN() - ($E39 + 5) < 0, 0, IF(COLUMN() - ($E39 + 5) = 0, $F39, AN39 * (1 - IFERROR(INDEX('Inputs & Assuptions'!$B$13:$B$72, COLUMN() - ($E39 + 5)), 0)) ) )} -> 3159.1388 | AP39: {=IF(COLUMN() - ($E39 + 5) < 0, 0, IF(COLUMN() - ($E39 + 5) = 0, $F39, AO39 * (1 - IFERROR(INDEX('Inputs & Assuptions'!$B$13:$B$72, COLUMN() - ($E39 + 5)), 0)) ) )} -> 2985.3861 | AQ39: {=IF(COLUMN() - ($E39 + 5) < 0, 0, IF(COLUMN() - ($E39 + 5) = 0, $F39, AP39 * (1 - IFERROR(INDEX('Inputs & Assuptions'!$B$13:$B$72, COLUMN() - ($E39 + 5)), 0)) ) )} -> 2836.1168 | AR39: {=IF(COLUMN() - ($E39 + 5) < 0, 0, IF(COLUMN() - ($E39 + 5) = 0, $F39, AQ39 * (1 - IFERROR(INDEX('Inputs & Assuptions'!$B$13:$B$72, COLUMN() - ($E39 + 5)), 0)) ) )} -> 2708.4916 | AS39: {=IF(COLUMN() - ($E39 + 5) < 0, 0, IF(COLUMN() - ($E39 + 5) = 0, $F39, AR39 * (1 - IFERROR(INDEX('Inputs & Assuptions'!$B$13:$B$72, COLUMN() - ($E39 + 5)), 0)) ) )} -> 2600.1519 | AT39: {=IF(COLUMN() - ($E39 + 5) < 0, 0, IF(COLUMN() - ($E39 + 5) = 0, $F39, AS39 * (1 - IFERROR(INDEX('Inputs & Assuptions'!$B$13:$B$72, COLUMN() - ($E39 + 5)), 0)) ) )} -> 2509.1466 | AU39: {=IF(COLUMN() - ($E39 + 5) < 0, 0, IF(COLUMN() - ($E39 + 5) = 0, $F39, AT39 * (1 - IFERROR(INDEX('Inputs & Assuptions'!$B$13:$B$72, COLUMN() - ($E39 + 5)), 0)) ) )} -> 2433.8722 | ... BM39: {=IF(COLUMN() - ($E39 + 5) < 0, 0, IF(COLUMN() - ($E39 + 5) = 0, $F39, BL39 * (1 - IFERROR(INDEX('Inputs & Assuptions'!$B$13:$B$72, COLUMN() - ($E39 + 5)), 0)) ) )} -> 1980.1203
A40: =A39+1 -> 35 | B40: =IF(MOD($A40-1, 12) = 0, $B39 * 1.05, $B39) -> 6615 | C40: =$B40*(1-'Inputs & Assuptions'!$B$12) -> 3836.7 | E40: =E39+1 -> 35 | AN40: =+$C40 -> 3836.7 | AO40: {=IF(COLUMN() - ($E40 + 5) < 0, 0, IF(COLUMN() - ($E40 + 5) = 0, $F40, AN40 * (1 - IFERROR(INDEX('Inputs & Assuptions'!$B$13:$B$72, COLUMN() - ($E40 + 5)), 0)) ) )} -> 3433.8465 | AP40: {=IF(COLUMN() - ($E40 + 5) < 0, 0, IF(COLUMN() - ($E40 + 5) = 0, $F40, AO40 * (1 - IFERROR(INDEX('Inputs & Assuptions'!$B$13:$B$72, COLUMN() - ($E40 + 5)), 0)) ) )} -> 3159.1388 | AQ40: {=IF(COLUMN() - ($E40 + 5) < 0, 0, IF(COLUMN() - ($E40 + 5) = 0, $F40, AP40 * (1 - IFERROR(INDEX('Inputs & Assuptions'!$B$13:$B$72, COLUMN() - ($E40 + 5)), 0)) ) )} -> 2985.3861 | AR40: {=IF(COLUMN() - ($E40 + 5) < 0, 0, IF(COLUMN() - ($E40 + 5) = 0, $F40, AQ40 * (1 - IFERROR(INDEX('Inputs & Assuptions'!$B$13:$B$72, COLUMN() - ($E40 + 5)), 0)) ) )} -> 2836.1168 | AS40: {=IF(COLUMN() - ($E40 + 5) < 0, 0, IF(COLUMN() - ($E40 + 5) = 0, $F40, AR40 * (1 - IFERROR(INDEX('Inputs & Assuptions'!$B$13:$B$72, COLUMN() - ($E40 + 5)), 0)) ) )} -> 2708.4916 | AT40: {=IF(COLUMN() - ($E40 + 5) < 0, 0, IF(COLUMN() - ($E40 + 5) = 0, $F40, AS40 * (1 - IFERROR(INDEX('Inputs & Assuptions'!$B$13:$B$72, COLUMN() - ($E40 + 5)), 0)) ) )} -> 2600.1519 | AU40: {=IF(COLUMN() - ($E40 + 5) < 0, 0, IF(COLUMN() - ($E40 + 5) = 0, $F40, AT40 * (1 - IFERROR(INDEX('Inputs & Assuptions'!$B$13:$B$72, COLUMN() - ($E40 + 5)), 0)) ) )} -> 2509.1466 | AV40: {=IF(COLUMN() - ($E40 + 5) < 0, 0, IF(COLUMN() - ($E40 + 5) = 0, $F40, AU40 * (1 - IFERROR(INDEX('Inputs & Assuptions'!$B$13:$B$72, COLUMN() - ($E40 + 5)), 0)) ) )} -> 2433.8722 | ... BM40: {=IF(COLUMN() - ($E40 + 5) < 0, 0, IF(COLUMN() - ($E40 + 5) = 0, $F40, BL40 * (1 - IFERROR(INDEX('Inputs & Assuptions'!$B$13:$B$72, COLUMN() - ($E40 + 5)), 0)) ) )} -> 2000.1215
A41: =A40+1 -> 36 | B41: =IF(MOD($A41-1, 12) = 0, $B40 * 1.05, $B40) -> 6615 | C41: =$B41*(1-'Inputs & Assuptions'!$B$12) -> 3836.7 | E41: =E40+1 -> 36 | AO41: =+$C41 -> 3836.7 | AP41: {=IF(COLUMN() - ($E41 + 5) < 0, 0, IF(COLUMN() - ($E41 + 5) = 0, $F41, AO41 * (1 - IFERROR(INDEX('Inputs & Assuptions'!$B$13:$B$72, COLUMN() - ($E41 + 5)), 0)) ) )} -> 3433.8465 | AQ41: {=IF(COLUMN() - ($E41 + 5) < 0, 0, IF(COLUMN() - ($E41 + 5) = 0, $F41, AP41 * (1 - IFERROR(INDEX('Inputs & Assuptions'!$B$13:$B$72, COLUMN() - ($E41 + 5)), 0)) ) )} -> 3159.1388 | AR41: {=IF(COLUMN() - ($E41 + 5) < 0, 0, IF(COLUMN() - ($E41 + 5) = 0, $F41, AQ41 * (1 - IFERROR(INDEX('Inputs & Assuptions'!$B$13:$B$72, COLUMN() - ($E41 + 5)), 0)) ) )} -> 2985.3861 | AS41: {=IF(COLUMN() - ($E41 + 5) < 0, 0, IF(COLUMN() - ($E41 + 5) = 0, $F41, AR41 * (1 - IFERROR(INDEX('Inputs & Assuptions'!$B$13:$B$72, COLUMN() - ($E41 + 5)), 0)) ) )} -> 2836.1168 | AT41: {=IF(COLUMN() - ($E41 + 5) < 0, 0, IF(COLUMN() - ($E41 + 5) = 0, $F41, AS41 * (1 - IFERROR(INDEX('Inputs & Assuptions'!$B$13:$B$72, COLUMN() - ($E41 + 5)), 0)) ) )} -> 2708.4916 | AU41: {=IF(COLUMN() - ($E41 + 5) < 0, 0, IF(COLUMN() - ($E41 + 5) = 0, $F41, AT41 * (1 - IFERROR(INDEX('Inputs & Assuptions'!$B$13:$B$72, COLUMN() - ($E41 + 5)), 0)) ) )} -> 2600.1519 | AV41: {=IF(COLUMN() - ($E41 + 5) < 0, 0, IF(COLUMN() - ($E41 + 5) = 0, $F41, AU41 * (1 - IFERROR(INDEX('Inputs & Assuptions'!$B$13:$B$72, COLUMN() - ($E41 + 5)), 0)) ) )} -> 2509.1466 | AW41: {=IF(COLUMN() - ($E41 + 5) < 0, 0, IF(COLUMN() - ($E41 + 5) = 0, $F41, AV41 * (1 - IFERROR(INDEX('Inputs & Assuptions'!$B$13:$B$72, COLUMN() - ($E41 + 5)), 0)) ) )} -> 2433.8722 | ... BM41: {=IF(COLUMN() - ($E41 + 5) < 0, 0, IF(COLUMN() - ($E41 + 5) = 0, $F41, BL41 * (1 - IFERROR(INDEX('Inputs & Assuptions'!$B$13:$B$72, COLUMN() - ($E41 + 5)), 0)) ) )} -> 2020.3248
A42: =A41+1 -> 37 | B42: =IF(MOD($A42-1, 12) = 0, $B41 * 1.05, $B41) -> 6945.75 | C42: =$B42*(1-'Inputs & Assuptions'!$B$12) -> 4028.535 | E42: =E41+1 -> 37 | AP42: =+$C42 -> 4028.535 | AQ42: {=IF(COLUMN() - ($E42 + 5) < 0, 0, IF(COLUMN() - ($E42 + 5) = 0, $F42, AP42 * (1 - IFERROR(INDEX('Inputs & Assuptions'!$B$13:$B$72, COLUMN() - ($E42 + 5)), 0)) ) )} -> 3605.5388 | AR42: {=IF(COLUMN() - ($E42 + 5) < 0, 0, IF(COLUMN() - ($E42 + 5) = 0, $F42, AQ42 * (1 - IFERROR(INDEX('Inputs & Assuptions'!$B$13:$B$72, COLUMN() - ($E42 + 5)), 0)) ) )} -> 3317.0957 | AS42: {=IF(COLUMN() - ($E42 + 5) < 0, 0, IF(COLUMN() - ($E42 + 5) = 0, $F42, AR42 * (1 - IFERROR(INDEX('Inputs & Assuptions'!$B$13:$B$72, COLUMN() - ($E42 + 5)), 0)) ) )} -> 3134.6555 | AT42: {=IF(COLUMN() - ($E42 + 5) < 0, 0, IF(COLUMN() - ($E42 + 5) = 0, $F42, AS42 * (1 - IFERROR(INDEX('Inputs & Assuptions'!$B$13:$B$72, COLUMN() - ($E42 + 5)), 0)) ) )} -> 2977.9227 | AU42: {=IF(COLUMN() - ($E42 + 5) < 0, 0, IF(COLUMN() - ($E42 + 5) = 0, $F42, AT42 * (1 - IFERROR(INDEX('Inputs & Assuptions'!$B$13:$B$72, COLUMN() - ($E42 + 5)), 0)) ) )} -> 2843.9162 | AV42: {=IF(COLUMN() - ($E42 + 5) < 0, 0, IF(COLUMN() - ($E42 + 5) = 0, $F42, AU42 * (1 - IFERROR(INDEX('Inputs & Assuptions'!$B$13:$B$72, COLUMN() - ($E42 + 5)), 0)) ) )} -> 2730.1595 | AW42: {=IF(COLUMN() - ($E42 + 5) < 0, 0, IF(COLUMN() - ($E42 + 5) = 0, $F42, AV42 * (1 - IFERROR(INDEX('Inputs & Assuptions'!$B$13:$B$72, COLUMN() - ($E42 + 5)), 0)) ) )} -> 2634.6039 | AX42: {=IF(COLUMN() - ($E42 + 5) < 0, 0, IF(COLUMN() - ($E42 + 5) = 0, $F42, AW42 * (1 - IFERROR(INDEX('Inputs & Assuptions'!$B$13:$B$72, COLUMN() - ($E42 + 5)), 0)) ) )} -> 2555.5658 | ... BM42: {=IF(COLUMN() - ($E42 + 5) < 0, 0, IF(COLUMN() - ($E42 + 5) = 0, $F42, BL42 * (1 - IFERROR(INDEX('Inputs & Assuptions'!$B$13:$B$72, COLUMN() - ($E42 + 5)), 0)) ) )} -> 2142.7687
A43: =A42+1 -> 38 | B43: =IF(MOD($A43-1, 12) = 0, $B42 * 1.05, $B42) -> 6945.75 | C43: =$B43*(1-'Inputs & Assuptions'!$B$12) -> 4028.535 | E43: =E42+1 -> 38 | AQ43: =+$C43 -> 4028.535 | AR43: {=IF(COLUMN() - ($E43 + 5) < 0, 0, IF(COLUMN() - ($E43 + 5) = 0, $F43, AQ43 * (1 - IFERROR(INDEX('Inputs & Assuptions'!$B$13:$B$72, COLUMN() - ($E43 + 5)), 0)) ) )} -> 3605.5388 | AS43: {=IF(COLUMN() - ($E43 + 5) < 0, 0, IF(COLUMN() - ($E43 + 5) = 0, $F43, AR43 * (1 - IFERROR(INDEX('Inputs & Assuptions'!$B$13:$B$72, COLUMN() - ($E43 + 5)), 0)) ) )} -> 3317.0957 | AT43: {=IF(COLUMN() - ($E43 + 5) < 0, 0, IF(COLUMN() - ($E43 + 5) = 0, $F43, AS43 * (1 - IFERROR(INDEX('Inputs & Assuptions'!$B$13:$B$72, COLUMN() - ($E43 + 5)), 0)) ) )} -> 3134.6555 | AU43: {=IF(COLUMN() - ($E43 + 5) < 0, 0, IF(COLUMN() - ($E43 + 5) = 0, $F43, AT43 * (1 - IFERROR(INDEX('Inputs & Assuptions'!$B$13:$B$72, COLUMN() - ($E43 + 5)), 0)) ) )} -> 2977.9227 | AV43: {=IF(COLUMN() - ($E43 + 5) < 0, 0, IF(COLUMN() - ($E43 + 5) = 0, $F43, AU43 * (1 - IFERROR(INDEX('Inputs & Assuptions'!$B$13:$B$72, COLUMN() - ($E43 + 5)), 0)) ) )} -> 2843.9162 | AW43: {=IF(COLUMN() - ($E43 + 5) < 0, 0, IF(COLUMN() - ($E43 + 5) = 0, $F43, AV43 * (1 - IFERROR(INDEX('Inputs & Assuptions'!$B$13:$B$72, COLUMN() - ($E43 + 5)), 0)) ) )} -> 2730.1595 | AX43: {=IF(COLUMN() - ($E43 + 5) < 0, 0, IF(COLUMN() - ($E43 + 5) = 0, $F43, AW43 * (1 - IFERROR(INDEX('Inputs & Assuptions'!$B$13:$B$72, COLUMN() - ($E43 + 5)), 0)) ) )} -> 2634.6039 | AY43: {=IF(COLUMN() - ($E43 + 5) < 0, 0, IF(COLUMN() - ($E43 + 5) = 0, $F43, AX43 * (1 - IFERROR(INDEX('Inputs & Assuptions'!$B$13:$B$72, COLUMN() - ($E43 + 5)), 0)) ) )} -> 2555.5658 | ... BM43: {=IF(COLUMN() - ($E43 + 5) < 0, 0, IF(COLUMN() - ($E43 + 5) = 0, $F43, BL43 * (1 - IFERROR(INDEX('Inputs & Assuptions'!$B$13:$B$72, COLUMN() - ($E43 + 5)), 0)) ) )} -> 2164.4128
A44: =A43+1 -> 39 | B44: =IF(MOD($A44-1, 12) = 0, $B43 * 1.05, $B43) -> 6945.75 | C44: =$B44*(1-'Inputs & Assuptions'!$B$12) -> 4028.535 | E44: =E43+1 -> 39 | AR44: =+$C44 -> 4028.535 | AS44: {=IF(COLUMN() - ($E44 + 5) < 0, 0, IF(COLUMN() - ($E44 + 5) = 0, $F44, AR44 * (1 - IFERROR(INDEX('Inputs & Assuptions'!$B$13:$B$72, COLUMN() - ($E44 + 5)), 0)) ) )} -> 3605.5388 | AT44: {=IF(COLUMN() - ($E44 + 5) < 0, 0, IF(COLUMN() - ($E44 + 5) = 0, $F44, AS44 * (1 - IFERROR(INDEX('Inputs & Assuptions'!$B$13:$B$72, COLUMN() - ($E44 + 5)), 0)) ) )} -> 3317.0957 | AU44: {=IF(COLUMN() - ($E44 + 5) < 0, 0, IF(COLUMN() - ($E44 + 5) = 0, $F44, AT44 * (1 - IFERROR(INDEX('Inputs & Assuptions'!$B$13:$B$72, COLUMN() - ($E44 + 5)), 0)) ) )} -> 3134.6555 | AV44: {=IF(COLUMN() - ($E44 + 5) < 0, 0, IF(COLUMN() - ($E44 + 5) = 0, $F44, AU44 * (1 - IFERROR(INDEX('Inputs & Assuptions'!$B$13:$B$72, COLUMN() - ($E44 + 5)), 0)) ) )} -> 2977.9227 | AW44: {=IF(COLUMN() - ($E44 + 5) < 0, 0, IF(COLUMN() - ($E44 + 5) = 0, $F44, AV44 * (1 - IFERROR(INDEX('Inputs & Assuptions'!$B$13:$B$72, COLUMN() - ($E44 + 5)), 0)) ) )} -> 2843.9162 | AX44: {=IF(COLUMN() - ($E44 + 5) < 0, 0, IF(COLUMN() - ($E44 + 5) = 0, $F44, AW44 * (1 - IFERROR(INDEX('Inputs & Assuptions'!$B$13:$B$72, COLUMN() - ($E44 + 5)), 0)) ) )} -> 2730.1595 | AY44: {=IF(COLUMN() - ($E44 + 5) < 0, 0, IF(COLUMN() - ($E44 + 5) = 0, $F44, AX44 * (1 - IFERROR(INDEX('Inputs & Assuptions'!$B$13:$B$72, COLUMN() - ($E44 + 5)), 0)) ) )} -> 2634.6039 | AZ44: {=IF(COLUMN() - ($E44 + 5) < 0, 0, IF(COLUMN() - ($E44 + 5) = 0, $F44, AY44 * (1 - IFERROR(INDEX('Inputs & Assuptions'!$B$13:$B$72, COLUMN() - ($E44 + 5)), 0)) ) )} -> 2555.5658 | ... BM44: {=IF(COLUMN() - ($E44 + 5) < 0, 0, IF(COLUMN() - ($E44 + 5) = 0, $F44, BL44 * (1 - IFERROR(INDEX('Inputs & Assuptions'!$B$13:$B$72, COLUMN() - ($E44 + 5)), 0)) ) )} -> 2186.2756
A45: =A44+1 -> 40 | B45: =IF(MOD($A45-1, 12) = 0, $B44 * 1.05, $B44) -> 6945.75 | C45: =$B45*(1-'Inputs & Assuptions'!$B$12) -> 4028.535 | E45: =E44+1 -> 40 | AS45: =+$C45 -> 4028.535 | AT45: {=IF(COLUMN() - ($E45 + 5) < 0, 0, IF(COLUMN() - ($E45 + 5) = 0, $F45, AS45 * (1 - IFERROR(INDEX('Inputs & Assuptions'!$B$13:$B$72, COLUMN() - ($E45 + 5)), 0)) ) )} -> 3605.5388 | AU45: {=IF(COLUMN() - ($E45 + 5) < 0, 0, IF(COLUMN() - ($E45 + 5) = 0, $F45, AT45 * (1 - IFERROR(INDEX('Inputs & Assuptions'!$B$13:$B$72, COLUMN() - ($E45 + 5)), 0)) ) )} -> 3317.0957 | AV45: {=IF(COLUMN() - ($E45 + 5) < 0, 0, IF(COLUMN() - ($E45 + 5) = 0, $F45, AU45 * (1 - IFERROR(INDEX('Inputs & Assuptions'!$B$13:$B$72, COLUMN() - ($E45 + 5)), 0)) ) )} -> 3134.6555 | AW45: {=IF(COLUMN() - ($E45 + 5) < 0, 0, IF(COLUMN() - ($E45 + 5) = 0, $F45, AV45 * (1 - IFERROR(INDEX('Inputs & Assuptions'!$B$13:$B$72, COLUMN() - ($E45 + 5)), 0)) ) )} -> 2977.9227 | AX45: {=IF(COLUMN() - ($E45 + 5) < 0, 0, IF(COLUMN() - ($E45 + 5) = 0, $F45, AW45 * (1 - IFERROR(INDEX('Inputs & Assuptions'!$B$13:$B$72, COLUMN() - ($E45 + 5)), 0)) ) )} -> 2843.9162 | AY45: {=IF(COLUMN() - ($E45 + 5) < 0, 0, IF(COLUMN() - ($E45 + 5) = 0, $F45, AX45 * (1 - IFERROR(INDEX('Inputs & Assuptions'!$B$13:$B$72, COLUMN() - ($E45 + 5)), 0)) ) )} -> 2730.1595 | AZ45: {=IF(COLUMN() - ($E45 + 5) < 0, 0, IF(COLUMN() - ($E45 + 5) = 0, $F45, AY45 * (1 - IFERROR(INDEX('Inputs & Assuptions'!$B$13:$B$72, COLUMN() - ($E45 + 5)), 0)) ) )} -> 2634.6039 | BA45: {=IF(COLUMN() - ($E45 + 5) < 0, 0, IF(COLUMN() - ($E45 + 5) = 0, $F45, AZ45 * (1 - IFERROR(INDEX('Inputs & Assuptions'!$B$13:$B$72, COLUMN() - ($E45 + 5)), 0)) ) )} -> 2555.5658 | ... BM45: {=IF(COLUMN() - ($E45 + 5) < 0, 0, IF(COLUMN() - ($E45 + 5) = 0, $F45, BL45 * (1 - IFERROR(INDEX('Inputs & Assuptions'!$B$13:$B$72, COLUMN() - ($E45 + 5)), 0)) ) )} -> 2208.3592
A46: =A45+1 -> 41 | B46: =IF(MOD($A46-1, 12) = 0, $B45 * 1.05, $B45) -> 6945.75 | C46: =$B46*(1-'Inputs & Assuptions'!$B$12) -> 4028.535 | E46: =E45+1 -> 41 | AT46: =+$C46 -> 4028.535 | AU46: {=IF(COLUMN() - ($E46 + 5) < 0, 0, IF(COLUMN() - ($E46 + 5) = 0, $F46, AT46 * (1 - IFERROR(INDEX('Inputs & Assuptions'!$B$13:$B$72, COLUMN() - ($E46 + 5)), 0)) ) )} -> 3605.5388 | AV46: {=IF(COLUMN() - ($E46 + 5) < 0, 0, IF(COLUMN() - ($E46 + 5) = 0, $F46, AU46 * (1 - IFERROR(INDEX('Inputs & Assuptions'!$B$13:$B$72, COLUMN() - ($E46 + 5)), 0)) ) )} -> 3317.0957 | AW46: {=IF(COLUMN() - ($E46 + 5) < 0, 0, IF(COLUMN() - ($E46 + 5) = 0, $F46, AV46 * (1 - IFERROR(INDEX('Inputs & Assuptions'!$B$13:$B$72, COLUMN() - ($E46 + 5)), 0)) ) )} -> 3134.6555 | AX46: {=IF(COLUMN() - ($E46 + 5) < 0, 0, IF(COLUMN() - ($E46 + 5) = 0, $F46, AW46 * (1 - IFERROR(INDEX('Inputs & Assuptions'!$B$13:$B$72, COLUMN() - ($E46 + 5)), 0)) ) )} -> 2977.9227 | AY46: {=IF(COLUMN() - ($E46 + 5) < 0, 0, IF(COLUMN() - ($E46 + 5) = 0, $F46, AX46 * (1 - IFERROR(INDEX('Inputs & Assuptions'!$B$13:$B$72, COLUMN() - ($E46 + 5)), 0)) ) )} -> 2843.9162 | AZ46: {=IF(COLUMN() - ($E46 + 5) < 0, 0, IF(COLUMN() - ($E46 + 5) = 0, $F46, AY46 * (1 - IFERROR(INDEX('Inputs & Assuptions'!$B$13:$B$72, COLUMN() - ($E46 + 5)), 0)) ) )} -> 2730.1595 | BA46: {=IF(COLUMN() - ($E46 + 5) < 0, 0, IF(COLUMN() - ($E46 + 5) = 0, $F46, AZ46 * (1 - IFERROR(INDEX('Inputs & Assuptions'!$B$13:$B$72, COLUMN() - ($E46 + 5)), 0)) ) )} -> 2634.6039 | BB46: {=IF(COLUMN() - ($E46 + 5) < 0, 0, IF(COLUMN() - ($E46 + 5) = 0, $F46, BA46 * (1 - IFERROR(INDEX('Inputs & Assuptions'!$B$13:$B$72, COLUMN() - ($E46 + 5)), 0)) ) )} -> 2555.5658 | ... BM46: {=IF(COLUMN() - ($E46 + 5) < 0, 0, IF(COLUMN() - ($E46 + 5) = 0, $F46, BL46 * (1 - IFERROR(INDEX('Inputs & Assuptions'!$B$13:$B$72, COLUMN() - ($E46 + 5)), 0)) ) )} -> 2230.6658
A47: =A46+1 -> 42 | B47: =IF(MOD($A47-1, 12) = 0, $B46 * 1.05, $B46) -> 6945.75 | C47: =$B47*(1-'Inputs & Assuptions'!$B$12) -> 4028.535 | E47: =E46+1 -> 42 | AU47: =+$C47 -> 4028.535 | AV47: {=IF(COLUMN() - ($E47 + 5) < 0, 0, IF(COLUMN() - ($E47 + 5) = 0, $F47, AU47 * (1 - IFERROR(INDEX('Inputs & Assuptions'!$B$13:$B$72, COLUMN() - ($E47 + 5)), 0)) ) )} -> 3605.5388 | AW47: {=IF(COLUMN() - ($E47 + 5) < 0, 0, IF(COLUMN() - ($E47 + 5) = 0, $F47, AV47 * (1 - IFERROR(INDEX('Inputs & Assuptions'!$B$13:$B$72, COLUMN() - ($E47 + 5)), 0)) ) )} -> 3317.0957 | AX47: {=IF(COLUMN() - ($E47 + 5) < 0, 0, IF(COLUMN() - ($E47 + 5) = 0, $F47, AW47 * (1 - IFERROR(INDEX('Inputs & Assuptions'!$B$13:$B$72, COLUMN() - ($E47 + 5)), 0)) ) )} -> 3134.6555 | AY47: {=IF(COLUMN() - ($E47 + 5) < 0, 0, IF(COLUMN() - ($E47 + 5) = 0, $F47, AX47 * (1 - IFERROR(INDEX('Inputs & Assuptions'!$B$13:$B$72, COLUMN() - ($E47 + 5)), 0)) ) )} -> 2977.9227 | AZ47: {=IF(COLUMN() - ($E47 + 5) < 0, 0, IF(COLUMN() - ($E47 + 5) = 0, $F47, AY47 * (1 - IFERROR(INDEX('Inputs & Assuptions'!$B$13:$B$72, COLUMN() - ($E47 + 5)), 0)) ) )} -> 2843.9162 | BA47: {=IF(COLUMN() - ($E47 + 5) < 0, 0, IF(COLUMN() - ($E47 + 5) = 0, $F47, AZ47 * (1 - IFERROR(INDEX('Inputs & Assuptions'!$B$13:$B$72, COLUMN() - ($E47 + 5)), 0)) ) )} -> 2730.1595 | BB47: {=IF(COLUMN() - ($E47 + 5) < 0, 0, IF(COLUMN() - ($E47 + 5) = 0, $F47, BA47 * (1 - IFERROR(INDEX('Inputs & Assuptions'!$B$13:$B$72, COLUMN() - ($E47 + 5)), 0)) ) )} -> 2634.6039 | BC47: {=IF(COLUMN() - ($E47 + 5) < 0, 0, IF(COLUMN() - ($E47 + 5) = 0, $F47, BB47 * (1 - IFERROR(INDEX('Inputs & Assuptions'!$B$13:$B$72, COLUMN() - ($E47 + 5)), 0)) ) )} -> 2555.5658 | ... BM47: {=IF(COLUMN() - ($E47 + 5) < 0, 0, IF(COLUMN() - ($E47 + 5) = 0, $F47, BL47 * (1 - IFERROR(INDEX('Inputs & Assuptions'!$B$13:$B$72, COLUMN() - ($E47 + 5)), 0)) ) )} -> 2253.1978
A48: =A47+1 -> 43 | B48: =IF(MOD($A48-1, 12) = 0, $B47 * 1.05, $B47) -> 6945.75 | C48: =$B48*(1-'Inputs & Assuptions'!$B$12) -> 4028.535 | E48: =E47+1 -> 43 | AV48: =+$C48 -> 4028.535 | AW48: {=IF(COLUMN() - ($E48 + 5) < 0, 0, IF(COLUMN() - ($E48 + 5) = 0, $F48, AV48 * (1 - IFERROR(INDEX('Inputs & Assuptions'!$B$13:$B$72, COLUMN() - ($E48 + 5)), 0)) ) )} -> 3605.5388 | AX48: {=IF(COLUMN() - ($E48 + 5) < 0, 0, IF(COLUMN() - ($E48 + 5) = 0, $F48, AW48 * (1 - IFERROR(INDEX('Inputs & Assuptions'!$B$13:$B$72, COLUMN() - ($E48 + 5)), 0)) ) )} -> 3317.0957 | AY48: {=IF(COLUMN() - ($E48 + 5) < 0, 0, IF(COLUMN() - ($E48 + 5) = 0, $F48, AX48 * (1 - IFERROR(INDEX('Inputs & Assuptions'!$B$13:$B$72, COLUMN() - ($E48 + 5)), 0)) ) )} -> 3134.6555 | AZ48: {=IF(COLUMN() - ($E48 + 5) < 0, 0, IF(COLUMN() - ($E48 + 5) = 0, $F48, AY48 * (1 - IFERROR(INDEX('Inputs & Assuptions'!$B$13:$B$72, COLUMN() - ($E48 + 5)), 0)) ) )} -> 2977.9227 | BA48: {=IF(COLUMN() - ($E48 + 5) < 0, 0, IF(COLUMN() - ($E48 + 5) = 0, $F48, AZ48 * (1 - IFERROR(INDEX('Inputs & Assuptions'!$B$13:$B$72, COLUMN() - ($E48 + 5)), 0)) ) )} -> 2843.9162 | BB48: {=IF(COLUMN() - ($E48 + 5) < 0, 0, IF(COLUMN() - ($E48 + 5) = 0, $F48, BA48 * (1 - IFERROR(INDEX('Inputs & Assuptions'!$B$13:$B$72, COLUMN() - ($E48 + 5)), 0)) ) )} -> 2730.1595 | BC48: {=IF(COLUMN() - ($E48 + 5) < 0, 0, IF(COLUMN() - ($E48 + 5) = 0, $F48, BB48 * (1 - IFERROR(INDEX('Inputs & Assuptions'!$B$13:$B$72, COLUMN() - ($E48 + 5)), 0)) ) )} -> 2634.6039 | BD48: {=IF(COLUMN() - ($E48 + 5) < 0, 0, IF(COLUMN() - ($E48 + 5) = 0, $F48, BC48 * (1 - IFERROR(INDEX('Inputs & Assuptions'!$B$13:$B$72, COLUMN() - ($E48 + 5)), 0)) ) )} -> 2555.5658 | ... BM48: {=IF(COLUMN() - ($E48 + 5) < 0, 0, IF(COLUMN() - ($E48 + 5) = 0, $F48, BL48 * (1 - IFERROR(INDEX('Inputs & Assuptions'!$B$13:$B$72, COLUMN() - ($E48 + 5)), 0)) ) )} -> 2275.9574
A49: =A48+1 -> 44 | B49: =IF(MOD($A49-1, 12) = 0, $B48 * 1.05, $B48) -> 6945.75 | C49: =$B49*(1-'Inputs & Assuptions'!$B$12) -> 4028.535 | E49: =E48+1 -> 44 | AW49: =+$C49 -> 4028.535 | AX49: {=IF(COLUMN() - ($E49 + 5) < 0, 0, IF(COLUMN() - ($E49 + 5) = 0, $F49, AW49 * (1 - IFERROR(INDEX('Inputs & Assuptions'!$B$13:$B$72, COLUMN() - ($E49 + 5)), 0)) ) )} -> 3605.5388 | AY49: {=IF(COLUMN() - ($E49 + 5) < 0, 0, IF(COLUMN() - ($E49 + 5) = 0, $F49, AX49 * (1 - IFERROR(INDEX('Inputs & Assuptions'!$B$13:$B$72, COLUMN() - ($E49 + 5)), 0)) ) )} -> 3317.0957 | AZ49: {=IF(COLUMN() - ($E49 + 5) < 0, 0, IF(COLUMN() - ($E49 + 5) = 0, $F49, AY49 * (1 - IFERROR(INDEX('Inputs & Assuptions'!$B$13:$B$72, COLUMN() - ($E49 + 5)), 0)) ) )} -> 3134.6555 | BA49: {=IF(COLUMN() - ($E49 + 5) < 0, 0, IF(COLUMN() - ($E49 + 5) = 0, $F49, AZ49 * (1 - IFERROR(INDEX('Inputs & Assuptions'!$B$13:$B$72, COLUMN() - ($E49 + 5)), 0)) ) )} -> 2977.9227 | BB49: {=IF(COLUMN() - ($E49 + 5) < 0, 0, IF(COLUMN() - ($E49 + 5) = 0, $F49, BA49 * (1 - IFERROR(INDEX('Inputs & Assuptions'!$B$13:$B$72, COLUMN() - ($E49 + 5)), 0)) ) )} -> 2843.9162 | BC49: {=IF(COLUMN() - ($E49 + 5) < 0, 0, IF(COLUMN() - ($E49 + 5) = 0, $F49, BB49 * (1 - IFERROR(INDEX('Inputs & Assuptions'!$B$13:$B$72, COLUMN() - ($E49 + 5)), 0)) ) )} -> 2730.1595 | BD49: {=IF(COLUMN() - ($E49 + 5) < 0, 0, IF(COLUMN() - ($E49 + 5) = 0, $F49, BC49 * (1 - IFERROR(INDEX('Inputs & Assuptions'!$B$13:$B$72, COLUMN() - ($E49 + 5)), 0)) ) )} -> 2634.6039 | BE49: {=IF(COLUMN() - ($E49 + 5) < 0, 0, IF(COLUMN() - ($E49 + 5) = 0, $F49, BD49 * (1 - IFERROR(INDEX('Inputs & Assuptions'!$B$13:$B$72, COLUMN() - ($E49 + 5)), 0)) ) )} -> 2555.5658 | ... BM49: {=IF(COLUMN() - ($E49 + 5) < 0, 0, IF(COLUMN() - ($E49 + 5) = 0, $F49, BL49 * (1 - IFERROR(INDEX('Inputs & Assuptions'!$B$13:$B$72, COLUMN() - ($E49 + 5)), 0)) ) )} -> 2298.9468
A50: =A49+1 -> 45 | B50: =IF(MOD($A50-1, 12) = 0, $B49 * 1.05, $B49) -> 6945.75 | C50: =$B50*(1-'Inputs & Assuptions'!$B$12) -> 4028.535 | E50: =E49+1 -> 45 | AX50: =+$C50 -> 4028.535 | AY50: {=IF(COLUMN() - ($E50 + 5) < 0, 0, IF(COLUMN() - ($E50 + 5) = 0, $F50, AX50 * (1 - IFERROR(INDEX('Inputs & Assuptions'!$B$13:$B$72, COLUMN() - ($E50 + 5)), 0)) ) )} -> 3605.5388 | AZ50: {=IF(COLUMN() - ($E50 + 5) < 0, 0, IF(COLUMN() - ($E50 + 5) = 0, $F50, AY50 * (1 - IFERROR(INDEX('Inputs & Assuptions'!$B$13:$B$72, COLUMN() - ($E50 + 5)), 0)) ) )} -> 3317.0957 | BA50: {=IF(COLUMN() - ($E50 + 5) < 0, 0, IF(COLUMN() - ($E50 + 5) = 0, $F50, AZ50 * (1 - IFERROR(INDEX('Inputs & Assuptions'!$B$13:$B$72, COLUMN() - ($E50 + 5)), 0)) ) )} -> 3134.6555 | BB50: {=IF(COLUMN() - ($E50 + 5) < 0, 0, IF(COLUMN() - ($E50 + 5) = 0, $F50, BA50 * (1 - IFERROR(INDEX('Inputs & Assuptions'!$B$13:$B$72, COLUMN() - ($E50 + 5)), 0)) ) )} -> 2977.9227 | BC50: {=IF(COLUMN() - ($E50 + 5) < 0, 0, IF(COLUMN() - ($E50 + 5) = 0, $F50, BB50 * (1 - IFERROR(INDEX('Inputs & Assuptions'!$B$13:$B$72, COLUMN() - ($E50 + 5)), 0)) ) )} -> 2843.9162 | BD50: {=IF(COLUMN() - ($E50 + 5) < 0, 0, IF(COLUMN() - ($E50 + 5) = 0, $F50, BC50 * (1 - IFERROR(INDEX('Inputs & Assuptions'!$B$13:$B$72, COLUMN() - ($E50 + 5)), 0)) ) )} -> 2730.1595 | BE50: {=IF(COLUMN() - ($E50 + 5) < 0, 0, IF(COLUMN() - ($E50 + 5) = 0, $F50, BD50 * (1 - IFERROR(INDEX('Inputs & Assuptions'!$B$13:$B$72, COLUMN() - ($E50 + 5)), 0)) ) )} -> 2634.6039 | BF50: {=IF(COLUMN() - ($E50 + 5) < 0, 0, IF(COLUMN() - ($E50 + 5) = 0, $F50, BE50 * (1 - IFERROR(INDEX('Inputs & Assuptions'!$B$13:$B$72, COLUMN() - ($E50 + 5)), 0)) ) )} -> 2555.5658 | ... BM50: {=IF(COLUMN() - ($E50 + 5) < 0, 0, IF(COLUMN() - ($E50 + 5) = 0, $F50, BL50 * (1 - IFERROR(INDEX('Inputs & Assuptions'!$B$13:$B$72, COLUMN() - ($E50 + 5)), 0)) ) )} -> 2322.1685
A51: =A50+1 -> 46 | B51: =IF(MOD($A51-1, 12) = 0, $B50 * 1.05, $B50) -> 6945.75 | C51: =$B51*(1-'Inputs & Assuptions'!$B$12) -> 4028.535 | E51: =E50+1 -> 46 | AY51: =+$C51 -> 4028.535 | AZ51: {=IF(COLUMN() - ($E51 + 5) < 0, 0, IF(COLUMN() - ($E51 + 5) = 0, $F51, AY51 * (1 - IFERROR(INDEX('Inputs & Assuptions'!$B$13:$B$72, COLUMN() - ($E51 + 5)), 0)) ) )} -> 3605.5388 | BA51: {=IF(COLUMN() - ($E51 + 5) < 0, 0, IF(COLUMN() - ($E51 + 5) = 0, $F51, AZ51 * (1 - IFERROR(INDEX('Inputs & Assuptions'!$B$13:$B$72, COLUMN() - ($E51 + 5)), 0)) ) )} -> 3317.0957 | BB51: {=IF(COLUMN() - ($E51 + 5) < 0, 0, IF(COLUMN() - ($E51 + 5) = 0, $F51, BA51 * (1 - IFERROR(INDEX('Inputs & Assuptions'!$B$13:$B$72, COLUMN() - ($E51 + 5)), 0)) ) )} -> 3134.6555 | BC51: {=IF(COLUMN() - ($E51 + 5) < 0, 0, IF(COLUMN() - ($E51 + 5) = 0, $F51, BB51 * (1 - IFERROR(INDEX('Inputs & Assuptions'!$B$13:$B$72, COLUMN() - ($E51 + 5)), 0)) ) )} -> 2977.9227 | BD51: {=IF(COLUMN() - ($E51 + 5) < 0, 0, IF(COLUMN() - ($E51 + 5) = 0, $F51, BC51 * (1 - IFERROR(INDEX('Inputs & Assuptions'!$B$13:$B$72, COLUMN() - ($E51 + 5)), 0)) ) )} -> 2843.9162 | BE51: {=IF(COLUMN() - ($E51 + 5) < 0, 0, IF(COLUMN() - ($E51 + 5) = 0, $F51, BD51 * (1 - IFERROR(INDEX('Inputs & Assuptions'!$B$13:$B$72, COLUMN() - ($E51 + 5)), 0)) ) )} -> 2730.1595 | BF51: {=IF(COLUMN() - ($E51 + 5) < 0, 0, IF(COLUMN() - ($E51 + 5) = 0, $F51, BE51 * (1 - IFERROR(INDEX('Inputs & Assuptions'!$B$13:$B$72, COLUMN() - ($E51 + 5)), 0)) ) )} -> 2634.6039 | BG51: {=IF(COLUMN() - ($E51 + 5) < 0, 0, IF(COLUMN() - ($E51 + 5) = 0, $F51, BF51 * (1 - IFERROR(INDEX('Inputs & Assuptions'!$B$13:$B$72, COLUMN() - ($E51 + 5)), 0)) ) )} -> 2555.5658 | ... BM51: {=IF(COLUMN() - ($E51 + 5) < 0, 0, IF(COLUMN() - ($E51 + 5) = 0, $F51, BL51 * (1 - IFERROR(INDEX('Inputs & Assuptions'!$B$13:$B$72, COLUMN() - ($E51 + 5)), 0)) ) )} -> 2345.6248
A52: =A51+1 -> 47 | B52: =IF(MOD($A52-1, 12) = 0, $B51 * 1.05, $B51) -> 6945.75 | C52: =$B52*(1-'Inputs & Assuptions'!$B$12) -> 4028.535 | E52: =E51+1 -> 47 | AZ52: =+$C52 -> 4028.535 | BA52: {=IF(COLUMN() - ($E52 + 5) < 0, 0, IF(COLUMN() - ($E52 + 5) = 0, $F52, AZ52 * (1 - IFERROR(INDEX('Inputs & Assuptions'!$B$13:$B$72, COLUMN() - ($E52 + 5)), 0)) ) )} -> 3605.5388 | BB52: {=IF(COLUMN() - ($E52 + 5) < 0, 0, IF(COLUMN() - ($E52 + 5) = 0, $F52, BA52 * (1 - IFERROR(INDEX('Inputs & Assuptions'!$B$13:$B$72, COLUMN() - ($E52 + 5)), 0)) ) )} -> 3317.0957 | BC52: {=IF(COLUMN() - ($E52 + 5) < 0, 0, IF(COLUMN() - ($E52 + 5) = 0, $F52, BB52 * (1 - IFERROR(INDEX('Inputs & Assuptions'!$B$13:$B$72, COLUMN() - ($E52 + 5)), 0)) ) )} -> 3134.6555 | BD52: {=IF(COLUMN() - ($E52 + 5) < 0, 0, IF(COLUMN() - ($E52 + 5) = 0, $F52, BC52 * (1 - IFERROR(INDEX('Inputs & Assuptions'!$B$13:$B$72, COLUMN() - ($E52 + 5)), 0)) ) )} -> 2977.9227 | BE52: {=IF(COLUMN() - ($E52 + 5) < 0, 0, IF(COLUMN() - ($E52 + 5) = 0, $F52, BD52 * (1 - IFERROR(INDEX('Inputs & Assuptions'!$B$13:$B$72, COLUMN() - ($E52 + 5)), 0)) ) )} -> 2843.9162 | BF52: {=IF(COLUMN() - ($E52 + 5) < 0, 0, IF(COLUMN() - ($E52 + 5) = 0, $F52, BE52 * (1 - IFERROR(INDEX('Inputs & Assuptions'!$B$13:$B$72, COLUMN() - ($E52 + 5)), 0)) ) )} -> 2730.1595 | BG52: {=IF(COLUMN() - ($E52 + 5) < 0, 0, IF(COLUMN() - ($E52 + 5) = 0, $F52, BF52 * (1 - IFERROR(INDEX('Inputs & Assuptions'!$B$13:$B$72, COLUMN() - ($E52 + 5)), 0)) ) )} -> 2634.6039 | BH52: {=IF(COLUMN() - ($E52 + 5) < 0, 0, IF(COLUMN() - ($E52 + 5) = 0, $F52, BG52 * (1 - IFERROR(INDEX('Inputs & Assuptions'!$B$13:$B$72, COLUMN() - ($E52 + 5)), 0)) ) )} -> 2555.5658 | ... BM52: {=IF(COLUMN() - ($E52 + 5) < 0, 0, IF(COLUMN() - ($E52 + 5) = 0, $F52, BL52 * (1 - IFERROR(INDEX('Inputs & Assuptions'!$B$13:$B$72, COLUMN() - ($E52 + 5)), 0)) ) )} -> 2369.318
A53: =A52+1 -> 48 | B53: =IF(MOD($A53-1, 12) = 0, $B52 * 1.05, $B52) -> 6945.75 | C53: =$B53*(1-'Inputs & Assuptions'!$B$12) -> 4028.535 | E53: =E52+1 -> 48 | BA53: =+$C53 -> 4028.535 | BB53: {=IF(COLUMN() - ($E53 + 5) < 0, 0, IF(COLUMN() - ($E53 + 5) = 0, $F53, BA53 * (1 - IFERROR(INDEX('Inputs & Assuptions'!$B$13:$B$72, COLUMN() - ($E53 + 5)), 0)) ) )} -> 3605.5388 | BC53: {=IF(COLUMN() - ($E53 + 5) < 0, 0, IF(COLUMN() - ($E53 + 5) = 0, $F53, BB53 * (1 - IFERROR(INDEX('Inputs & Assuptions'!$B$13:$B$72, COLUMN() - ($E53 + 5)), 0)) ) )} -> 3317.0957 | BD53: {=IF(COLUMN() - ($E53 + 5) < 0, 0, IF(COLUMN() - ($E53 + 5) = 0, $F53, BC53 * (1 - IFERROR(INDEX('Inputs & Assuptions'!$B$13:$B$72, COLUMN() - ($E53 + 5)), 0)) ) )} -> 3134.6555 | BE53: {=IF(COLUMN() - ($E53 + 5) < 0, 0, IF(COLUMN() - ($E53 + 5) = 0, $F53, BD53 * (1 - IFERROR(INDEX('Inputs & Assuptions'!$B$13:$B$72, COLUMN() - ($E53 + 5)), 0)) ) )} -> 2977.9227 | BF53: {=IF(COLUMN() - ($E53 + 5) < 0, 0, IF(COLUMN() - ($E53 + 5) = 0, $F53, BE53 * (1 - IFERROR(INDEX('Inputs & Assuptions'!$B$13:$B$72, COLUMN() - ($E53 + 5)), 0)) ) )} -> 2843.9162 | BG53: {=IF(COLUMN() - ($E53 + 5) < 0, 0, IF(COLUMN() - ($E53 + 5) = 0, $F53, BF53 * (1 - IFERROR(INDEX('Inputs & Assuptions'!$B$13:$B$72, COLUMN() - ($E53 + 5)), 0)) ) )} -> 2730.1595 | BH53: {=IF(COLUMN() - ($E53 + 5) < 0, 0, IF(COLUMN() - ($E53 + 5) = 0, $F53, BG53 * (1 - IFERROR(INDEX('Inputs & Assuptions'!$B$13:$B$72, COLUMN() - ($E53 + 5)), 0)) ) )} -> 2634.6039 | BI53: {=IF(COLUMN() - ($E53 + 5) < 0, 0, IF(COLUMN() - ($E53 + 5) = 0, $F53, BH53 * (1 - IFERROR(INDEX('Inputs & Assuptions'!$B$13:$B$72, COLUMN() - ($E53 + 5)), 0)) ) )} -> 2555.5658 | ... BM53: {=IF(COLUMN() - ($E53 + 5) < 0, 0, IF(COLUMN() - ($E53 + 5) = 0, $F53, BL53 * (1 - IFERROR(INDEX('Inputs & Assuptions'!$B$13:$B$72, COLUMN() - ($E53 + 5)), 0)) ) )} -> 2393.2505
A54: =A53+1 -> 49 | B54: =IF(MOD($A54-1, 12) = 0, $B53 * 1.05, $B53) -> 7293.0375 | C54: =$B54*(1-'Inputs & Assuptions'!$B$12) -> 4229.9618 | E54: =E53+1 -> 49 | BB54: =+$C54 -> 4229.9618 | BC54: {=IF(COLUMN() - ($E54 + 5) < 0, 0, IF(COLUMN() - ($E54 + 5) = 0, $F54, BB54 * (1 - IFERROR(INDEX('Inputs & Assuptions'!$B$13:$B$72, COLUMN() - ($E54 + 5)), 0)) ) )} -> 3785.8158 | BD54: {=IF(COLUMN() - ($E54 + 5) < 0, 0, IF(COLUMN() - ($E54 + 5) = 0, $F54, BC54 * (1 - IFERROR(INDEX('Inputs & Assuptions'!$B$13:$B$72, COLUMN() - ($E54 + 5)), 0)) ) )} -> 3482.9505 | BE54: {=IF(COLUMN() - ($E54 + 5) < 0, 0, IF(COLUMN() - ($E54 + 5) = 0, $F54, BD54 * (1 - IFERROR(INDEX('Inputs & Assuptions'!$B$13:$B$72, COLUMN() - ($E54 + 5)), 0)) ) )} -> 3291.3882 | BF54: {=IF(COLUMN() - ($E54 + 5) < 0, 0, IF(COLUMN() - ($E54 + 5) = 0, $F54, BE54 * (1 - IFERROR(INDEX('Inputs & Assuptions'!$B$13:$B$72, COLUMN() - ($E54 + 5)), 0)) ) )} -> 3126.8188 | BG54: {=IF(COLUMN() - ($E54 + 5) < 0, 0, IF(COLUMN() - ($E54 + 5) = 0, $F54, BF54 * (1 - IFERROR(INDEX('Inputs & Assuptions'!$B$13:$B$72, COLUMN() - ($E54 + 5)), 0)) ) )} -> 2986.112 | BH54: {=IF(COLUMN() - ($E54 + 5) < 0, 0, IF(COLUMN() - ($E54 + 5) = 0, $F54, BG54 * (1 - IFERROR(INDEX('Inputs & Assuptions'!$B$13:$B$72, COLUMN() - ($E54 + 5)), 0)) ) )} -> 2866.6675 | BI54: {=IF(COLUMN() - ($E54 + 5) < 0, 0, IF(COLUMN() - ($E54 + 5) = 0, $F54, BH54 * (1 - IFERROR(INDEX('Inputs & Assuptions'!$B$13:$B$72, COLUMN() - ($E54 + 5)), 0)) ) )} -> 2766.3341 | BJ54: {=IF(COLUMN() - ($E54 + 5) < 0, 0, IF(COLUMN() - ($E54 + 5) = 0, $F54, BI54 * (1 - IFERROR(INDEX('Inputs & Assuptions'!$B$13:$B$72, COLUMN() - ($E54 + 5)), 0)) ) )} -> 2683.3441 | ... BM54: {=IF(COLUMN() - ($E54 + 5) < 0, 0, IF(COLUMN() - ($E54 + 5) = 0, $F54, BL54 * (1 - IFERROR(INDEX('Inputs & Assuptions'!$B$13:$B$72, COLUMN() - ($E54 + 5)), 0)) ) )} -> 2538.2959
A55: =A54+1 -> 50 | B55: =IF(MOD($A55-1, 12) = 0, $B54 * 1.05, $B54) -> 7293.0375 | C55: =$B55*(1-'Inputs & Assuptions'!$B$12) -> 4229.9618 | E55: =E54+1 -> 50 | BC55: =+$C55 -> 4229.9618 | BD55: {=IF(COLUMN() - ($E55 + 5) < 0, 0, IF(COLUMN() - ($E55 + 5) = 0, $F55, BC55 * (1 - IFERROR(INDEX('Inputs & Assuptions'!$B$13:$B$72, COLUMN() - ($E55 + 5)), 0)) ) )} -> 3785.8158 | BE55: {=IF(COLUMN() - ($E55 + 5) < 0, 0, IF(COLUMN() - ($E55 + 5) = 0, $F55, BD55 * (1 - IFERROR(INDEX('Inputs & Assuptions'!$B$13:$B$72, COLUMN() - ($E55 + 5)), 0)) ) )} -> 3482.9505 | BF55: {=IF(COLUMN() - ($E55 + 5) < 0, 0, IF(COLUMN() - ($E55 + 5) = 0, $F55, BE55 * (1 - IFERROR(INDEX('Inputs & Assuptions'!$B$13:$B$72, COLUMN() - ($E55 + 5)), 0)) ) )} -> 3291.3882 | BG55: {=IF(COLUMN() - ($E55 + 5) < 0, 0, IF(COLUMN() - ($E55 + 5) = 0, $F55, BF55 * (1 - IFERROR(INDEX('Inputs & Assuptions'!$B$13:$B$72, COLUMN() - ($E55 + 5)), 0)) ) )} -> 3126.8188 | BH55: {=IF(COLUMN() - ($E55 + 5) < 0, 0, IF(COLUMN() - ($E55 + 5) = 0, $F55, BG55 * (1 - IFERROR(INDEX('Inputs & Assuptions'!$B$13:$B$72, COLUMN() - ($E55 + 5)), 0)) ) )} -> 2986.112 | BI55: {=IF(COLUMN() - ($E55 + 5) < 0, 0, IF(COLUMN() - ($E55 + 5) = 0, $F55, BH55 * (1 - IFERROR(INDEX('Inputs & Assuptions'!$B$13:$B$72, COLUMN() - ($E55 + 5)), 0)) ) )} -> 2866.6675 | BJ55: {=IF(COLUMN() - ($E55 + 5) < 0, 0, IF(COLUMN() - ($E55 + 5) = 0, $F55, BI55 * (1 - IFERROR(INDEX('Inputs & Assuptions'!$B$13:$B$72, COLUMN() - ($E55 + 5)), 0)) ) )} -> 2766.3341 | BK55: {=IF(COLUMN() - ($E55 + 5) < 0, 0, IF(COLUMN() - ($E55 + 5) = 0, $F55, BJ55 * (1 - IFERROR(INDEX('Inputs & Assuptions'!$B$13:$B$72, COLUMN() - ($E55 + 5)), 0)) ) )} -> 2683.3441 | ... BM55: {=IF(COLUMN() - ($E55 + 5) < 0, 0, IF(COLUMN() - ($E55 + 5) = 0, $F55, BL55 * (1 - IFERROR(INDEX('Inputs & Assuptions'!$B$13:$B$72, COLUMN() - ($E55 + 5)), 0)) ) )} -> 2563.9353
A56: =A55+1 -> 51 | B56: =IF(MOD($A56-1, 12) = 0, $B55 * 1.05, $B55) -> 7293.0375 | C56: =$B56*(1-'Inputs & Assuptions'!$B$12) -> 4229.9618 | E56: =E55+1 -> 51 | BD56: =+$C56 -> 4229.9618 | BE56: {=IF(COLUMN() - ($E56 + 5) < 0, 0, IF(COLUMN() - ($E56 + 5) = 0, $F56, BD56 * (1 - IFERROR(INDEX('Inputs & Assuptions'!$B$13:$B$72, COLUMN() - ($E56 + 5)), 0)) ) )} -> 3785.8158 | BF56: {=IF(COLUMN() - ($E56 + 5) < 0, 0, IF(COLUMN() - ($E56 + 5) = 0, $F56, BE56 * (1 - IFERROR(INDEX('Inputs & Assuptions'!$B$13:$B$72, COLUMN() - ($E56 + 5)), 0)) ) )} -> 3482.9505 | BG56: {=IF(COLUMN() - ($E56 + 5) < 0, 0, IF(COLUMN() - ($E56 + 5) = 0, $F56, BF56 * (1 - IFERROR(INDEX('Inputs & Assuptions'!$B$13:$B$72, COLUMN() - ($E56 + 5)), 0)) ) )} -> 3291.3882 | BH56: {=IF(COLUMN() - ($E56 + 5) < 0, 0, IF(COLUMN() - ($E56 + 5) = 0, $F56, BG56 * (1 - IFERROR(INDEX('Inputs & Assuptions'!$B$13:$B$72, COLUMN() - ($E56 + 5)), 0)) ) )} -> 3126.8188 | BI56: {=IF(COLUMN() - ($E56 + 5) < 0, 0, IF(COLUMN() - ($E56 + 5) = 0, $F56, BH56 * (1 - IFERROR(INDEX('Inputs & Assuptions'!$B$13:$B$72, COLUMN() - ($E56 + 5)), 0)) ) )} -> 2986.112 | BJ56: {=IF(COLUMN() - ($E56 + 5) < 0, 0, IF(COLUMN() - ($E56 + 5) = 0, $F56, BI56 * (1 - IFERROR(INDEX('Inputs & Assuptions'!$B$13:$B$72, COLUMN() - ($E56 + 5)), 0)) ) )} -> 2866.6675 | BK56: {=IF(COLUMN() - ($E56 + 5) < 0, 0, IF(COLUMN() - ($E56 + 5) = 0, $F56, BJ56 * (1 - IFERROR(INDEX('Inputs & Assuptions'!$B$13:$B$72, COLUMN() - ($E56 + 5)), 0)) ) )} -> 2766.3341 | BL56: {=IF(COLUMN() - ($E56 + 5) < 0, 0, IF(COLUMN() - ($E56 + 5) = 0, $F56, BK56 * (1 - IFERROR(INDEX('Inputs & Assuptions'!$B$13:$B$72, COLUMN() - ($E56 + 5)), 0)) ) )} -> 2683.3441 | BM56: {=IF(COLUMN() - ($E56 + 5) < 0, 0, IF(COLUMN() - ($E56 + 5) = 0, $F56, BL56 * (1 - IFERROR(INDEX('Inputs & Assuptions'!$B$13:$B$72, COLUMN() - ($E56 + 5)), 0)) ) )} -> 2616.2605
A57: =A56+1 -> 52 | B57: =IF(MOD($A57-1, 12) = 0, $B56 * 1.05, $B56) -> 7293.0375 | C57: =$B57*(1-'Inputs & Assuptions'!$B$12) -> 4229.9618 | E57: =E56+1 -> 52 | BE57: =+$C57 -> 4229.9618 | BF57: {=IF(COLUMN() - ($E57 + 5) < 0, 0, IF(COLUMN() - ($E57 + 5) = 0, $F57, BE57 * (1 - IFERROR(INDEX('Inputs & Assuptions'!$B$13:$B$72, COLUMN() - ($E57 + 5)), 0)) ) )} -> 3785.8158 | BG57: {=IF(COLUMN() - ($E57 + 5) < 0, 0, IF(COLUMN() - ($E57 + 5) = 0, $F57, BF57 * (1 - IFERROR(INDEX('Inputs & Assuptions'!$B$13:$B$72, COLUMN() - ($E57 + 5)), 0)) ) )} -> 3482.9505 | BH57: {=IF(COLUMN() - ($E57 + 5) < 0, 0, IF(COLUMN() - ($E57 + 5) = 0, $F57, BG57 * (1 - IFERROR(INDEX('Inputs & Assuptions'!$B$13:$B$72, COLUMN() - ($E57 + 5)), 0)) ) )} -> 3291.3882 | BI57: {=IF(COLUMN() - ($E57 + 5) < 0, 0, IF(COLUMN() - ($E57 + 5) = 0, $F57, BH57 * (1 - IFERROR(INDEX('Inputs & Assuptions'!$B$13:$B$72, COLUMN() - ($E57 + 5)), 0)) ) )} -> 3126.8188 | BJ57: {=IF(COLUMN() - ($E57 + 5) < 0, 0, IF(COLUMN() - ($E57 + 5) = 0, $F57, BI57 * (1 - IFERROR(INDEX('Inputs & Assuptions'!$B$13:$B$72, COLUMN() - ($E57 + 5)), 0)) ) )} -> 2986.112 | BK57: {=IF(COLUMN() - ($E57 + 5) < 0, 0, IF(COLUMN() - ($E57 + 5) = 0, $F57, BJ57 * (1 - IFERROR(INDEX('Inputs & Assuptions'!$B$13:$B$72, COLUMN() - ($E57 + 5)), 0)) ) )} -> 2866.6675 | BL57: {=IF(COLUMN() - ($E57 + 5) < 0, 0, IF(COLUMN() - ($E57 + 5) = 0, $F57, BK57 * (1 - IFERROR(INDEX('Inputs & Assuptions'!$B$13:$B$72, COLUMN() - ($E57 + 5)), 0)) ) )} -> 2766.3341 | BM57: {=IF(COLUMN() - ($E57 + 5) < 0, 0, IF(COLUMN() - ($E57 + 5) = 0, $F57, BL57 * (1 - IFERROR(INDEX('Inputs & Assuptions'!$B$13:$B$72, COLUMN() - ($E57 + 5)), 0)) ) )} -> 2683.3441
A58: =A57+1 -> 53 | B58: =IF(MOD($A58-1, 12) = 0, $B57 * 1.05, $B57) -> 7293.0375 | C58: =$B58*(1-'Inputs & Assuptions'!$B$12) -> 4229.9618 | E58: =E57+1 -> 53 | BF58: =+$C58 -> 4229.9618 | BG58: {=IF(COLUMN() - ($E58 + 5) < 0, 0, IF(COLUMN() - ($E58 + 5) = 0, $F58, BF58 * (1 - IFERROR(INDEX('Inputs & Assuptions'!$B$13:$B$72, COLUMN() - ($E58 + 5)), 0)) ) )} -> 3785.8158 | BH58: {=IF(COLUMN() - ($E58 + 5) < 0, 0, IF(COLUMN() - ($E58 + 5) = 0, $F58, BG58 * (1 - IFERROR(INDEX('Inputs & Assuptions'!$B$13:$B$72, COLUMN() - ($E58 + 5)), 0)) ) )} -> 3482.9505 | BI58: {=IF(COLUMN() - ($E58 + 5) < 0, 0, IF(COLUMN() - ($E58 + 5) = 0, $F58, BH58 * (1 - IFERROR(INDEX('Inputs & Assuptions'!$B$13:$B$72, COLUMN() - ($E58 + 5)), 0)) ) )} -> 3291.3882 | BJ58: {=IF(COLUMN() - ($E58 + 5) < 0, 0, IF(COLUMN() - ($E58 + 5) = 0, $F58, BI58 * (1 - IFERROR(INDEX('Inputs & Assuptions'!$B$13:$B$72, COLUMN() - ($E58 + 5)), 0)) ) )} -> 3126.8188 | BK58: {=IF(COLUMN() - ($E58 + 5) < 0, 0, IF(COLUMN() - ($E58 + 5) = 0, $F58, BJ58 * (1 - IFERROR(INDEX('Inputs & Assuptions'!$B$13:$B$72, COLUMN() - ($E58 + 5)), 0)) ) )} -> 2986.112 | BL58: {=IF(COLUMN() - ($E58 + 5) < 0, 0, IF(COLUMN() - ($E58 + 5) = 0, $F58, BK58 * (1 - IFERROR(INDEX('Inputs & Assuptions'!$B$13:$B$72, COLUMN() - ($E58 + 5)), 0)) ) )} -> 2866.6675 | BM58: {=IF(COLUMN() - ($E58 + 5) < 0, 0, IF(COLUMN() - ($E58 + 5) = 0, $F58, BL58 * (1 - IFERROR(INDEX('Inputs & Assuptions'!$B$13:$B$72, COLUMN() - ($E58 + 5)), 0)) ) )} -> 2766.3341
A59: =A58+1 -> 54 | B59: =IF(MOD($A59-1, 12) = 0, $B58 * 1.05, $B58) -> 7293.0375 | C59: =$B59*(1-'Inputs & Assuptions'!$B$12) -> 4229.9618 | E59: =E58+1 -> 54 | BG59: =+$C59 -> 4229.9618 | BH59: {=IF(COLUMN() - ($E59 + 5) < 0, 0, IF(COLUMN() - ($E59 + 5) = 0, $F59, BG59 * (1 - IFERROR(INDEX('Inputs & Assuptions'!$B$13:$B$72, COLUMN() - ($E59 + 5)), 0)) ) )} -> 3785.8158 | BI59: {=IF(COLUMN() - ($E59 + 5) < 0, 0, IF(COLUMN() - ($E59 + 5) = 0, $F59, BH59 * (1 - IFERROR(INDEX('Inputs & Assuptions'!$B$13:$B$72, COLUMN() - ($E59 + 5)), 0)) ) )} -> 3482.9505 | BJ59: {=IF(COLUMN() - ($E59 + 5) < 0, 0, IF(COLUMN() - ($E59 + 5) = 0, $F59, BI59 * (1 - IFERROR(INDEX('Inputs & Assuptions'!$B$13:$B$72, COLUMN() - ($E59 + 5)), 0)) ) )} -> 3291.3882 | BK59: {=IF(COLUMN() - ($E59 + 5) < 0, 0, IF(COLUMN() - ($E59 + 5) = 0, $F59, BJ59 * (1 - IFERROR(INDEX('Inputs & Assuptions'!$B$13:$B$72, COLUMN() - ($E59 + 5)), 0)) ) )} -> 3126.8188 | BL59: {=IF(COLUMN() - ($E59 + 5) < 0, 0, IF(COLUMN() - ($E59 + 5) = 0, $F59, BK59 * (1 - IFERROR(INDEX('Inputs & Assuptions'!$B$13:$B$72, COLUMN() - ($E59 + 5)), 0)) ) )} -> 2986.112 | BM59: {=IF(COLUMN() - ($E59 + 5) < 0, 0, IF(COLUMN() - ($E59 + 5) = 0, $F59, BL59 * (1 - IFERROR(INDEX('Inputs & Assuptions'!$B$13:$B$72, COLUMN() - ($E59 + 5)), 0)) ) )} -> 2866.6675
A60: =A59+1 -> 55 | B60: =IF(MOD($A60-1, 12) = 0, $B59 * 1.05, $B59) -> 7293.0375 | C60: =$B60*(1-'Inputs & Assuptions'!$B$12) -> 4229.9618 | E60: =E59+1 -> 55 | BH60: =+$C60 -> 4229.9618 | BI60: {=IF(COLUMN() - ($E60 + 5) < 0, 0, IF(COLUMN() - ($E60 + 5) = 0, $F60, BH60 * (1 - IFERROR(INDEX('Inputs & Assuptions'!$B$13:$B$72, COLUMN() - ($E60 + 5)), 0)) ) )} -> 3785.8158 | BJ60: {=IF(COLUMN() - ($E60 + 5) < 0, 0, IF(COLUMN() - ($E60 + 5) = 0, $F60, BI60 * (1 - IFERROR(INDEX('Inputs & Assuptions'!$B$13:$B$72, COLUMN() - ($E60 + 5)), 0)) ) )} -> 3482.9505 | BK60: {=IF(COLUMN() - ($E60 + 5) < 0, 0, IF(COLUMN() - ($E60 + 5) = 0, $F60, BJ60 * (1 - IFERROR(INDEX('Inputs & Assuptions'!$B$13:$B$72, COLUMN() - ($E60 + 5)), 0)) ) )} -> 3291.3882 | BL60: {=IF(COLUMN() - ($E60 + 5) < 0, 0, IF(COLUMN() - ($E60 + 5) = 0, $F60, BK60 * (1 - IFERROR(INDEX('Inputs & Assuptions'!$B$13:$B$72, COLUMN() - ($E60 + 5)), 0)) ) )} -> 3126.8188 | BM60: {=IF(COLUMN() - ($E60 + 5) < 0, 0, IF(COLUMN() - ($E60 + 5) = 0, $F60, BL60 * (1 - IFERROR(INDEX('Inputs & Assuptions'!$B$13:$B$72, COLUMN() - ($E60 + 5)), 0)) ) )} -> 2986.112
A61: =A60+1 -> 56 | B61: =IF(MOD($A61-1, 12) = 0, $B60 * 1.05, $B60) -> 7293.0375 | C61: =$B61*(1-'Inputs & Assuptions'!$B$12) -> 4229.9618 | E61: =E60+1 -> 56 | BI61: =+$C61 -> 4229.9618 | BJ61: {=IF(COLUMN() - ($E61 + 5) < 0, 0, IF(COLUMN() - ($E61 + 5) = 0, $F61, BI61 * (1 - IFERROR(INDEX('Inputs & Assuptions'!$B$13:$B$72, COLUMN() - ($E61 + 5)), 0)) ) )} -> 3785.8158 | BK61: {=IF(COLUMN() - ($E61 + 5) < 0, 0, IF(COLUMN() - ($E61 + 5) = 0, $F61, BJ61 * (1 - IFERROR(INDEX('Inputs & Assuptions'!$B$13:$B$72, COLUMN() - ($E61 + 5)), 0)) ) )} -> 3482.9505 | BL61: {=IF(COLUMN() - ($E61 + 5) < 0, 0, IF(COLUMN() - ($E61 + 5) = 0, $F61, BK61 * (1 - IFERROR(INDEX('Inputs & Assuptions'!$B$13:$B$72, COLUMN() - ($E61 + 5)), 0)) ) )} -> 3291.3882 | BM61: {=IF(COLUMN() - ($E61 + 5) < 0, 0, IF(COLUMN() - ($E61 + 5) = 0, $F61, BL61 * (1 - IFERROR(INDEX('Inputs & Assuptions'!$B$13:$B$72, COLUMN() - ($E61 + 5)), 0)) ) )} -> 3126.8188
A62: =A61+1 -> 57 | B62: =IF(MOD($A62-1, 12) = 0, $B61 * 1.05, $B61) -> 7293.0375 | C62: =$B62*(1-'Inputs & Assuptions'!$B$12) -> 4229.9618 | E62: =E61+1 -> 57 | BJ62: =+$C62 -> 4229.9618 | BK62: {=IF(COLUMN() - ($E62 + 5) < 0, 0, IF(COLUMN() - ($E62 + 5) = 0, $F62, BJ62 * (1 - IFERROR(INDEX('Inputs & Assuptions'!$B$13:$B$72, COLUMN() - ($E62 + 5)), 0)) ) )} -> 3785.8158 | BL62: {=IF(COLUMN() - ($E62 + 5) < 0, 0, IF(COLUMN() - ($E62 + 5) = 0, $F62, BK62 * (1 - IFERROR(INDEX('Inputs & Assuptions'!$B$13:$B$72, COLUMN() - ($E62 + 5)), 0)) ) )} -> 3482.9505 | BM62: {=IF(COLUMN() - ($E62 + 5) < 0, 0, IF(COLUMN() - ($E62 + 5) = 0, $F62, BL62 * (1 - IFERROR(INDEX('Inputs & Assuptions'!$B$13:$B$72, COLUMN() - ($E62 + 5)), 0)) ) )} -> 3291.3882
A63: =A62+1 -> 58 | B63: =IF(MOD($A63-1, 12) = 0, $B62 * 1.05, $B62) -> 7293.0375 | C63: =$B63*(1-'Inputs & Assuptions'!$B$12) -> 4229.9618 | E63: =E62+1 -> 58 | BK63: =+$C63 -> 4229.9618 | BL63: {=IF(COLUMN() - ($E63 + 5) < 0, 0, IF(COLUMN() - ($E63 + 5) = 0, $F63, BK63 * (1 - IFERROR(INDEX('Inputs & Assuptions'!$B$13:$B$72, COLUMN() - ($E63 + 5)), 0)) ) )} -> 3785.8158 | BM63: {=IF(COLUMN() - ($E63 + 5) < 0, 0, IF(COLUMN() - ($E63 + 5) = 0, $F63, BL63 * (1 - IFERROR(INDEX('Inputs & Assuptions'!$B$13:$B$72, COLUMN() - ($E63 + 5)), 0)) ) )} -> 3482.9505
A64: =A63+1 -> 59 | B64: =IF(MOD($A64-1, 12) = 0, $B63 * 1.05, $B63) -> 7293.0375 | C64: =$B64*(1-'Inputs & Assuptions'!$B$12) -> 4229.9618 | E64: =E63+1 -> 59 | BL64: =+$C64 -> 4229.9618 | BM64: {=IF(COLUMN() - ($E64 + 5) < 0, 0, IF(COLUMN() - ($E64 + 5) = 0, $F64, BL64 * (1 - IFERROR(INDEX('Inputs & Assuptions'!$B$13:$B$72, COLUMN() - ($E64 + 5)), 0)) ) )} -> 3785.8158
A65: =A64+1 -> 60 | B65: =IF(MOD($A65-1, 12) = 0, $B64 * 1.05, $B64) -> 7293.0375 | C65: =$B65*(1-'Inputs & Assuptions'!$B$12) -> 4229.9618 | E65: =E64+1 -> 60 | BM65: =+$C65 -> 4229.9618
F67: =+SUM(F6:F65) -> 3480 | G67: =+SUM(G6:G65) -> 6594.6 | H67: =+SUM(H6:H65) -> 9460.032 | I67: =+SUM(I6:I65) -> 12167.865 | J67: =+SUM(J6:J65) -> 14740.307 | K67: =+SUM(K6:K65) -> 17196.989 | L67: =+SUM(L6:L65) -> 19555.403 | M67: =+SUM(M6:M65) -> 21831.273 | ... BM67: =+SUM(BM6:BM65) -> 122817.69

Sheet Channel 2 Sales
F2: New Sales | G2: =+'Inputs & Assuptions'!$C$4 -> 1500
F3: Sales Increase | G3: =+'Inputs & Assuptions'!$C$5 -> 0.05
B5: NEW_Monthly_Sales_Inc_NTU | C5: NEW_Monthly_Sales_Exc_NTU | E5: Duration | F5: 1 | G5: =+F5+1 -> 2 | H5: =+G5+1 -> 3 | I5: =+H5+1 -> 4 | J5: =+I5+1 -> 5 | K5: =+J5+1 -> 6 | L5: =+K5+1 -> 7 | M5: =+L5+1 -> 8 | N5: =+M5+1 -> 9 | ... BM5: =+BL5+1 -> 60
A6: 1 | B6: =IF(MOD($A6, 12) = 0, $G$2 * 1.05, $G$2) -> 1500 | C6: =$B6*(1-'Inputs & Assuptions'!$C$12) -> 1170 | E6: 1 | F6: =$C6 -> 1170 | G6: {=IF(COLUMN() - ($E6 + 5) < 0, 0, IF(COLUMN() - ($E6 + 5) = 0, $F6, F6 * (1 - IFERROR(INDEX('Inputs & Assuptions'!$C$13:$C$72, COLUMN() - ($E6 + 5)), 0)) ) )} -> 1108.575 | H6: {=IF(COLUMN() - ($E6 + 5) < 0, 0, IF(COLUMN() - ($E6 + 5) = 0, $F6, G6 * (1 - IFERROR(INDEX('Inputs & Assuptions'!$C$13:$C$72, COLUMN() - ($E6 + 5)), 0)) ) )} -> 1064.232 | I6: {=IF(COLUMN() - ($E6 + 5) < 0, 0, IF(COLUMN() - ($E6 + 5) = 0, $F6, H6 * (1 - IFERROR(INDEX('Inputs & Assuptions'!$C$13:$C$72, COLUMN() - ($E6 + 5)), 0)) ) )} -> 1034.9656 | J6: {=IF(COLUMN() - ($E6 + 5) < 0, 0, IF(COLUMN() - ($E6 + 5) = 0, $F6, I6 * (1 - IFERROR(INDEX('Inputs & Assuptions'!$C$13:$C$72, COLUMN() - ($E6 + 5)), 0)) ) )} -> 1009.0915 | K6: {=IF(COLUMN() - ($E6 + 5) < 0, 0, IF(COLUMN() - ($E6 + 5) = 0, $F6, J6 * (1 - IFERROR(INDEX('Inputs & Assuptions'!$C$13:$C$72, COLUMN() - ($E6 + 5)), 0)) ) )} -> 986.38692 | L6: {=IF(COLUMN() - ($E6 + 5) < 0, 0, IF(COLUMN() - ($E6 + 5) = 0, $F6, K6 * (1 - IFERROR(INDEX('Inputs & Assuptions'!$C$13:$C$72, COLUMN() - ($E6 + 5)), 0)) ) )} -> 966.65918 | M6: {=IF(COLUMN() - ($E6 + 5) < 0, 0, IF(COLUMN() - ($E6 + 5) = 0, $F6, L6 * (1 - IFERROR(INDEX('Inputs & Assuptions'!$C$13:$C$72, COLUMN() - ($E6 + 5)), 0)) ) )} -> 949.74265 | N6: {=IF(COLUMN() - ($E6 + 5) < 0, 0, IF(COLUMN() - ($E6 + 5) = 0, $F6, M6 * (1 - IFERROR(INDEX('Inputs & Assuptions'!$C$13:$C$72, COLUMN() - ($E6 + 5)), 0)) ) )} -> 935.49651 | ... BM6: {=IF(COLUMN() - ($E6 + 5) < 0, 0, IF(COLUMN() - ($E6 + 5) = 0, $F6, BL6 * (1 - IFERROR(INDEX('Inputs & Assuptions'!$C$13:$C$72, COLUMN() - ($E6 + 5)), 0)) ) )} -> 715.39422
A7: =A6+1 -> 2 | B7: =IF(MOD($A7-1, 12) = 0, $B6 * 1.05, $B6) -> 1500 | C7: =$B7*(1-'Inputs & Assuptions'!$C$12) -> 1170 | E7: =E6+1 -> 2 | G7: =$C7 -> 1170 | H7: {=IF(COLUMN() - ($E7 + 5) < 0, 0, IF(COLUMN() - ($E7 + 5) = 0, $F7, G7 * (1 - IFERROR(INDEX('Inputs & Assuptions'!$C$13:$C$72, COLUMN() - ($E7 + 5)), 0)) ) )} -> 1108.575 | I7: {=IF(COLUMN() - ($E7 + 5) < 0, 0, IF(COLUMN() - ($E7 + 5) = 0, $F7, H7 * (1 - IFERROR(INDEX('Inputs & Assuptions'!$C$13:$C$72, COLUMN() - ($E7 + 5)), 0)) ) )} -> 1064.232 | J7: {=IF(COLUMN() - ($E7 + 5) < 0, 0, IF(COLUMN() - ($E7 + 5) = 0, $F7, I7 * (1 - IFERROR(INDEX('Inputs & Assuptions'!$C$13:$C$72, COLUMN() - ($E7 + 5)), 0)) ) )} -> 1034.9656 | K7: {=IF(COLUMN() - ($E7 + 5) < 0, 0, IF(COLUMN() - ($E7 + 5) = 0, $F7, J7 * (1 - IFERROR(INDEX('Inputs & Assuptions'!$C$13:$C$72, COLUMN() - ($E7 + 5)), 0)) ) )} -> 1009.0915 | L7: {=IF(COLUMN() - ($E7 + 5) < 0, 0, IF(COLUMN() - ($E7 + 5) = 0, $F7, K7 * (1 - IFERROR(INDEX('Inputs & Assuptions'!$C$13:$C$72, COLUMN() - ($E7 + 5)), 0)) ) )} -> 986.38692 | M7: {=IF(COLUMN() - ($E7 + 5) < 0, 0, IF(COLUMN() - ($E7 + 5) = 0, $F7, L7 * (1 - IFERROR(INDEX('Inputs & Assuptions'!$C$13:$C$72, COLUMN() - ($E7 + 5)), 0)) ) )} -> 966.65918 | N7: {=IF(COLUMN() - ($E7 + 5) < 0, 0, IF(COLUMN() - ($E7 + 5) = 0, $F7, M7 * (1 - IFERROR(INDEX('Inputs & Assuptions'!$C$13:$C$72, COLUMN() - ($E7 + 5)), 0)) ) )} -> 949.74265 | O7: {=IF(COLUMN() - ($E7 + 5) < 0, 0, IF(COLUMN() - ($E7 + 5) = 0, $F7, N7 * (1 - IFERROR(INDEX('Inputs & Assuptions'!$C$13:$C$72, COLUMN() - ($E7 + 5)), 0)) ) )} -> 935.49651 | ... BM7: {=IF(COLUMN() - ($E7 + 5) < 0, 0, IF(COLUMN() - ($E7 + 5) = 0, $F7, BL7 * (1 - IFERROR(INDEX('Inputs & Assuptions'!$C$13:$C$72, COLUMN() - ($E7 + 5)), 0)) ) )} -> 718.98916
A8: =A7+1 -> 3 | B8: =IF(MOD($A8-1, 12) = 0, $B7 * 1.05, $B7) -> 1500 | C8: =$B8*(1-'Inputs & Assuptions'!$C$12) -> 1170 | E8: =E7+1 -> 3 | H8: =$C8 -> 1170 | I8: {=IF(COLUMN() - ($E8 + 5) < 0, 0, IF(COLUMN() - ($E8 + 5) = 0, $F8, H8 * (1 - IFERROR(INDEX('Inputs & Assuptions'!$C$13:$C$72, COLUMN() - ($E8 + 5)), 0)) ) )} -> 1108.575 | J8: {=IF(COLUMN() - ($E8 + 5) < 0, 0, IF(COLUMN() - ($E8 + 5) = 0, $F8, I8 * (1 - IFERROR(INDEX('Inputs & Assuptions'!$C$13:$C$72, COLUMN() - ($E8 + 5)), 0)) ) )} -> 1064.232 | K8: {=IF(COLUMN() - ($E8 + 5) < 0, 0, IF(COLUMN() - ($E8 + 5) = 0, $F8, J8 * (1 - IFERROR(INDEX('Inputs & Assuptions'!$C$13:$C$72, COLUMN() - ($E8 + 5)), 0)) ) )} -> 1034.9656 | L8: {=IF(COLUMN() - ($E8 + 5) < 0, 0, IF(COLUMN() - ($E8 + 5) = 0, $F8, K8 * (1 - IFERROR(INDEX('Inputs & Assuptions'!$C$13:$C$72, COLUMN() - ($E8 + 5)), 0)) ) )} -> 1009.0915 | M8: {=IF(COLUMN() - ($E8 + 5) < 0, 0, IF(COLUMN() - ($E8 + 5) = 0, $F8, L8 * (1 - IFERROR(INDEX('Inputs & Assuptions'!$C$13:$C$72, COLUMN() - ($E8 + 5)), 0)) ) )} -> 986.38692 | N8: {=IF(COLUMN() - ($E8 + 5) < 0, 0, IF(COLUMN() - ($E8 + 5) = 0, $F8, M8 * (1 - IFERROR(INDEX('Inputs & Assuptions'!$C$13:$C$72, COLUMN() - ($E8 + 5)), 0)) ) )} -> 966.65918 | O8: {=IF(COLUMN() - ($E8 + 5) < 0, 0, IF(COLUMN() - ($E8 + 5) = 0, $F8, N8 * (1 - IFERROR(INDEX('Inputs & Assuptions'!$C$13:$C$72, COLUMN() - ($E8 + 5)), 0)) ) )} -> 949.74265 | P8: {=IF(COLUMN() - ($E8 + 5) < 0, 0, IF(COLUMN() - ($E8 + 5) = 0, $F8, O8 * (1 - IFERROR(INDEX('Inputs & Assuptions'!$C$13:$C$72, COLUMN() - ($E8 + 5)), 0)) ) )} -> 935.49651 | ... BM8: {=IF(COLUMN() - ($E8 + 5) < 0, 0, IF(COLUMN() - ($E8 + 5) = 0, $F8, BL8 * (1 - IFERROR(INDEX('Inputs & Assuptions'!$C$13:$C$72, COLUMN() - ($E8 + 5)), 0)) ) )} -> 722.60217
A9: =A8+1 -> 4 | B9: =IF(MOD($A9-1, 12) = 0, $B8 * 1.05, $B8) -> 1500 | C9: =$B9*(1-'Inputs & Assuptions'!$C$12) -> 1170 | E9: =E8+1 -> 4 | I9: =$C9 -> 1170 | J9: =$C9 -> 1170 | K9: {=IF(COLUMN() - ($E9 + 5) < 0, 0, IF(COLUMN() - ($E9 + 5) = 0, $F9, J9 * (1 - IFERROR(INDEX('Inputs & Assuptions'!$C$13:$C$72, COLUMN() - ($E9 + 5)), 0)) ) )} -> 1123.2 | L9: {=IF(COLUMN() - ($E9 + 5) < 0, 0, IF(COLUMN() - ($E9 + 5) = 0, $F9, K9 * (1 - IFERROR(INDEX('Inputs & Assuptions'!$C$13:$C$72, COLUMN() - ($E9 + 5)), 0)) ) )} -> 1092.312 | M9: {=IF(COLUMN() - ($E9 + 5) < 0, 0, IF(COLUMN() - ($E9 + 5) = 0, $F9, L9 * (1 - IFERROR(INDEX('Inputs & Assuptions'!$C$13:$C$72, COLUMN() - ($E9 + 5)), 0)) ) )} -> 1065.0042 | N9: {=IF(COLUMN() - ($E9 + 5) < 0, 0, IF(COLUMN() - ($E9 + 5) = 0, $F9, M9 * (1 - IFERROR(INDEX('Inputs & Assuptions'!$C$13:$C$72, COLUMN() - ($E9 + 5)), 0)) ) )} -> 1041.0416 | O9: {=IF(COLUMN() - ($E9 + 5) < 0, 0, IF(COLUMN() - ($E9 + 5) = 0, $F9, N9 * (1 - IFERROR(INDEX('Inputs & Assuptions'!$C$13:$C$72, COLUMN() - ($E9 + 5)), 0)) ) )} -> 1020.2208 | P9: {=IF(COLUMN() - ($E9 + 5) < 0, 0, IF(COLUMN() - ($E9 + 5) = 0, $F9, O9 * (1 - IFERROR(INDEX('Inputs & Assuptions'!$C$13:$C$72, COLUMN() - ($E9 + 5)), 0)) ) )} -> 1002.3669 | Q9: {=IF(COLUMN() - ($E9 + 5) < 0, 0, IF(COLUMN() - ($E9 + 5) = 0, $F9, P9 * (1 - IFERROR(INDEX('Inputs & Assuptions'!$C$13:$C$72, COLUMN() - ($E9 + 5)), 0)) ) )} -> 987.33141 | R9: {=IF(COLUMN() - ($E9 + 5) < 0, 0, IF(COLUMN() - ($E9 + 5) = 0, $F9, Q9 * (1 - IFERROR(INDEX('Inputs & Assuptions'!$C$13:$C$72, COLUMN() - ($E9 + 5)), 0)) ) )} -> 974.98976 | ... BM9: {=IF(COLUMN() - ($E9 + 5) < 0, 0, IF(COLUMN() - ($E9 + 5) = 0, $F9, BL9 * (1 - IFERROR(INDEX('Inputs & Assuptions'!$C$13:$C$72, COLUMN() - ($E9 + 5)), 0)) ) )} -> 766.47318
A10: =A9+1 -> 5 | B10: =IF(MOD($A10-1, 12) = 0, $B9 * 1.05, $B9) -> 1500 | C10: =$B10*(1-'Inputs & Assuptions'!$C$12) -> 1170 | E10: =E9+1 -> 5 | I10: =$C10 -> 1170 | J10: =$B10*(1-'Inputs & Assuptions'!$C$12) -> 1170 | K10: {=IF(COLUMN() - ($E10 + 5) < 0, 0, IF(COLUMN() - ($E10 + 5) = 0, $F10, J10 * (1 - IFERROR(INDEX('Inputs & Assuptions'!$C$13:$C$72, COLUMN() - ($E10 + 5)), 0)) ) )} -> 1108.575 | L10: {=IF(COLUMN() - ($E10 + 5) < 0, 0, IF(COLUMN() - ($E10 + 5) = 0, $F10, K10 * (1 - IFERROR(INDEX('Inputs & Assuptions'!$C$13:$C$72, COLUMN() - ($E10 + 5)), 0)) ) )} -> 1064.232 | M10: {=IF(COLUMN() - ($E10 + 5) < 0, 0, IF(COLUMN() - ($E10 + 5) = 0, $F10, L10 * (1 - IFERROR(INDEX('Inputs & Assuptions'!$C$13:$C$72, COLUMN() - ($E10 + 5)), 0)) ) )} -> 1034.9656 | N10: {=IF(COLUMN() - ($E10 + 5) < 0, 0, IF(COLUMN() - ($E10 + 5) = 0, $F10, M10 * (1 - IFERROR(INDEX('Inputs & Assuptions'!$C$13:$C$72, COLUMN() - ($E10 + 5)), 0)) ) )} -> 1009.0915 | O10: {=IF(COLUMN() - ($E10 + 5) < 0, 0, IF(COLUMN() - ($E10 + 5) = 0, $F10, N10 * (1 - IFERROR(INDEX('Inputs & Assuptions'!$C$13:$C$72, COLUMN() - ($E10 + 5)), 0)) ) )} -> 986.38692 | P10: {=IF(COLUMN() - ($E10 + 5) < 0, 0, IF(COLUMN() - ($E10 + 5) = 0, $F10, O10 * (1 - IFERROR(INDEX('Inputs & Assuptions'!$C$13:$C$72, COLUMN() - ($E10 + 5)), 0)) ) )} -> 966.65918 | Q10: {=IF(COLUMN() - ($E10 + 5) < 0, 0, IF(COLUMN() - ($E10 + 5) = 0, $F10, P10 * (1 - IFERROR(INDEX('Inputs & Assuptions'!$C$13:$C$72, COLUMN() - ($E10 + 5)), 0)) ) )} -> 949.74265 | R10: {=IF(COLUMN() - ($E10 + 5) < 0, 0, IF(COLUMN() - ($E10 + 5) = 0, $F10, Q10 * (1 - IFERROR(INDEX('Inputs & Assuptions'!$C$13:$C$72, COLUMN() - ($E10 + 5)), 0)) ) )} -> 935.49651 | ... BM10: {=IF(COLUMN() - ($E10 + 5) < 0, 0, IF(COLUMN() - ($E10 + 5) = 0, $F10, BL10 * (1 - IFERROR(INDEX('Inputs & Assuptions'!$C$13:$C$72, COLUMN() - ($E10 + 5)), 0)) ) )} -> 729.88276
A11: =A10+1 -> 6 | B11: =IF(MOD($A11-1, 12) = 0, $B10 * 1.05, $B10) -> 1500 | C11: =$B11*(1-'Inputs & Assuptions'!$C$12) -> 1170 | E11: =E10+1 -> 6 | K11: =$C11 -> 1170 | L11: {=IF(COLUMN() - ($E11 + 5) < 0, 0, IF(COLUMN() - ($E11 + 5) = 0, $F11, K11 * (1 - IFERROR(INDEX('Inputs & Assuptions'!$C$13:$C$72, COLUMN() - ($E11 + 5)), 0)) ) )} -> 1108.575 | M11: {=IF(COLUMN() - ($E11 + 5) < 0, 0, IF(COLUMN() - ($E11 + 5) = 0, $F11, L11 * (1 - IFERROR(INDEX('Inputs & Assuptions'!$C$13:$C$72, COLUMN() - ($E11 + 5)), 0)) ) )} -> 1064.232 | N11: {=IF(COLUMN() - ($E11 + 5) < 0, 0, IF(COLUMN() - ($E11 + 5) = 0, $F11, M11 * (1 - IFERROR(INDEX('Inputs & Assuptions'!$C$13:$C$72, COLUMN() - ($E11 + 5)), 0)) ) )} -> 1034.9656 | O11: {=IF(COLUMN() - ($E11 + 5) < 0, 0, IF(COLUMN() - ($E11 + 5) = 0, $F11, N11 * (1 - IFERROR(INDEX('Inputs & Assuptions'!$C$13:$C$72, COLUMN() - ($E11 + 5)), 0)) ) )} -> 1009.0915 | P11: {=IF(COLUMN() - ($E11 + 5) < 0, 0, IF(COLUMN() - ($E11 + 5) = 0, $F11, O11 * (1 - IFERROR(INDEX('Inputs & Assuptions'!$C$13:$C$72, COLUMN() - ($E11 + 5)), 0)) ) )} -> 986.38692 | Q11: {=IF(COLUMN() - ($E11 + 5) < 0, 0, IF(COLUMN() - ($E11 + 5) = 0, $F11, P11 * (1 - IFERROR(INDEX('Inputs & Assuptions'!$C$13:$C$72, COLUMN() - ($E11 + 5)), 0)) ) )} -> 966.65918 | R11: {=IF(COLUMN() - ($E11 + 5) < 0, 0, IF(COLUMN() - ($E11 + 5) = 0, $F11, Q11 * (1 - IFERROR(INDEX('Inputs & Assuptions'!$C$13:$C$72, COLUMN() - ($E11 + 5)), 0)) ) )} -> 949.74265 | S11: {=IF(COLUMN() - ($E11 + 5) < 0, 0, IF(COLUMN() - ($E11 + 5) = 0, $F11, R11 * (1 - IFERROR(INDEX('Inputs & Assuptions'!$C$13:$C$72, COLUMN() - ($E11 + 5)), 0)) ) )} -> 935.49651 | ... BM11: {=IF(COLUMN() - ($E11 + 5) < 0, 0, IF(COLUMN() - ($E11 + 5) = 0, $F11, BL11 * (1 - IFERROR(INDEX('Inputs & Assuptions'!$C$13:$C$72, COLUMN() - ($E11 + 5)), 0)) ) )} -> 733.55051
A12: =A11+1 -> 7 | B12: =IF(MOD($A12-1, 12) = 0, $B11 * 1.05, $B11) -> 1500 | C12: =$B12*(1-'Inputs & Assuptions'!$C$12) -> 1170 | E12: =E11+1 -> 7 | L12: =$C12 -> 1170 | M12: {=IF(COLUMN() - ($E12 + 5) < 0, 0, IF(COLUMN() - ($E12 + 5) = 0, $F12, L12 * (1 - IFERROR(INDEX('Inputs & Assuptions'!$C$13:$C$72, COLUMN() - ($E12 + 5)), 0)) ) )} -> 1108.575 | N12: {=IF(COLUMN() - ($E12 + 5) < 0, 0, IF(COLUMN() - ($E12 + 5) = 0, $F12, M12 * (1 - IFERROR(INDEX('Inputs & Assuptions'!$C$13:$C$72, COLUMN() - ($E12 + 5)), 0)) ) )} -> 1064.232 | O12: {=IF(COLUMN() - ($E12 + 5) < 0, 0, IF(COLUMN() - ($E12 + 5) = 0, $F12, N12 * (1 - IFERROR(INDEX('Inputs & Assuptions'!$C$13:$C$72, COLUMN() - ($E12 + 5)), 0)) ) )} -> 1034.9656 | P12: {=IF(COLUMN() - ($E12 + 5) < 0, 0, IF(COLUMN() - ($E12 + 5) = 0, $F12, O12 * (1 - IFERROR(INDEX('Inputs & Assuptions'!$C$13:$C$72, COLUMN() - ($E12 + 5)), 0)) ) )} -> 1009.0915 | Q12: {=IF(COLUMN() - ($E12 + 5) < 0, 0, IF(COLUMN() - ($E12 + 5) = 0, $F12, P12 * (1 - IFERROR(INDEX('Inputs & Assuptions'!$C$13:$C$72, COLUMN() - ($E12 + 5)), 0)) ) )} -> 986.38692 | R12: {=IF(COLUMN() - ($E12 + 5) < 0, 0, IF(COLUMN() - ($E12 + 5) = 0, $F12, Q12 * (1 - IFERROR(INDEX('Inputs & Assuptions'!$C$13:$C$72, COLUMN() - ($E12 + 5)), 0)) ) )} -> 966.65918 | S12: {=IF(COLUMN() - ($E12 + 5) < 0, 0, IF(COLUMN() - ($E12 + 5) = 0, $F12, R12 * (1 - IFERROR(INDEX('Inputs & Assuptions'!$C$13:$C$72, COLUMN() - ($E12 + 5)), 0)) ) )} -> 949.74265 | T12: {=IF(COLUMN() - ($E12 + 5) < 0, 0, IF(COLUMN() - ($E12 + 5) = 0, $F12, S12 * (1 - IFERROR(INDEX('Inputs & Assuptions'!$C$13:$C$72, COLUMN() - ($E12 + 5)), 0)) ) )} -> 935.49651 | ... BM12: {=IF(COLUMN() - ($E12 + 5) < 0, 0, IF(COLUMN() - ($E12 + 5) = 0, $F12, BL12 * (1 - IFERROR(INDEX('Inputs & Assuptions'!$C$13:$C$72, COLUMN() - ($E12 + 5)), 0)) ) )} -> 737.23669
A13: =A12+1 -> 8 | B13: =IF(MOD($A13-1, 12) = 0, $B12 * 1.05, $B12) -> 1500 | C13: =$B13*(1-'Inputs & Assuptions'!$C$12) -> 1170 | E13: =E12+1 -> 8 | M13: =$C13 -> 1170 | N13: {=IF(COLUMN() - ($E13 + 5) < 0, 0, IF(COLUMN() - ($E13 + 5) = 0, $F13, M13 * (1 - IFERROR(INDEX('Inputs & Assuptions'!$C$13:$C$72, COLUMN() - ($E13 + 5)), 0)) ) )} -> 1108.575 | O13: {=IF(COLUMN() - ($E13 + 5) < 0, 0, IF(COLUMN() - ($E13 + 5) = 0, $F13, N13 * (1 - IFERROR(INDEX('Inputs & Assuptions'!$C$13:$C$72, COLUMN() - ($E13 + 5)), 0)) ) )} -> 1064.232 | P13: {=IF(COLUMN() - ($E13 + 5) < 0, 0, IF(COLUMN() - ($E13 + 5) = 0, $F13, O13 * (1 - IFERROR(INDEX('Inputs & Assuptions'!$C$13:$C$72, COLUMN() - ($E13 + 5)), 0)) ) )} -> 1034.9656 | Q13: {=IF(COLUMN() - ($E13 + 5) < 0, 0, IF(COLUMN() - ($E13 + 5) = 0, $F13, P13 * (1 - IFERROR(INDEX('Inputs & Assuptions'!$C$13:$C$72, COLUMN() - ($E13 + 5)), 0)) ) )} -> 1009.0915 | R13: {=IF(COLUMN() - ($E13 + 5) < 0, 0, IF(COLUMN() - ($E13 + 5) = 0, $F13, Q13 * (1 - IFERROR(INDEX('Inputs & Assuptions'!$C$13:$C$72, COLUMN() - ($E13 + 5)), 0)) ) )} -> 986.38692 | S13: {=IF(COLUMN() - ($E13 + 5) < 0, 0, IF(COLUMN() - ($E13 + 5) = 0, $F13, R13 * (1 - IFERROR(INDEX('Inputs & Assuptions'!$C$13:$C$72, COLUMN() - ($E13 + 5)), 0)) ) )} -> 966.65918 | T13: {=IF(COLUMN() - ($E13 + 5) < 0, 0, IF(COLUMN() - ($E13 + 5) = 0, $F13, S13 * (1 - IFERROR(INDEX('Inputs & Assuptions'!$C$13:$C$72, COLUMN() - ($E13 + 5)), 0)) ) )} -> 949.74265 | U13: {=IF(COLUMN() - ($E13 + 5) < 0, 0, IF(COLUMN() - ($E13 + 5) = 0, $F13, T13 * (1 - IFERROR(INDEX('Inputs & Assuptions'!$C$13:$C$72, COLUMN() - ($E13 + 5)), 0)) ) )} -> 935.49651 | ... BM13: {=IF(COLUMN() - ($E13 + 5) < 0, 0, IF(COLUMN() - ($E13 + 5) = 0, $F13, BL13 * (1 - IFERROR(INDEX('Inputs & Assuptions'!$C$13:$C$72, COLUMN() - ($E13 + 5)), 0)) ) )} -> 740.9414
A14: =A13+1 -> 9 | B14: =IF(MOD($A14-1, 12) = 0, $B13 * 1.05, $B13) -> 1500 | C14: =$B14*(1-'Inputs & Assuptions'!$C$12) -> 1170 | E14: =E13+1 -> 9 | N14: =$C14 -> 1170 | O14: {=IF(COLUMN() - ($E14 + 5) < 0, 0, IF(COLUMN() - ($E14 + 5) = 0, $F14, N14 * (1 - IFERROR(INDEX('Inputs & Assuptions'!$C$13:$C$72, COLUMN() - ($E14 + 5)), 0)) ) )} -> 1108.575 | P14: {=IF(COLUMN() - ($E14 + 5) < 0, 0, IF(COLUMN() - ($E14 + 5) = 0, $F14, O14 * (1 - IFERROR(INDEX('Inputs & Assuptions'!$C$13:$C$72, COLUMN() - ($E14 + 5)), 0)) ) )} -> 1064.232 | Q14: {=IF(COLUMN() - ($E14 + 5) < 0, 0, IF(COLUMN() - ($E14 + 5) = 0, $F14, P14 * (1 - IFERROR(INDEX('Inputs & Assuptions'!$C$13:$C$72, COLUMN() - ($E14 + 5)), 0)) ) )} -> 1034.9656 | R14: {=IF(COLUMN() - ($E14 + 5) < 0, 0, IF(COLUMN() - ($E14 + 5) = 0, $F14, Q14 * (1 - IFERROR(INDEX('Inputs & Assuptions'!$C$13:$C$72, COLUMN() - ($E14 + 5)), 0)) ) )} -> 1009.0915 | S14: {=IF(COLUMN() - ($E14 + 5) < 0, 0, IF(COLUMN() - ($E14 + 5) = 0, $F14, R14 * (1 - IFERROR(INDEX('Inputs & Assuptions'!$C$13:$C$72, COLUMN() - ($E14 + 5)), 0)) ) )} -> 986.38692 | T14: {=IF(COLUMN() - ($E14 + 5) < 0, 0, IF(COLUMN() - ($E14 + 5) = 0, $F14, S14 * (1 - IFERROR(INDEX('Inputs & Assuptions'!$C$13:$C$72, COLUMN() - ($E14 + 5)), 0)) ) )} -> 966.65918 | U14: {=IF(COLUMN() - ($E14 + 5) < 0, 0, IF(COLUMN() - ($E14 + 5) = 0, $F14, T14 * (1 - IFERROR(INDEX('Inputs & Assuptions'!$C$13:$C$72, COLUMN() - ($E14 + 5)), 0)) ) )} -> 949.74265 | V14: {=IF(COLUMN() - ($E14 + 5) < 0, 0, IF(COLUMN() - ($E14 + 5) = 0, $F14, U14 * (1 - IFERROR(INDEX('Inputs & Assuptions'!$C$13:$C$72, COLUMN() - ($E14 + 5)), 0)) ) )} -> 935.49651 | ... BM14: {=IF(COLUMN() - ($E14 + 5) < 0, 0, IF(COLUMN() - ($E14 + 5) = 0, $F14, BL14 * (1 - IFERROR(INDEX('Inputs & Assuptions'!$C$13:$C$72, COLUMN() - ($E14 + 5)), 0)) ) )} -> 744.66472
A15: =A14+1 -> 10 | B15: =IF(MOD($A15-1, 12) = 0, $B14 * 1.05, $B14) -> 1500 | C15: =$B15*(1-'Inputs & Assuptions'!$C$12) -> 1170 | E15: =E14+1 -> 10 | O15: =$C15 -> 1170 | P15: {=IF(COLUMN() - ($E15 + 5) < 0, 0, IF(COLUMN() - ($E15 + 5) = 0, $F15, O15 * (1 - IFERROR(INDEX('Inputs & Assuptions'!$C$13:$C$72, COLUMN() - ($E15 + 5)), 0)) ) )} -> 1108.575 | Q15: {=IF(COLUMN() - ($E15 + 5) < 0, 0, IF(COLUMN() - ($E15 + 5) = 0, $F15, P15 * (1 - IFERROR(INDEX('Inputs & Assuptions'!$C$13:$C$72, COLUMN() - ($E15 + 5)), 0)) ) )} -> 1064.232 | R15: {=IF(COLUMN() - ($E15 + 5) < 0, 0, IF(COLUMN() - ($E15 + 5) = 0, $F15, Q15 * (1 - IFERROR(INDEX('Inputs & Assuptions'!$C$13:$C$72, COLUMN() - ($E15 + 5)), 0)) ) )} -> 1034.9656 | S15: {=IF(COLUMN() - ($E15 + 5) < 0, 0, IF(COLUMN() - ($E15 + 5) = 0, $F15, R15 * (1 - IFERROR(INDEX('Inputs & Assuptions'!$C$13:$C$72, COLUMN() - ($E15 + 5)), 0)) ) )} -> 1009.0915 | T15: {=IF(COLUMN() - ($E15 + 5) < 0, 0, IF(COLUMN() - ($E15 + 5) = 0, $F15, S15 * (1 - IFERROR(INDEX('Inputs & Assuptions'!$C$13:$C$72, COLUMN() - ($E15 + 5)), 0)) ) )} -> 986.38692 | U15: {=IF(COLUMN() - ($E15 + 5) < 0, 0, IF(COLUMN() - ($E15 + 5) = 0, $F15, T15 * (1 - IFERROR(INDEX('Inputs & Assuptions'!$C$13:$C$72, COLUMN() - ($E15 + 5)), 0)) ) )} -> 966.65918 | V15: {=IF(COLUMN() - ($E15 + 5) < 0, 0, IF(COLUMN() - ($E15 + 5) = 0, $F15, U15 * (1 - IFERROR(INDEX('Inputs & Assuptions'!$C$13:$C$72, COLUMN() - ($E15 + 5)), 0)) ) )} -> 949.74265 | W15: {=IF(COLUMN() - ($E15 + 5) < 0, 0, IF(COLUMN() - ($E15 + 5) = 0, $F15, V15 * (1 - IFERROR(INDEX('Inputs & Assuptions'!$C$13:$C$72, COLUMN() - ($E15 + 5)), 0)) ) )} -> 935.49651 | ... BM15: {=IF(COLUMN() - ($E15 + 5) < 0, 0, IF(COLUMN() - ($E15 + 5) = 0, $F15, BL15 * (1 - IFERROR(INDEX('Inputs & Assuptions'!$C$13:$C$72, COLUMN() - ($E15 + 5)), 0)) ) )} -> 748.40676
A16: =A15+1 -> 11 | B16: =IF(MOD($A16-1, 12) = 0, $B15 * 1.05, $B15) -> 1500 | C16: =$B16*(1-'Inputs & Assuptions'!$C$12) -> 1170 | E16: =E15+1 -> 11 | P16: =$C16 -> 1170 | Q16: {=IF(COLUMN() - ($E16 + 5) < 0, 0, IF(COLUMN() - ($E16 + 5) = 0, $F16, P16 * (1 - IFERROR(INDEX('Inputs & Assuptions'!$C$13:$C$72, COLUMN() - ($E16 + 5)), 0)) ) )} -> 1108.575 | R16: {=IF(COLUMN() - ($E16 + 5) < 0, 0, IF(COLUMN() - ($E16 + 5) = 0, $F16, Q16 * (1 - IFERROR(INDEX('Inputs & Assuptions'!$C$13:$C$72, COLUMN() - ($E16 + 5)), 0)) ) )} -> 1064.232 | S16: {=IF(COLUMN() - ($E16 + 5) < 0, 0, IF(COLUMN() - ($E16 + 5) = 0, $F16, R16 * (1 - IFERROR(INDEX('Inputs & Assuptions'!$C$13:$C$72, COLUMN() - ($E16 + 5)), 0)) ) )} -> 1034.9656 | T16: {=IF(COLUMN() - ($E16 + 5) < 0, 0, IF(COLUMN() - ($E16 + 5) = 0, $F16, S16 * (1 - IFERROR(INDEX('Inputs & Assuptions'!$C$13:$C$72, COLUMN() - ($E16 + 5)), 0)) ) )} -> 1009.0915 | U16: {=IF(COLUMN() - ($E16 + 5) < 0, 0, IF(COLUMN() - ($E16 + 5) = 0, $F16, T16 * (1 - IFERROR(INDEX('Inputs & Assuptions'!$C$13:$C$72, COLUMN() - ($E16 + 5)), 0)) ) )} -> 986.38692 | V16: {=IF(COLUMN() - ($E16 + 5) < 0, 0, IF(COLUMN() - ($E16 + 5) = 0, $F16, U16 * (1 - IFERROR(INDEX('Inputs & Assuptions'!$C$13:$C$72, COLUMN() - ($E16 + 5)), 0)) ) )} -> 966.65918 | W16: {=IF(COLUMN() - ($E16 + 5) < 0, 0, IF(COLUMN() - ($E16 + 5) = 0, $F16, V16 * (1 - IFERROR(INDEX('Inputs & Assuptions'!$C$13:$C$72, COLUMN() - ($E16 + 5)), 0)) ) )} -> 949.74265 | X16: {=IF(COLUMN() - ($E16 + 5) < 0, 0, IF(COLUMN() - ($E16 + 5) = 0, $F16, W16 * (1 - IFERROR(INDEX('Inputs & Assuptions'!$C$13:$C$72, COLUMN() - ($E16 + 5)), 0)) ) )} -> 935.49651 | ... BM16: {=IF(COLUMN() - ($E16 + 5) < 0, 0, IF(COLUMN() - ($E16 + 5) = 0, $F16, BL16 * (1 - IFERROR(INDEX('Inputs & Assuptions'!$C$13:$C$72, COLUMN() - ($E16 + 5)), 0)) ) )} -> 752.16759
A17: =A16+1 -> 12 | B17: =IF(MOD($A17-1, 12) = 0, $B16 * 1.05, $B16) -> 1500 | C17: =$B17*(1-'Inputs & Assuptions'!$C$12) -> 1170 | E17: =E16+1 -> 12 | Q17: =$C17 -> 1170 | R17: {=IF(COLUMN() - ($E17 + 5) < 0, 0, IF(COLUMN() - ($E17 + 5) = 0, $F17, Q17 * (1 - IFERROR(INDEX('Inputs & Assuptions'!$C$13:$C$72, COLUMN() - ($E17 + 5)), 0)) ) )} -> 1108.575 | S17: {=IF(COLUMN() - ($E17 + 5) < 0, 0, IF(COLUMN() - ($E17 + 5) = 0, $F17, R17 * (1 - IFERROR(INDEX('Inputs & Assuptions'!$C$13:$C$72, COLUMN() - ($E17 + 5)), 0)) ) )} -> 1064.232 | T17: {=IF(COLUMN() - ($E17 + 5) < 0, 0, IF(COLUMN() - ($E17 + 5) = 0, $F17, S17 * (1 - IFERROR(INDEX('Inputs & Assuptions'!$C$13:$C$72, COLUMN() - ($E17 + 5)), 0)) ) )} -> 1034.9656 | U17: {=IF(COLUMN() - ($E17 + 5) < 0, 0, IF(COLUMN() - ($E17 + 5) = 0, $F17, T17 * (1 - IFERROR(INDEX('Inputs & Assuptions'!$C$13:$C$72, COLUMN() - ($E17 + 5)), 0)) ) )} -> 1009.0915 | V17: {=IF(COLUMN() - ($E17 + 5) < 0, 0, IF(COLUMN() - ($E17 + 5) = 0, $F17, U17 * (1 - IFERROR(INDEX('Inputs & Assuptions'!$C$13:$C$72, COLUMN() - ($E17 + 5)), 0)) ) )} -> 986.38692 | W17: {=IF(COLUMN() - ($E17 + 5) < 0, 0, IF(COLUMN() - ($E17 + 5) = 0, $F17, V17 * (1 - IFERROR(INDEX('Inputs & Assuptions'!$C$13:$C$72, COLUMN() - ($E17 + 5)), 0)) ) )} -> 966.65918 | X17: {=IF(COLUMN() - ($E17 + 5) < 0, 0, IF(COLUMN() - ($E17 + 5) = 0, $F17, W17 * (1 - IFERROR(INDEX('Inputs & Assuptions'!$C$13:$C$72, COLUMN() - ($E17 + 5)), 0)) ) )} -> 949.74265 | Y17: {=IF(COLUMN() - ($E17 + 5) < 0, 0, IF(COLUMN() - ($E17 + 5) = 0, $F17, X17 * (1 - IFERROR(INDEX('Inputs & Assuptions'!$C$13:$C$72, COLUMN() - ($E17 + 5)), 0)) ) )} -> 935.49651 | ... BM17: {=IF(COLUMN() - ($E17 + 5) < 0, 0, IF(COLUMN() - ($E17 + 5) = 0, $F17, BL17 * (1 - IFERROR(INDEX('Inputs & Assuptions'!$C$13:$C$72, COLUMN() - ($E17 + 5)), 0)) ) )} -> 755.94733
A18: =A17+1 -> 13 | B18: =IF(MOD($A18-1, 12) = 0, $B17 * 1.05, $B17) -> 1575 | C18: =$B18*(1-'Inputs & Assuptions'!$C$12) -> 1228.5 | E18: =E17+1 -> 13 | R18: =$C18 -> 1228.5 | S18: {=IF(COLUMN() - ($E18 + 5) < 0, 0, IF(COLUMN() - ($E18 + 5) = 0, $F18, R18 * (1 - IFERROR(INDEX('Inputs & Assuptions'!$C$13:$C$72, COLUMN() - ($E18 + 5)), 0)) ) )} -> 1164.0038 | T18: {=IF(COLUMN() - ($E18 + 5) < 0, 0, IF(COLUMN() - ($E18 + 5) = 0, $F18, S18 * (1 - IFERROR(INDEX('Inputs & Assuptions'!$C$13:$C$72, COLUMN() - ($E18 + 5)), 0)) ) )} -> 1117.4436 | U18: {=IF(COLUMN() - ($E18 + 5) < 0, 0, IF(COLUMN() - ($E18 + 5) = 0, $F18, T18 * (1 - IFERROR(INDEX('Inputs & Assuptions'!$C$13:$C$72, COLUMN() - ($E18 + 5)), 0)) ) )} -> 1086.7139 | V18: {=IF(COLUMN() - ($E18 + 5) < 0, 0, IF(COLUMN() - ($E18 + 5) = 0, $F18, U18 * (1 - IFERROR(INDEX('Inputs & Assuptions'!$C$13:$C$72, COLUMN() - ($E18 + 5)), 0)) ) )} -> 1059.5461 | W18: {=IF(COLUMN() - ($E18 + 5) < 0, 0, IF(COLUMN() - ($E18 + 5) = 0, $F18, V18 * (1 - IFERROR(INDEX('Inputs & Assuptions'!$C$13:$C$72, COLUMN() - ($E18 + 5)), 0)) ) )} -> 1035.7063 | X18: {=IF(COLUMN() - ($E18 + 5) < 0, 0, IF(COLUMN() - ($E18 + 5) = 0, $F18, W18 * (1 - IFERROR(INDEX('Inputs & Assuptions'!$C$13:$C$72, COLUMN() - ($E18 + 5)), 0)) ) )} -> 1014.9921 | Y18: {=IF(COLUMN() - ($E18 + 5) < 0, 0, IF(COLUMN() - ($E18 + 5) = 0, $F18, X18 * (1 - IFERROR(INDEX('Inputs & Assuptions'!$C$13:$C$72, COLUMN() - ($E18 + 5)), 0)) ) )} -> 997.22978 | Z18: {=IF(COLUMN() - ($E18 + 5) < 0, 0, IF(COLUMN() - ($E18 + 5) = 0, $F18, Y18 * (1 - IFERROR(INDEX('Inputs & Assuptions'!$C$13:$C$72, COLUMN() - ($E18 + 5)), 0)) ) )} -> 982.27133 | ... BM18: {=IF(COLUMN() - ($E18 + 5) < 0, 0, IF(COLUMN() - ($E18 + 5) = 0, $F18, BL18 * (1 - IFERROR(INDEX('Inputs & Assuptions'!$C$13:$C$72, COLUMN() - ($E18 + 5)), 0)) ) )} -> 797.73336
A19: =A18+1 -> 14 | B19: =IF(MOD($A19-1, 12) = 0, $B18 * 1.05, $B18) -> 1575 | C19: =$B19*(1-'Inputs & Assuptions'!$C$12) -> 1228.5 | E19: =E18+1 -> 14 | S19: =$C19 -> 1228.5 | T19: {=IF(COLUMN() - ($E19 + 5) < 0, 0, IF(COLUMN() - ($E19 + 5) = 0, $F19, S19 * (1 - IFERROR(INDEX('Inputs & Assuptions'!$C$13:$C$72, COLUMN() - ($E19 + 5)), 0)) ) )} -> 1164.0038 | U19: {=IF(COLUMN() - ($E19 + 5) < 0, 0, IF(COLUMN() - ($E19 + 5) = 0, $F19, T19 * (1 - IFERROR(INDEX('Inputs & Assuptions'!$C$13:$C$72, COLUMN() - ($E19 + 5)), 0)) ) )} -> 1117.4436 | V19: {=IF(COLUMN() - ($E19 + 5) < 0, 0, IF(COLUMN() - ($E19 + 5) = 0, $F19, U19 * (1 - IFERROR(INDEX('Inputs & Assuptions'!$C$13:$C$72, COLUMN() - ($E19 + 5)), 0)) ) )} -> 1086.7139 | W19: {=IF(COLUMN() - ($E19 + 5) < 0, 0, IF(COLUMN() - ($E19 + 5) = 0, $F19, V19 * (1 - IFERROR(INDEX('Inputs & Assuptions'!$C$13:$C$72, COLUMN() - ($E19 + 5)), 0)) ) )} -> 1059.5461 | X19: {=IF(COLUMN() - ($E19 + 5) < 0, 0, IF(COLUMN() - ($E19 + 5) = 0, $F19, W19 * (1 - IFERROR(INDEX('Inputs & Assuptions'!$C$13:$C$72, COLUMN() - ($E19 + 5)), 0)) ) )} -> 1035.7063 | Y19: {=IF(COLUMN() - ($E19 + 5) < 0, 0, IF(COLUMN() - ($E19 + 5) = 0, $F19, X19 * (1 - IFERROR(INDEX('Inputs & Assuptions'!$C$13:$C$72, COLUMN() - ($E19 + 5)), 0)) ) )} -> 1014.9921 | Z19: {=IF(COLUMN() - ($E19 + 5) < 0, 0, IF(COLUMN() - ($E19 + 5) = 0, $F19, Y19 * (1 - IFERROR(INDEX('Inputs & Assuptions'!$C$13:$C$72, COLUMN() - ($E19 + 5)), 0)) ) )} -> 997.22978 | AA19: {=IF(COLUMN() - ($E19 + 5) < 0, 0, IF(COLUMN() - ($E19 + 5) = 0, $F19, Z19 * (1 - IFERROR(INDEX('Inputs & Assuptions'!$C$13:$C$72, COLUMN() - ($E19 + 5)), 0)) ) )} -> 982.27133 | ... BM19: {=IF(COLUMN() - ($E19 + 5) < 0, 0, IF(COLUMN() - ($E19 + 5) = 0, $F19, BL19 * (1 - IFERROR(INDEX('Inputs & Assuptions'!$C$13:$C$72, COLUMN() - ($E19 + 5)), 0)) ) )} -> 801.74207
A20: =A19+1 -> 15 | B20: =IF(MOD($A20-1, 12) = 0, $B19 * 1.05, $B19) -> 1575 | C20: =$B20*(1-'Inputs & Assuptions'!$C$12) -> 1228.5 | E20: =E19+1 -> 15 | T20: =$C20 -> 1228.5 | U20: {=IF(COLUMN() - ($E20 + 5) < 0, 0, IF(COLUMN() - ($E20 + 5) = 0, $F20, T20 * (1 - IFERROR(INDEX('Inputs & Assuptions'!$C$13:$C$72, COLUMN() - ($E20 + 5)), 0)) ) )} -> 1164.0038 | V20: {=IF(COLUMN() - ($E20 + 5) < 0, 0, IF(COLUMN() - ($E20 + 5) = 0, $F20, U20 * (1 - IFERROR(INDEX('Inputs & Assuptions'!$C$13:$C$72, COLUMN() - ($E20 + 5)), 0)) ) )} -> 1117.4436 | W20: {=IF(COLUMN() - ($E20 + 5) < 0, 0, IF(COLUMN() - ($E20 + 5) = 0, $F20, V20 * (1 - IFERROR(INDEX('Inputs & Assuptions'!$C$13:$C$72, COLUMN() - ($E20 + 5)), 0)) ) )} -> 1086.7139 | X20: {=IF(COLUMN() - ($E20 + 5) < 0, 0, IF(COLUMN() - ($E20 + 5) = 0, $F20, W20 * (1 - IFERROR(INDEX('Inputs & Assuptions'!$C$13:$C$72, COLUMN() - ($E20 + 5)), 0)) ) )} -> 1059.5461 | Y20: {=IF(COLUMN() - ($E20 + 5) < 0, 0, IF(COLUMN() - ($E20 + 5) = 0, $F20, X20 * (1 - IFERROR(INDEX('Inputs & Assuptions'!$C$13:$C$72, COLUMN() - ($E20 + 5)), 0)) ) )} -> 1035.7063 | Z20: {=IF(COLUMN() - ($E20 + 5) < 0, 0, IF(COLUMN() - ($E20 + 5) = 0, $F20, Y20 * (1 - IFERROR(INDEX('Inputs & Assuptions'!$C$13:$C$72, COLUMN() - ($E20 + 5)), 0)) ) )} -> 1014.9921 | AA20: {=IF(COLUMN() - ($E20 + 5) < 0, 0, IF(COLUMN() - ($E20 + 5) = 0, $F20, Z20 * (1 - IFERROR(INDEX('Inputs & Assuptions'!$C$13:$C$72, COLUMN() - ($E20 + 5)), 0)) ) )} -> 997.22978 | AB20: {=IF(COLUMN() - ($E20 + 5) < 0, 0, IF(COLUMN() - ($E20 + 5) = 0, $F20, AA20 * (1 - IFERROR(INDEX('Inputs & Assuptions'!$C$13:$C$72, COLUMN() - ($E20 + 5)), 0)) ) )} -> 982.27133 | ... BM20: {=IF(COLUMN() - ($E20 + 5) < 0, 0, IF(COLUMN() - ($E20 + 5) = 0, $F20, BL20 * (1 - IFERROR(INDEX('Inputs & Assuptions'!$C$13:$C$72, COLUMN() - ($E20 + 5)), 0)) ) )} -> 805.77093
A21: =A20+1 -> 16 | B21: =IF(MOD($A21-1, 12) = 0, $B20 * 1.05, $B20) -> 1575 | C21: =$B21*(1-'Inputs & Assuptions'!$C$12) -> 1228.5 | E21: =E20+1 -> 16 | U21: =$C21 -> 1228.5 | V21: {=IF(COLUMN() - ($E21 + 5) < 0, 0, IF(COLUMN() - ($E21 + 5) = 0, $F21, U21 * (1 - IFERROR(INDEX('Inputs & Assuptions'!$C$13:$C$72, COLUMN() - ($E21 + 5)), 0)) ) )} -> 1164.0038 | W21: {=IF(COLUMN() - ($E21 + 5) < 0, 0, IF(COLUMN() - ($E21 + 5) = 0, $F21, V21 * (1 - IFERROR(INDEX('Inputs & Assuptions'!$C$13:$C$72, COLUMN() - ($E21 + 5)), 0)) ) )} -> 1117.4436 | X21: {=IF(COLUMN() - ($E21 + 5) < 0, 0, IF(COLUMN() - ($E21 + 5) = 0, $F21, W21 * (1 - IFERROR(INDEX('Inputs & Assuptions'!$C$13:$C$72, COLUMN() - ($E21 + 5)), 0)) ) )} -> 1086.7139 | Y21: {=IF(COLUMN() - ($E21 + 5) < 0, 0, IF(COLUMN() - ($E21 + 5) = 0, $F21, X21 * (1 - IFERROR(INDEX('Inputs & Assuptions'!$C$13:$C$72, COLUMN() - ($E21 + 5)), 0)) ) )} -> 1059.5461 | Z21: {=IF(COLUMN() - ($E21 + 5) < 0, 0, IF(COLUMN() - ($E21 + 5) = 0, $F21, Y21 * (1 - IFERROR(INDEX('Inputs & Assuptions'!$C$13:$C$72, COLUMN() - ($E21 + 5)), 0)) ) )} -> 1035.7063 | AA21: {=IF(COLUMN() - ($E21 + 5) < 0, 0, IF(COLUMN() - ($E21 + 5) = 0, $F21, Z21 * (1 - IFERROR(INDEX('Inputs & Assuptions'!$C$13:$C$72, COLUMN() - ($E21 + 5)), 0)) ) )} -> 1014.9921 | AB21: {=IF(COLUMN() - ($E21 + 5) < 0, 0, IF(COLUMN() - ($E21 + 5) = 0, $F21, AA21 * (1 - IFERROR(INDEX('Inputs & Assuptions'!$C$13:$C$72, COLUMN() - ($E21 + 5)), 0)) ) )} -> 997.22978 | AC21: {=IF(COLUMN() - ($E21 + 5) < 0, 0, IF(COLUMN() - ($E21 + 5) = 0, $F21, AB21 * (1 - IFERROR(INDEX('Inputs & Assuptions'!$C$13:$C$72, COLUMN() - ($E21 + 5)), 0)) ) )} -> 982.27133 | ... BM21: {=IF(COLUMN() - ($E21 + 5) < 0, 0, IF(COLUMN() - ($E21 + 5) = 0, $F21, BL21 * (1 - IFERROR(INDEX('Inputs & Assuptions'!$C$13:$C$72, COLUMN() - ($E21 + 5)), 0)) ) )} -> 809.82003
A22: =A21+1 -> 17 | B22: =IF(MOD($A22-1, 12) = 0, $B21 * 1.05, $B21) -> 1575 | C22: =$B22*(1-'Inputs & Assuptions'!$C$12) -> 1228.5 | E22: =E21+1 -> 17 | V22: =$C22 -> 1228.5 | W22: {=IF(COLUMN() - ($E22 + 5) < 0, 0, IF(COLUMN() - ($E22 + 5) = 0, $F22, V22 * (1 - IFERROR(INDEX('Inputs & Assuptions'!$C$13:$C$72, COLUMN() - ($E22 + 5)), 0)) ) )} -> 1164.0038 | X22: {=IF(COLUMN() - ($E22 + 5) < 0, 0, IF(COLUMN() - ($E22 + 5) = 0, $F22, W22 * (1 - IFERROR(INDEX('Inputs & Assuptions'!$C$13:$C$72, COLUMN() - ($E22 + 5)), 0)) ) )} -> 1117.4436 | Y22: {=IF(COLUMN() - ($E22 + 5) < 0, 0, IF(COLUMN() - ($E22 + 5) = 0, $F22, X22 * (1 - IFERROR(INDEX('Inputs & Assuptions'!$C$13:$C$72, COLUMN() - ($E22 + 5)), 0)) ) )} -> 1086.7139 | Z22: {=IF(COLUMN() - ($E22 + 5) < 0, 0, IF(COLUMN() - ($E22 + 5) = 0, $F22, Y22 * (1 - IFERROR(INDEX('Inputs & Assuptions'!$C$13:$C$72, COLUMN() - ($E22 + 5)), 0)) ) )} -> 1059.5461 | AA22: {=IF(COLUMN() - ($E22 + 5) < 0, 0, IF(COLUMN() - ($E22 + 5) = 0, $F22, Z22 * (1 - IFERROR(INDEX('Inputs & Assuptions'!$C$13:$C$72, COLUMN() - ($E22 + 5)), 0)) ) )} -> 1035.7063 | AB22: {=IF(COLUMN() - ($E22 + 5) < 0, 0, IF(COLUMN() - ($E22 + 5) = 0, $F22, AA22 * (1 - IFERROR(INDEX('Inputs & Assuptions'!$C$13:$C$72, COLUMN() - ($E22 + 5)), 0)) ) )} -> 1014.9921 | AC22: {=IF(COLUMN() - ($E22 + 5) < 0, 0, IF(COLUMN() - ($E22 + 5) = 0, $F22, AB22 * (1 - IFERROR(INDEX('Inputs & Assuptions'!$C$13:$C$72, COLUMN() - ($E22 + 5)), 0)) ) )} -> 997.22978 | AD22: {=IF(COLUMN() - ($E22 + 5) < 0, 0, IF(COLUMN() - ($E22 + 5) = 0, $F22, AC22 * (1 - IFERROR(INDEX('Inputs & Assuptions'!$C$13:$C$72, COLUMN() - ($E22 + 5)), 0)) ) )} -> 982.27133 | ... BM22: {=IF(COLUMN() - ($E22 + 5) < 0, 0, IF(COLUMN() - ($E22 + 5) = 0, $F22, BL22 * (1 - IFERROR(INDEX('Inputs & Assuptions'!$C$13:$C$72, COLUMN() - ($E22 + 5)), 0)) ) )} -> 813.88948
A23: =A22+1 -> 18 | B23: =IF(MOD($A23-1, 12) = 0, $B22 * 1.05, $B22) -> 1575 | C23: =$B23*(1-'Inputs & Assuptions'!$C$12) -> 1228.5 | E23: =E22+1 -> 18 | W23: =$C23 -> 1228.5 | X23: {=IF(COLUMN() - ($E23 + 5) < 0, 0, IF(COLUMN() - ($E23 + 5) = 0, $F23, W23 * (1 - IFERROR(INDEX('Inputs & Assuptions'!$C$13:$C$72, COLUMN() - ($E23 + 5)), 0)) ) )} -> 1164.0038 | Y23: {=IF(COLUMN() - ($E23 + 5) < 0, 0, IF(COLUMN() - ($E23 + 5) = 0, $F23, X23 * (1 - IFERROR(INDEX('Inputs & Assuptions'!$C$13:$C$72, COLUMN() - ($E23 + 5)), 0)) ) )} -> 1117.4436 | Z23: {=IF(COLUMN() - ($E23 + 5) < 0, 0, IF(COLUMN() - ($E23 + 5) = 0, $F23, Y23 * (1 - IFERROR(INDEX('Inputs & Assuptions'!$C$13:$C$72, COLUMN() - ($E23 + 5)), 0)) ) )} -> 1086.7139 | AA23: {=IF(COLUMN() - ($E23 + 5) < 0, 0, IF(COLUMN() - ($E23 + 5) = 0, $F23, Z23 * (1 - IFERROR(INDEX('Inputs & Assuptions'!$C$13:$C$72, COLUMN() - ($E23 + 5)), 0)) ) )} -> 1059.5461 | AB23: {=IF(COLUMN() - ($E23 + 5) < 0, 0, IF(COLUMN() - ($E23 + 5) = 0, $F23, AA23 * (1 - IFERROR(INDEX('Inputs & Assuptions'!$C$13:$C$72, COLUMN() - ($E23 + 5)), 0)) ) )} -> 1035.7063 | AC23: {=IF(COLUMN() - ($E23 + 5) < 0, 0, IF(COLUMN() - ($E23 + 5) = 0, $F23, AB23 * (1 - IFERROR(INDEX('Inputs & Assuptions'!$C$13:$C$72, COLUMN() - ($E23 + 5)), 0)) ) )} -> 1014.9921 | AD23: {=IF(COLUMN() - ($E23 + 5) < 0, 0, IF(COLUMN() - ($E23 + 5) = 0, $F23, AC23 * (1 - IFERROR(INDEX('Inputs & Assuptions'!$C$13:$C$72, COLUMN() - ($E23 + 5)), 0)) ) )} -> 997.22978 | AE23: {=IF(COLUMN() - ($E23 + 5) < 0, 0, IF(COLUMN() - ($E23 + 5) = 0, $F23, AD23 * (1 - IFERROR(INDEX('Inputs & Assuptions'!$C$13:$C$72, COLUMN() - ($E23 + 5)), 0)) ) )} -> 982.27133 | ... BM23: {=IF(COLUMN() - ($E23 + 5) < 0, 0, IF(COLUMN() - ($E23 + 5) = 0, $F23, BL23 * (1 - IFERROR(INDEX('Inputs & Assuptions'!$C$13:$C$72, COLUMN() - ($E23 + 5)), 0)) ) )} -> 817.97937
A24: =A23+1 -> 19 | B24: =IF(MOD($A24-1, 12) = 0, $B23 * 1.05, $B23) -> 1575 | C24: =$B24*(1-'Inputs & Assuptions'!$C$12) -> 1228.5 | E24: =E23+1 -> 19 | X24: =$C24 -> 1228.5 | Y24: {=IF(COLUMN() - ($E24 + 5) < 0, 0, IF(COLUMN() - ($E24 + 5) = 0, $F24, X24 * (1 - IFERROR(INDEX('Inputs & Assuptions'!$C$13:$C$72, COLUMN() - ($E24 + 5)), 0)) ) )} -> 1164.0038 | Z24: {=IF(COLUMN() - ($E24 + 5) < 0, 0, IF(COLUMN() - ($E24 + 5) = 0, $F24, Y24 * (1 - IFERROR(INDEX('Inputs & Assuptions'!$C$13:$C$72, COLUMN() - ($E24 + 5)), 0)) ) )} -> 1117.4436 | AA24: {=IF(COLUMN() - ($E24 + 5) < 0, 0, IF(COLUMN() - ($E24 + 5) = 0, $F24, Z24 * (1 - IFERROR(INDEX('Inputs & Assuptions'!$C$13:$C$72, COLUMN() - ($E24 + 5)), 0)) ) )} -> 1086.7139 | AB24: {=IF(COLUMN() - ($E24 + 5) < 0, 0, IF(COLUMN() - ($E24 + 5) = 0, $F24, AA24 * (1 - IFERROR(INDEX('Inputs & Assuptions'!$C$13:$C$72, COLUMN() - ($E24 + 5)), 0)) ) )} -> 1059.5461 | AC24: {=IF(COLUMN() - ($E24 + 5) < 0, 0, IF(COLUMN() - ($E24 + 5) = 0, $F24, AB24 * (1 - IFERROR(INDEX('Inputs & Assuptions'!$C$13:$C$72, COLUMN() - ($E24 + 5)), 0)) ) )} -> 1035.7063 | AD24: {=IF(COLUMN() - ($E24 + 5) < 0, 0, IF(COLUMN() - ($E24 + 5) = 0, $F24, AC24 * (1 - IFERROR(INDEX('Inputs & Assuptions'!$C$13:$C$72, COLUMN() - ($E24 + 5)), 0)) ) )} -> 1014.9921 | AE24: {=IF(COLUMN() - ($E24 + 5) < 0, 0, IF(COLUMN() - ($E24 + 5) = 0, $F24, AD24 * (1 - IFERROR(INDEX('Inputs & Assuptions'!$C$13:$C$72, COLUMN() - ($E24 + 5)), 0)) ) )} -> 997.22978 | AF24: {=IF(COLUMN() - ($E24 + 5) < 0, 0, IF(COLUMN() - ($E24 + 5) = 0, $F24, AE24 * (1 - IFERROR(INDEX('Inputs & Assuptions'!$C$13:$C$72, COLUMN() - ($E24 + 5)), 0)) ) )} -> 982.27133 | ... BM24: {=IF(COLUMN() - ($E24 + 5) < 0, 0, IF(COLUMN() - ($E24 + 5) = 0, $F24, BL24 * (1 - IFERROR(INDEX('Inputs & Assuptions'!$C$13:$C$72, COLUMN() - ($E24 + 5)), 0)) ) )} -> 822.08982
A25: =A24+1 -> 20 | B25: =IF(MOD($A25-1, 12) = 0, $B24 * 1.05, $B24) -> 1575 | C25: =$B25*(1-'Inputs & Assuptions'!$C$12) -> 1228.5 | E25: =E24+1 -> 20 | Y25: =$C25 -> 1228.5 | Z25: {=IF(COLUMN() - ($E25 + 5) < 0, 0, IF(COLUMN() - ($E25 + 5) = 0, $F25, Y25 * (1 - IFERROR(INDEX('Inputs & Assuptions'!$C$13:$C$72, COLUMN() - ($E25 + 5)), 0)) ) )} -> 1164.0038 | AA25: {=IF(COLUMN() - ($E25 + 5) < 0, 0, IF(COLUMN() - ($E25 + 5) = 0, $F25, Z25 * (1 - IFERROR(INDEX('Inputs & Assuptions'!$C$13:$C$72, COLUMN() - ($E25 + 5)), 0)) ) )} -> 1117.4436 | AB25: {=IF(COLUMN() - ($E25 + 5) < 0, 0, IF(COLUMN() - ($E25 + 5) = 0, $F25, AA25 * (1 - IFERROR(INDEX('Inputs & Assuptions'!$C$13:$C$72, COLUMN() - ($E25 + 5)), 0)) ) )} -> 1086.7139 | AC25: {=IF(COLUMN() - ($E25 + 5) < 0, 0, IF(COLUMN() - ($E25 + 5) = 0, $F25, AB25 * (1 - IFERROR(INDEX('Inputs & Assuptions'!$C$13:$C$72, COLUMN() - ($E25 + 5)), 0)) ) )} -> 1059.5461 | AD25: {=IF(COLUMN() - ($E25 + 5) < 0, 0, IF(COLUMN() - ($E25 + 5) = 0, $F25, AC25 * (1 - IFERROR(INDEX('Inputs & Assuptions'!$C$13:$C$72, COLUMN() - ($E25 + 5)), 0)) ) )} -> 1035.7063 | AE25: {=IF(COLUMN() - ($E25 + 5) < 0, 0, IF(COLUMN() - ($E25 + 5) = 0, $F25, AD25 * (1 - IFERROR(INDEX('Inputs & Assuptions'!$C$13:$C$72, COLUMN() - ($E25 + 5)), 0)) ) )} -> 1014.9921 | AF25: {=IF(COLUMN() - ($E25 + 5) < 0, 0, IF(COLUMN() - ($E25 + 5) = 0, $F25, AE25 * (1 - IFERROR(INDEX('Inputs & Assuptions'!$C$13:$C$72, COLUMN() - ($E25 + 5)), 0)) ) )} -> 997.22978 | AG25: {=IF(COLUMN() - ($E25 + 5) < 0, 0, IF(COLUMN() - ($E25 + 5) = 0, $F25, AF25 * (1 - IFERROR(INDEX('Inputs & Assuptions'!$C$13:$C$72, COLUMN() - ($E25 + 5)), 0)) ) )} -> 982.27133 | ... BM25: {=IF(COLUMN() - ($E25 + 5) < 0, 0, IF(COLUMN() - ($E25 + 5) = 0, $F25, BL25 * (1 - IFERROR(INDEX('Inputs & Assuptions'!$C$13:$C$72, COLUMN() - ($E25 + 5)), 0)) ) )} -> 826.22093
A26: =A25+1 -> 21 | B26: =IF(MOD($A26-1, 12) = 0, $B25 * 1.05, $B25) -> 1575 | C26: =$B26*(1-'Inputs & Assuptions'!$C$12) -> 1228.5 | E26: =E25+1 -> 21 | Z26: =$C26 -> 1228.5 | AA26: {=IF(COLUMN() - ($E26 + 5) < 0, 0, IF(COLUMN() - ($E26 + 5) = 0, $F26, Z26 * (1 - IFERROR(INDEX('Inputs & Assuptions'!$C$13:$C$72, COLUMN() - ($E26 + 5)), 0)) ) )} -> 1164.0038 | AB26: {=IF(COLUMN() - ($E26 + 5) < 0, 0, IF(COLUMN() - ($E26 + 5) = 0, $F26, AA26 * (1 - IFERROR(INDEX('Inputs & Assuptions'!$C$13:$C$72, COLUMN() - ($E26 + 5)), 0)) ) )} -> 1117.4436 | AC26: {=IF(COLUMN() - ($E26 + 5) < 0, 0, IF(COLUMN() - ($E26 + 5) = 0, $F26, AB26 * (1 - IFERROR(INDEX('Inputs & Assuptions'!$C$13:$C$72, COLUMN() - ($E26 + 5)), 0)) ) )} -> 1086.7139 | AD26: {=IF(COLUMN() - ($E26 + 5) < 0, 0, IF(COLUMN() - ($E26 + 5) = 0, $F26, AC26 * (1 - IFERROR(INDEX('Inputs & Assuptions'!$C$13:$C$72, COLUMN() - ($E26 + 5)), 0)) ) )} -> 1059.5461 | AE26: {=IF(COLUMN() - ($E26 + 5) < 0, 0, IF(COLUMN() - ($E26 + 5) = 0, $F26, AD26 * (1 - IFERROR(INDEX('Inputs & Assuptions'!$C$13:$C$72, COLUMN() - ($E26 + 5)), 0)) ) )} -> 1035.7063 | AF26: {=IF(COLUMN() - ($E26 + 5) < 0, 0, IF(COLUMN() - ($E26 + 5) = 0, $F26, AE26 * (1 - IFERROR(INDEX('Inputs & Assuptions'!$C$13:$C$72, COLUMN() - ($E26 + 5)), 0)) ) )} -> 1014.9921 | AG26: {=IF(COLUMN() - ($E26 + 5) < 0, 0, IF(COLUMN() - ($E26 + 5) = 0, $F26, AF26 * (1 - IFERROR(INDEX('Inputs & Assuptions'!$C$13:$C$72, COLUMN() - ($E26 + 5)), 0)) ) )} -> 997.22978 | AH26: {=IF(COLUMN() - ($E26 + 5) < 0, 0, IF(COLUMN() - ($E26 + 5) = 0, $F26, AG26 * (1 - IFERROR(INDEX('Inputs & Assuptions'!$C$13:$C$72, COLUMN() - ($E26 + 5)), 0)) ) )} -> 982.27133 | ... BM26: {=IF(COLUMN() - ($E26 + 5) < 0, 0, IF(COLUMN() - ($E26 + 5) = 0, $F26, BL26 * (1 - IFERROR(INDEX('Inputs & Assuptions'!$C$13:$C$72, COLUMN() - ($E26 + 5)), 0)) ) )} -> 830.37279
A27: =A26+1 -> 22 | B27: =IF(MOD($A27-1, 12) = 0, $B26 * 1.05, $B26) -> 1575 | C27: =$B27*(1-'Inputs & Assuptions'!$C$12) -> 1228.5 | E27: =E26+1 -> 22 | AA27: =$C27 -> 1228.5 | AB27: {=IF(COLUMN() - ($E27 + 5) < 0, 0, IF(COLUMN() - ($E27 + 5) = 0, $F27, AA27 * (1 - IFERROR(INDEX('Inputs & Assuptions'!$C$13:$C$72, COLUMN() - ($E27 + 5)), 0)) ) )} -> 1164.0038 | AC27: {=IF(COLUMN() - ($E27 + 5) < 0, 0, IF(COLUMN() - ($E27 + 5) = 0, $F27, AB27 * (1 - IFERROR(INDEX('Inputs & Assuptions'!$C$13:$C$72, COLUMN() - ($E27 + 5)), 0)) ) )} -> 1117.4436 | AD27: {=IF(COLUMN() - ($E27 + 5) < 0, 0, IF(COLUMN() - ($E27 + 5) = 0, $F27, AC27 * (1 - IFERROR(INDEX('Inputs & Assuptions'!$C$13:$C$72, COLUMN() - ($E27 + 5)), 0)) ) )} -> 1086.7139 | AE27: {=IF(COLUMN() - ($E27 + 5) < 0, 0, IF(COLUMN() - ($E27 + 5) = 0, $F27, AD27 * (1 - IFERROR(INDEX('Inputs & Assuptions'!$C$13:$C$72, COLUMN() - ($E27 + 5)), 0)) ) )} -> 1059.5461 | AF27: {=IF(COLUMN() - ($E27 + 5) < 0, 0, IF(COLUMN() - ($E27 + 5) = 0, $F27, AE27 * (1 - IFERROR(INDEX('Inputs & Assuptions'!$C$13:$C$72, COLUMN() - ($E27 + 5)), 0)) ) )} -> 1035.7063 | AG27: {=IF(COLUMN() - ($E27 + 5) < 0, 0, IF(COLUMN() - ($E27 + 5) = 0, $F27, AF27 * (1 - IFERROR(INDEX('Inputs & Assuptions'!$C$13:$C$72, COLUMN() - ($E27 + 5)), 0)) ) )} -> 1014.9921 | AH27: {=IF(COLUMN() - ($E27 + 5) < 0, 0, IF(COLUMN() - ($E27 + 5) = 0, $F27, AG27 * (1 - IFERROR(INDEX('Inputs & Assuptions'!$C$13:$C$72, COLUMN() - ($E27 + 5)), 0)) ) )} -> 997.22978 | AI27: {=IF(COLUMN() - ($E27 + 5) < 0, 0, IF(COLUMN() - ($E27 + 5) = 0, $F27, AH27 * (1 - IFERROR(INDEX('Inputs & Assuptions'!$C$13:$C$72, COLUMN() - ($E27 + 5)), 0)) ) )} -> 982.27133 | ... BM27: {=IF(COLUMN() - ($E27 + 5) < 0, 0, IF(COLUMN() - ($E27 + 5) = 0, $F27, BL27 * (1 - IFERROR(INDEX('Inputs & Assuptions'!$C$13:$C$72, COLUMN() - ($E27 + 5)), 0)) ) )} -> 834.54552
A28: =A27+1 -> 23 | B28: =IF(MOD($A28-1, 12) = 0, $B27 * 1.05, $B27) -> 1575 | C28: =$B28*(1-'Inputs & Assuptions'!$C$12) -> 1228.5 | E28: =E27+1 -> 23 | AB28: =$C28 -> 1228.5 | AC28: {=IF(COLUMN() - ($E28 + 5) < 0, 0, IF(COLUMN() - ($E28 + 5) = 0, $F28, AB28 * (1 - IFERROR(INDEX('Inputs & Assuptions'!$C$13:$C$72, COLUMN() - ($E28 + 5)), 0)) ) )} -> 1164.0038 | AD28: {=IF(COLUMN() - ($E28 + 5) < 0, 0, IF(COLUMN() - ($E28 + 5) = 0, $F28, AC28 * (1 - IFERROR(INDEX('Inputs & Assuptions'!$C$13:$C$72, COLUMN() - ($E28 + 5)), 0)) ) )} -> 1117.4436 | AE28: {=IF(COLUMN() - ($E28 + 5) < 0, 0, IF(COLUMN() - ($E28 + 5) = 0, $F28, AD28 * (1 - IFERROR(INDEX('Inputs & Assuptions'!$C$13:$C$72, COLUMN() - ($E28 + 5)), 0)) ) )} -> 1086.7139 | AF28: {=IF(COLUMN() - ($E28 + 5) < 0, 0, IF(COLUMN() - ($E28 + 5) = 0, $F28, AE28 * (1 - IFERROR(INDEX('Inputs & Assuptions'!$C$13:$C$72, COLUMN() - ($E28 + 5)), 0)) ) )} -> 1059.5461 | AG28: {=IF(COLUMN() - ($E28 + 5) < 0, 0, IF(COLUMN() - ($E28 + 5) = 0, $F28, AF28 * (1 - IFERROR(INDEX('Inputs & Assuptions'!$C$13:$C$72, COLUMN() - ($E28 + 5)), 0)) ) )} -> 1035.7063 | AH28: {=IF(COLUMN() - ($E28 + 5) < 0, 0, IF(COLUMN() - ($E28 + 5) = 0, $F28, AG28 * (1 - IFERROR(INDEX('Inputs & Assuptions'!$C$13:$C$72, COLUMN() - ($E28 + 5)), 0)) ) )} -> 1014.9921 | AI28: {=IF(COLUMN() - ($E28 + 5) < 0, 0, IF(COLUMN() - ($E28 + 5) = 0, $F28, AH28 * (1 - IFERROR(INDEX('Inputs & Assuptions'!$C$13:$C$72, COLUMN() - ($E28 + 5)), 0)) ) )} -> 997.22978 | AJ28: {=IF(COLUMN() - ($E28 + 5) < 0, 0, IF(COLUMN() - ($E28 + 5) = 0, $F28, AI28 * (1 - IFERROR(INDEX('Inputs & Assuptions'!$C$13:$C$72, COLUMN() - ($E28 + 5)), 0)) ) )} -> 982.27133 | ... BM28: {=IF(COLUMN() - ($E28 + 5) < 0, 0, IF(COLUMN() - ($E28 + 5) = 0, $F28, BL28 * (1 - IFERROR(INDEX('Inputs & Assuptions'!$C$13:$C$72, COLUMN() - ($E28 + 5)), 0)) ) )} -> 838.73921
A29: =A28+1 -> 24 | B29: =IF(MOD($A29-1, 12) = 0, $B28 * 1.05, $B28) -> 1575 | C29: =$B29*(1-'Inputs & Assuptions'!$C$12) -> 1228.5 | E29: =E28+1 -> 24 | AC29: =$C29 -> 1228.5 | AD29: {=IF(COLUMN() - ($E29 + 5) < 0, 0, IF(COLUMN() - ($E29 + 5) = 0, $F29, AC29 * (1 - IFERROR(INDEX('Inputs & Assuptions'!$C$13:$C$72, COLUMN() - ($E29 + 5)), 0)) ) )} -> 1164.0038 | AE29: {=IF(COLUMN() - ($E29 + 5) < 0, 0, IF(COLUMN() - ($E29 + 5) = 0, $F29, AD29 * (1 - IFERROR(INDEX('Inputs & Assuptions'!$C$13:$C$72, COLUMN() - ($E29 + 5)), 0)) ) )} -> 1117.4436 | AF29: {=IF(COLUMN() - ($E29 + 5) < 0, 0, IF(COLUMN() - ($E29 + 5) = 0, $F29, AE29 * (1 - IFERROR(INDEX('Inputs & Assuptions'!$C$13:$C$72, COLUMN() - ($E29 + 5)), 0)) ) )} -> 1086.7139 | AG29: {=IF(COLUMN() - ($E29 + 5) < 0, 0, IF(COLUMN() - ($E29 + 5) = 0, $F29, AF29 * (1 - IFERROR(INDEX('Inputs & Assuptions'!$C$13:$C$72, COLUMN() - ($E29 + 5)), 0)) ) )} -> 1059.5461 | AH29: {=IF(COLUMN() - ($E29 + 5) < 0, 0, IF(COLUMN() - ($E29 + 5) = 0, $F29, AG29 * (1 - IFERROR(INDEX('Inputs & Assuptions'!$C$13:$C$72, COLUMN() - ($E29 + 5)), 0)) ) )} -> 1035.7063 | AI29: {=IF(COLUMN() - ($E29 + 5) < 0, 0, IF(COLUMN() - ($E29 + 5) = 0, $F29, AH29 * (1 - IFERROR(INDEX('Inputs & Assuptions'!$C$13:$C$72, COLUMN() - ($E29 + 5)), 0)) ) )} -> 1014.9921 | AJ29: {=IF(COLUMN() - ($E29 + 5) < 0, 0, IF(COLUMN() - ($E29 + 5) = 0, $F29, AI29 * (1 - IFERROR(INDEX('Inputs & Assuptions'!$C$13:$C$72, COLUMN() - ($E29 + 5)), 0)) ) )} -> 997.22978 | AK29: {=IF(COLUMN() - ($E29 + 5) < 0, 0, IF(COLUMN() - ($E29 + 5) = 0, $F29, AJ29 * (1 - IFERROR(INDEX('Inputs & Assuptions'!$C$13:$C$72, COLUMN() - ($E29 + 5)), 0)) ) )} -> 982.27133 | ... BM29: {=IF(COLUMN() - ($E29 + 5) < 0, 0, IF(COLUMN() - ($E29 + 5) = 0, $F29, BL29 * (1 - IFERROR(INDEX('Inputs & Assuptions'!$C$13:$C$72, COLUMN() - ($E29 + 5)), 0)) ) )} -> 842.95398
A30: =A29+1 -> 25 | B30: =IF(MOD($A30-1, 12) = 0, $B29 * 1.05, $B29) -> 1653.75 | C30: =$B30*(1-'Inputs & Assuptions'!$C$12) -> 1289.925 | E30: =E29+1 -> 25 | AD30: =$C30 -> 1289.925 | AE30: {=IF(COLUMN() - ($E30 + 5) < 0, 0, IF(COLUMN() - ($E30 + 5) = 0, $F30, AD30 * (1 - IFERROR(INDEX('Inputs & Assuptions'!$C$13:$C$72, COLUMN() - ($E30 + 5)), 0)) ) )} -> 1222.2039 | AF30: {=IF(COLUMN() - ($E30 + 5) < 0, 0, IF(COLUMN() - ($E30 + 5) = 0, $F30, AE30 * (1 - IFERROR(INDEX('Inputs & Assuptions'!$C$13:$C$72, COLUMN() - ($E30 + 5)), 0)) ) )} -> 1173.3158 | AG30: {=IF(COLUMN() - ($E30 + 5) < 0, 0, IF(COLUMN() - ($E30 + 5) = 0, $F30, AF30 * (1 - IFERROR(INDEX('Inputs & Assuptions'!$C$13:$C$72, COLUMN() - ($E30 + 5)), 0)) ) )} -> 1141.0496 | AH30: {=IF(COLUMN() - ($E30 + 5) < 0, 0, IF(COLUMN() - ($E30 + 5) = 0, $F30, AG30 * (1 - IFERROR(INDEX('Inputs & Assuptions'!$C$13:$C$72, COLUMN() - ($E30 + 5)), 0)) ) )} -> 1112.5234 | AI30: {=IF(COLUMN() - ($E30 + 5) < 0, 0, IF(COLUMN() - ($E30 + 5) = 0, $F30, AH30 * (1 - IFERROR(INDEX('Inputs & Assuptions'!$C$13:$C$72, COLUMN() - ($E30 + 5)), 0)) ) )} -> 1087.4916 | AJ30: {=IF(COLUMN() - ($E30 + 5) < 0, 0, IF(COLUMN() - ($E30 + 5) = 0, $F30, AI30 * (1 - IFERROR(INDEX('Inputs & Assuptions'!$C$13:$C$72, COLUMN() - ($E30 + 5)), 0)) ) )} -> 1065.7417 | AK30: {=IF(COLUMN() - ($E30 + 5) < 0, 0, IF(COLUMN() - ($E30 + 5) = 0, $F30, AJ30 * (1 - IFERROR(INDEX('Inputs & Assuptions'!$C$13:$C$72, COLUMN() - ($E30 + 5)), 0)) ) )} -> 1047.0913 | AL30: {=IF(COLUMN() - ($E30 + 5) < 0, 0, IF(COLUMN() - ($E30 + 5) = 0, $F30, AK30 * (1 - IFERROR(INDEX('Inputs & Assuptions'!$C$13:$C$72, COLUMN() - ($E30 + 5)), 0)) ) )} -> 1031.3849 | ... BM30: {=IF(COLUMN() - ($E30 + 5) < 0, 0, IF(COLUMN() - ($E30 + 5) = 0, $F30, BL30 * (1 - IFERROR(INDEX('Inputs & Assuptions'!$C$13:$C$72, COLUMN() - ($E30 + 5)), 0)) ) )} -> 889.54943
A31: =A30+1 -> 26 | B31: =IF(MOD($A31-1, 12) = 0, $B30 * 1.05, $B30) -> 1653.75 | C31: =$B31*(1-'Inputs & Assuptions'!$C$12) -> 1289.925 | E31: =E30+1 -> 26 | AE31: =$C31 -> 1289.925 | AF31: {=IF(COLUMN() - ($E31 + 5) < 0, 0, IF(COLUMN() - ($E31 + 5) = 0, $F31, AE31 * (1 - IFERROR(INDEX('Inputs & Assuptions'!$C$13:$C$72, COLUMN() - ($E31 + 5)), 0)) ) )} -> 1222.2039 | AG31: {=IF(COLUMN() - ($E31 + 5) < 0, 0, IF(COLUMN() - ($E31 + 5) = 0, $F31, AF31 * (1 - IFERROR(INDEX('Inputs & Assuptions'!$C$13:$C$72, COLUMN() - ($E31 + 5)), 0)) ) )} -> 1173.3158 | AH31: {=IF(COLUMN() - ($E31 + 5) < 0, 0, IF(COLUMN() - ($E31 + 5) = 0, $F31, AG31 * (1 - IFERROR(INDEX('Inputs & Assuptions'!$C$13:$C$72, COLUMN() - ($E31 + 5)), 0)) ) )} -> 1141.0496 | AI31: {=IF(COLUMN() - ($E31 + 5) < 0, 0, IF(COLUMN() - ($E31 + 5) = 0, $F31, AH31 * (1 - IFERROR(INDEX('Inputs & Assuptions'!$C$13:$C$72, COLUMN() - ($E31 + 5)), 0)) ) )} -> 1112.5234 | AJ31: {=IF(COLUMN() - ($E31 + 5) < 0, 0, IF(COLUMN() - ($E31 + 5) = 0, $F31, AI31 * (1 - IFERROR(INDEX('Inputs & Assuptions'!$C$13:$C$72, COLUMN() - ($E31 + 5)), 0)) ) )} -> 1087.4916 | AK31: {=IF(COLUMN() - ($E31 + 5) < 0, 0, IF(COLUMN() - ($E31 + 5) = 0, $F31, AJ31 * (1 - IFERROR(INDEX('Inputs & Assuptions'!$C$13:$C$72, COLUMN() - ($E31 + 5)), 0)) ) )} -> 1065.7417 | AL31: {=IF(COLUMN() - ($E31 + 5) < 0, 0, IF(COLUMN() - ($E31 + 5) = 0, $F31, AK31 * (1 - IFERROR(INDEX('Inputs & Assuptions'!$C$13:$C$72, COLUMN() - ($E31 + 5)), 0)) ) )} -> 1047.0913 | AM31: {=IF(COLUMN() - ($E31 + 5) < 0, 0, IF(COLUMN() - ($E31 + 5) = 0, $F31, AL31 * (1 - IFERROR(INDEX('Inputs & Assuptions'!$C$13:$C$72, COLUMN() - ($E31 + 5)), 0)) ) )} -> 1031.3849 | ... BM31: {=IF(COLUMN() - ($E31 + 5) < 0, 0, IF(COLUMN() - ($E31 + 5) = 0, $F31, BL31 * (1 - IFERROR(INDEX('Inputs & Assuptions'!$C$13:$C$72, COLUMN() - ($E31 + 5)), 0)) ) )} -> 894.01953
A32: =A31+1 -> 27 | B32: =IF(MOD($A32-1, 12) = 0, $B31 * 1.05, $B31) -> 1653.75 | C32: =$B32*(1-'Inputs & Assuptions'!$C$12) -> 1289.925 | E32: =E31+1 -> 27 | AF32: =$C32 -> 1289.925 | AG32: {=IF(COLUMN() - ($E32 + 5) < 0, 0, IF(COLUMN() - ($E32 + 5) = 0, $F32, AF32 * (1 - IFERROR(INDEX('Inputs & Assuptions'!$C$13:$C$72, COLUMN() - ($E32 + 5)), 0)) ) )} -> 1222.2039 | AH32: {=IF(COLUMN() - ($E32 + 5) < 0, 0, IF(COLUMN() - ($E32 + 5) = 0, $F32, AG32 * (1 - IFERROR(INDEX('Inputs & Assuptions'!$C$13:$C$72, COLUMN() - ($E32 + 5)), 0)) ) )} -> 1173.3158 | AI32: {=IF(COLUMN() - ($E32 + 5) < 0, 0, IF(COLUMN() - ($E32 + 5) = 0, $F32, AH32 * (1 - IFERROR(INDEX('Inputs & Assuptions'!$C$13:$C$72, COLUMN() - ($E32 + 5)), 0)) ) )} -> 1141.0496 | AJ32: {=IF(COLUMN() - ($E32 + 5) < 0, 0, IF(COLUMN() - ($E32 + 5) = 0, $F32, AI32 * (1 - IFERROR(INDEX('Inputs & Assuptions'!$C$13:$C$72, COLUMN() - ($E32 + 5)), 0)) ) )} -> 1112.5234 | AK32: {=IF(COLUMN() - ($E32 + 5) < 0, 0, IF(COLUMN() - ($E32 + 5) = 0, $F32, AJ32 * (1 - IFERROR(INDEX('Inputs & Assuptions'!$C$13:$C$72, COLUMN() - ($E32 + 5)), 0)) ) )} -> 1087.4916 | AL32: {=IF(COLUMN() - ($E32 + 5) < 0, 0, IF(COLUMN() - ($E32 + 5) = 0, $F32, AK32 * (1 - IFERROR(INDEX('Inputs & Assuptions'!$C$13:$C$72, COLUMN() - ($E32 + 5)), 0)) ) )} -> 1065.7417 | AM32: {=IF(COLUMN() - ($E32 + 5) < 0, 0, IF(COLUMN() - ($E32 + 5) = 0, $F32, AL32 * (1 - IFERROR(INDEX('Inputs & Assuptions'!$C$13:$C$72, COLUMN() - ($E32 + 5)), 0)) ) )} -> 1047.0913 | AN32: {=IF(COLUMN() - ($E32 + 5) < 0, 0, IF(COLUMN() - ($E32 + 5) = 0, $F32, AM32 * (1 - IFERROR(INDEX('Inputs & Assuptions'!$C$13:$C$72, COLUMN() - ($E32 + 5)), 0)) ) )} -> 1031.3849 | ... BM32: {=IF(COLUMN() - ($E32 + 5) < 0, 0, IF(COLUMN() - ($E32 + 5) = 0, $F32, BL32 * (1 - IFERROR(INDEX('Inputs & Assuptions'!$C$13:$C$72, COLUMN() - ($E32 + 5)), 0)) ) )} -> 898.51209
A33: =A32+1 -> 28 | B33: =IF(MOD($A33-1, 12) = 0, $B32 * 1.05, $B32) -> 1653.75 | C33: =$B33*(1-'Inputs & Assuptions'!$C$12) -> 1289.925 | E33: =E32+1 -> 28 | AG33: =$C33 -> 1289.925 | AH33: {=IF(COLUMN() - ($E33 + 5) < 0, 0, IF(COLUMN() - ($E33 + 5) = 0, $F33, AG33 * (1 - IFERROR(INDEX('Inputs & Assuptions'!$C$13:$C$72, COLUMN() - ($E33 + 5)), 0)) ) )} -> 1222.2039 | AI33: {=IF(COLUMN() - ($E33 + 5) < 0, 0, IF(COLUMN() - ($E33 + 5) = 0, $F33, AH33 * (1 - IFERROR(INDEX('Inputs & Assuptions'!$C$13:$C$72, COLUMN() - ($E33 + 5)), 0)) ) )} -> 1173.3158 | AJ33: {=IF(COLUMN() - ($E33 + 5) < 0, 0, IF(COLUMN() - ($E33 + 5) = 0, $F33, AI33 * (1 - IFERROR(INDEX('Inputs & Assuptions'!$C$13:$C$72, COLUMN() - ($E33 + 5)), 0)) ) )} -> 1141.0496 | AK33: {=IF(COLUMN() - ($E33 + 5) < 0, 0, IF(COLUMN() - ($E33 + 5) = 0, $F33, AJ33 * (1 - IFERROR(INDEX('Inputs & Assuptions'!$C$13:$C$72, COLUMN() - ($E33 + 5)), 0)) ) )} -> 1112.5234 | AL33: {=IF(COLUMN() - ($E33 + 5) < 0, 0, IF(COLUMN() - ($E33 + 5) = 0, $F33, AK33 * (1 - IFERROR(INDEX('Inputs & Assuptions'!$C$13:$C$72, COLUMN() - ($E33 + 5)), 0)) ) )} -> 1087.4916 | AM33: {=IF(COLUMN() - ($E33 + 5) < 0, 0, IF(COLUMN() - ($E33 + 5) = 0, $F33, AL33 * (1 - IFERROR(INDEX('Inputs & Assuptions'!$C$13:$C$72, COLUMN() - ($E33 + 5)), 0)) ) )} -> 1065.7417 | AN33: {=IF(COLUMN() - ($E33 + 5) < 0, 0, IF(COLUMN() - ($E33 + 5) = 0, $F33, AM33 * (1 - IFERROR(INDEX('Inputs & Assuptions'!$C$13:$C$72, COLUMN() - ($E33 + 5)), 0)) ) )} -> 1047.0913 | AO33: {=IF(COLUMN() - ($E33 + 5) < 0, 0, IF(COLUMN() - ($E33 + 5) = 0, $F33, AN33 * (1 - IFERROR(INDEX('Inputs & Assuptions'!$C$13:$C$72, COLUMN() - ($E33 + 5)), 0)) ) )} -> 1031.3849 | ... BM33: {=IF(COLUMN() - ($E33 + 5) < 0, 0, IF(COLUMN() - ($E33 + 5) = 0, $F33, BL33 * (1 - IFERROR(INDEX('Inputs & Assuptions'!$C$13:$C$72, COLUMN() - ($E33 + 5)), 0)) ) )} -> 903.02722
A34: =A33+1 -> 29 | B34: =IF(MOD($A34-1, 12) = 0, $B33 * 1.05, $B33) -> 1653.75 | C34: =$B34*(1-'Inputs & Assuptions'!$C$12) -> 1289.925 | E34: =E33+1 -> 29 | AH34: =$C34 -> 1289.925 | AI34: {=IF(COLUMN() - ($E34 + 5) < 0, 0, IF(COLUMN() - ($E34 + 5) = 0, $F34, AH34 * (1 - IFERROR(INDEX('Inputs & Assuptions'!$C$13:$C$72, COLUMN() - ($E34 + 5)), 0)) ) )} -> 1222.2039 | AJ34: {=IF(COLUMN() - ($E34 + 5) < 0, 0, IF(COLUMN() - ($E34 + 5) = 0, $F34, AI34 * (1 - IFERROR(INDEX('Inputs & Assuptions'!$C$13:$C$72, COLUMN() - ($E34 + 5)), 0)) ) )} -> 1173.3158 | AK34: {=IF(COLUMN() - ($E34 + 5) < 0, 0, IF(COLUMN() - ($E34 + 5) = 0, $F34, AJ34 * (1 - IFERROR(INDEX('Inputs & Assuptions'!$C$13:$C$72, COLUMN() - ($E34 + 5)), 0)) ) )} -> 1141.0496 | AL34: {=IF(COLUMN() - ($E34 + 5) < 0, 0, IF(COLUMN() - ($E34 + 5) = 0, $F34, AK34 * (1 - IFERROR(INDEX('Inputs & Assuptions'!$C$13:$C$72, COLUMN() - ($E34 + 5)), 0)) ) )} -> 1112.5234 | AM34: {=IF(COLUMN() - ($E34 + 5) < 0, 0, IF(COLUMN() - ($E34 + 5) = 0, $F34, AL34 * (1 - IFERROR(INDEX('Inputs & Assuptions'!$C$13:$C$72, COLUMN() - ($E34 + 5)), 0)) ) )} -> 1087.4916 | AN34: {=IF(COLUMN() - ($E34 + 5) < 0, 0, IF(COLUMN() - ($E34 + 5) = 0, $F34, AM34 * (1 - IFERROR(INDEX('Inputs & Assuptions'!$C$13:$C$72, COLUMN() - ($E34 + 5)), 0)) ) )} -> 1065.7417 | AO34: {=IF(COLUMN() - ($E34 + 5) < 0, 0, IF(COLUMN() - ($E34 + 5) = 0, $F34, AN34 * (1 - IFERROR(INDEX('Inputs & Assuptions'!$C$13:$C$72, COLUMN() - ($E34 + 5)), 0)) ) )} -> 1047.0913 | AP34: {=IF(COLUMN() - ($E34 + 5) < 0, 0, IF(COLUMN() - ($E34 + 5) = 0, $F34, AO34 * (1 - IFERROR(INDEX('Inputs & Assuptions'!$C$13:$C$72, COLUMN() - ($E34 + 5)), 0)) ) )} -> 1031.3849 | ... BM34: {=IF(COLUMN() - ($E34 + 5) < 0, 0, IF(COLUMN() - ($E34 + 5) = 0, $F34, BL34 * (1 - IFERROR(INDEX('Inputs & Assuptions'!$C$13:$C$72, COLUMN() - ($E34 + 5)), 0)) ) )} -> 907.56505
A35: =A34+1 -> 30 | B35: =IF(MOD($A35-1, 12) = 0, $B34 * 1.05, $B34) -> 1653.75 | C35: =$B35*(1-'Inputs & Assuptions'!$C$12) -> 1289.925 | E35: =E34+1 -> 30 | AI35: =$C35 -> 1289.925 | AJ35: {=IF(COLUMN() - ($E35 + 5) < 0, 0, IF(COLUMN() - ($E35 + 5) = 0, $F35, AI35 * (1 - IFERROR(INDEX('Inputs & Assuptions'!$C$13:$C$72, COLUMN() - ($E35 + 5)), 0)) ) )} -> 1222.2039 | AK35: {=IF(COLUMN() - ($E35 + 5) < 0, 0, IF(COLUMN() - ($E35 + 5) = 0, $F35, AJ35 * (1 - IFERROR(INDEX('Inputs & Assuptions'!$C$13:$C$72, COLUMN() - ($E35 + 5)), 0)) ) )} -> 1173.3158 | AL35: {=IF(COLUMN() - ($E35 + 5) < 0, 0, IF(COLUMN() - ($E35 + 5) = 0, $F35, AK35 * (1 - IFERROR(INDEX('Inputs & Assuptions'!$C$13:$C$72, COLUMN() - ($E35 + 5)), 0)) ) )} -> 1141.0496 | AM35: {=IF(COLUMN() - ($E35 + 5) < 0, 0, IF(COLUMN() - ($E35 + 5) = 0, $F35, AL35 * (1 - IFERROR(INDEX('Inputs & Assuptions'!$C$13:$C$72, COLUMN() - ($E35 + 5)), 0)) ) )} -> 1112.5234 | AN35: {=IF(COLUMN() - ($E35 + 5) < 0, 0, IF(COLUMN() - ($E35 + 5) = 0, $F35, AM35 * (1 - IFERROR(INDEX('Inputs & Assuptions'!$C$13:$C$72, COLUMN() - ($E35 + 5)), 0)) ) )} -> 1087.4916 | AO35: {=IF(COLUMN() - ($E35 + 5) < 0, 0, IF(COLUMN() - ($E35 + 5) = 0, $F35, AN35 * (1 - IFERROR(INDEX('Inputs & Assuptions'!$C$13:$C$72, COLUMN() - ($E35 + 5)), 0)) ) )} -> 1065.7417 | AP35: {=IF(COLUMN() - ($E35 + 5) < 0, 0, IF(COLUMN() - ($E35 + 5) = 0, $F35, AO35 * (1 - IFERROR(INDEX('Inputs & Assuptions'!$C$13:$C$72, COLUMN() - ($E35 + 5)), 0)) ) )} -> 1047.0913 | AQ35: {=IF(COLUMN() - ($E35 + 5) < 0, 0, IF(COLUMN() - ($E35 + 5) = 0, $F35, AP35 * (1 - IFERROR(INDEX('Inputs & Assuptions'!$C$13:$C$72, COLUMN() - ($E35 + 5)), 0)) ) )} -> 1031.3849 | ... BM35: {=IF(COLUMN() - ($E35 + 5) < 0, 0, IF(COLUMN() - ($E35 + 5) = 0, $F35, BL35 * (1 - IFERROR(INDEX('Inputs & Assuptions'!$C$13:$C$72, COLUMN() - ($E35 + 5)), 0)) ) )} -> 912.12568
A36: =A35+1 -> 31 | B36: =IF(MOD($A36-1, 12) = 0, $B35 * 1.05, $B35) -> 1653.75 | C36: =$B36*(1-'Inputs & Assuptions'!$C$12) -> 1289.925 | E36: =E35+1 -> 31 | AJ36: =$C36 -> 1289.925 | AK36: {=IF(COLUMN() - ($E36 + 5) < 0, 0, IF(COLUMN() - ($E36 + 5) = 0, $F36, AJ36 * (1 - IFERROR(INDEX('Inputs & Assuptions'!$C$13:$C$72, COLUMN() - ($E36 + 5)), 0)) ) )} -> 1222.2039 | AL36: {=IF(COLUMN() - ($E36 + 5) < 0, 0, IF(COLUMN() - ($E36 + 5) = 0, $F36, AK36 * (1 - IFERROR(INDEX('Inputs & Assuptions'!$C$13:$C$72, COLUMN() - ($E36 + 5)), 0)) ) )} -> 1173.3158 | AM36: {=IF(COLUMN() - ($E36 + 5) < 0, 0, IF(COLUMN() - ($E36 + 5) = 0, $F36, AL36 * (1 - IFERROR(INDEX('Inputs & Assuptions'!$C$13:$C$72, COLUMN() - ($E36 + 5)), 0)) ) )} -> 1141.0496 | AN36: {=IF(COLUMN() - ($E36 + 5) < 0, 0, IF(COLUMN() - ($E36 + 5) = 0, $F36, AM36 * (1 - IFERROR(INDEX('Inputs & Assuptions'!$C$13:$C$72, COLUMN() - ($E36 + 5)), 0)) ) )} -> 1112.5234 | AO36: {=IF(COLUMN() - ($E36 + 5) < 0, 0, IF(COLUMN() - ($E36 + 5) = 0, $F36, AN36 * (1 - IFERROR(INDEX('Inputs & Assuptions'!$C$13:$C$72, COLUMN() - ($E36 + 5)), 0)) ) )} -> 1087.4916 | AP36: {=IF(COLUMN() - ($E36 + 5) < 0, 0, IF(COLUMN() - ($E36 + 5) = 0, $F36, AO36 * (1 - IFERROR(INDEX('Inputs & Assuptions'!$C$13:$C$72, COLUMN() - ($E36 + 5)), 0)) ) )} -> 1065.7417 | AQ36: {=IF(COLUMN() - ($E36 + 5) < 0, 0, IF(COLUMN() - ($E36 + 5) = 0, $F36, AP36 * (1 - IFERROR(INDEX('Inputs & Assuptions'!$C$13:$C$72, COLUMN() - ($E36 + 5)), 0)) ) )} -> 1047.0913 | AR36: {=IF(COLUMN() - ($E36 + 5) < 0, 0, IF(COLUMN() - ($E36 + 5) = 0, $F36, AQ36 * (1 - IFERROR(INDEX('Inputs & Assuptions'!$C$13:$C$72, COLUMN() - ($E36 + 5)), 0)) ) )} -> 1031.3849 | ... BM36: {=IF(COLUMN() - ($E36 + 5) < 0, 0, IF(COLUMN() - ($E36 + 5) = 0, $F36, BL36 * (1 - IFERROR(INDEX('Inputs & Assuptions'!$C$13:$C$72, COLUMN() - ($E36 + 5)), 0)) ) )} -> 916.70922
A37: =A36+1 -> 32 | B37: =IF(MOD($A37-1, 12) = 0, $B36 * 1.05, $B36) -> 1653.75 | C37: =$B37*(1-'Inputs & Assuptions'!$C$12) -> 1289.925 | E37: =E36+1 -> 32 | AK37: =$C37 -> 1289.925 | AL37: {=IF(COLUMN() - ($E37 + 5) < 0, 0, IF(COLUMN() - ($E37 + 5) = 0, $F37, AK37 * (1 - IFERROR(INDEX('Inputs & Assuptions'!$C$13:$C$72, COLUMN() - ($E37 + 5)), 0)) ) )} -> 1222.2039 | AM37: {=IF(COLUMN() - ($E37 + 5) < 0, 0, IF(COLUMN() - ($E37 + 5) = 0, $F37, AL37 * (1 - IFERROR(INDEX('Inputs & Assuptions'!$C$13:$C$72, COLUMN() - ($E37 + 5)), 0)) ) )} -> 1173.3158 | AN37: {=IF(COLUMN() - ($E37 + 5) < 0, 0, IF(COLUMN() - ($E37 + 5) = 0, $F37, AM37 * (1 - IFERROR(INDEX('Inputs & Assuptions'!$C$13:$C$72, COLUMN() - ($E37 + 5)), 0)) ) )} -> 1141.0496 | AO37: {=IF(COLUMN() - ($E37 + 5) < 0, 0, IF(COLUMN() - ($E37 + 5) = 0, $F37, AN37 * (1 - IFERROR(INDEX('Inputs & Assuptions'!$C$13:$C$72, COLUMN() - ($E37 + 5)), 0)) ) )} -> 1112.5234 | AP37: {=IF(COLUMN() - ($E37 + 5) < 0, 0, IF(COLUMN() - ($E37 + 5) = 0, $F37, AO37 * (1 - IFERROR(INDEX('Inputs & Assuptions'!$C$13:$C$72, COLUMN() - ($E37 + 5)), 0)) ) )} -> 1087.4916 | AQ37: {=IF(COLUMN() - ($E37 + 5) < 0, 0, IF(COLUMN() - ($E37 + 5) = 0, $F37, AP37 * (1 - IFERROR(INDEX('Inputs & Assuptions'!$C$13:$C$72, COLUMN() - ($E37 + 5)), 0)) ) )} -> 1065.7417 | AR37: {=IF(COLUMN() - ($E37 + 5) < 0, 0, IF(COLUMN() - ($E37 + 5) = 0, $F37, AQ37 * (1 - IFERROR(INDEX('Inputs & Assuptions'!$C$13:$C$72, COLUMN() - ($E37 + 5)), 0)) ) )} -> 1047.0913 | AS37: {=IF(COLUMN() - ($E37 + 5) < 0, 0, IF(COLUMN() - ($E37 + 5) = 0, $F37, AR37 * (1 - IFERROR(INDEX('Inputs & Assuptions'!$C$13:$C$72, COLUMN() - ($E37 + 5)), 0)) ) )} -> 1031.3849 | ... BM37: {=IF(COLUMN() - ($E37 + 5) < 0, 0, IF(COLUMN() - ($E37 + 5) = 0, $F37, BL37 * (1 - IFERROR(INDEX('Inputs & Assuptions'!$C$13:$C$72, COLUMN() - ($E37 + 5)), 0)) ) )} -> 921.3158
A38: =A37+1 -> 33 | B38: =IF(MOD($A38-1, 12) = 0, $B37 * 1.05, $B37) -> 1653.75 | C38: =$B38*(1-'Inputs & Assuptions'!$C$12) -> 1289.925 | E38: =E37+1 -> 33 | AL38: =$C38 -> 1289.925 | AM38: {=IF(COLUMN() - ($E38 + 5) < 0, 0, IF(COLUMN() - ($E38 + 5) = 0, $F38, AL38 * (1 - IFERROR(INDEX('Inputs & Assuptions'!$C$13:$C$72, COLUMN() - ($E38 + 5)), 0)) ) )} -> 1222.2039 | AN38: {=IF(COLUMN() - ($E38 + 5) < 0, 0, IF(COLUMN() - ($E38 + 5) = 0, $F38, AM38 * (1 - IFERROR(INDEX('Inputs & Assuptions'!$C$13:$C$72, COLUMN() - ($E38 + 5)), 0)) ) )} -> 1173.3158 | AO38: {=IF(COLUMN() - ($E38 + 5) < 0, 0, IF(COLUMN() - ($E38 + 5) = 0, $F38, AN38 * (1 - IFERROR(INDEX('Inputs & Assuptions'!$C$13:$C$72, COLUMN() - ($E38 + 5)), 0)) ) )} -> 1141.0496 | AP38: {=IF(COLUMN() - ($E38 + 5) < 0, 0, IF(COLUMN() - ($E38 + 5) = 0, $F38, AO38 * (1 - IFERROR(INDEX('Inputs & Assuptions'!$C$13:$C$72, COLUMN() - ($E38 + 5)), 0)) ) )} -> 1112.5234 | AQ38: {=IF(COLUMN() - ($E38 + 5) < 0, 0, IF(COLUMN() - ($E38 + 5) = 0, $F38, AP38 * (1 - IFERROR(INDEX('Inputs & Assuptions'!$C$13:$C$72, COLUMN() - ($E38 + 5)), 0)) ) )} -> 1087.4916 | AR38: {=IF(COLUMN() - ($E38 + 5) < 0, 0, IF(COLUMN() - ($E38 + 5) = 0, $F38, AQ38 * (1 - IFERROR(INDEX('Inputs & Assuptions'!$C$13:$C$72, COLUMN() - ($E38 + 5)), 0)) ) )} -> 1065.7417 | AS38: {=IF(COLUMN() - ($E38 + 5) < 0, 0, IF(COLUMN() - ($E38 + 5) = 0, $F38, AR38 * (1 - IFERROR(INDEX('Inputs & Assuptions'!$C$13:$C$72, COLUMN() - ($E38 + 5)), 0)) ) )} -> 1047.0913 | AT38: {=IF(COLUMN() - ($E38 + 5) < 0, 0, IF(COLUMN() - ($E38 + 5) = 0, $F38, AS38 * (1 - IFERROR(INDEX('Inputs & Assuptions'!$C$13:$C$72, COLUMN() - ($E38 + 5)), 0)) ) )} -> 1031.3849 | ... BM38: {=IF(COLUMN() - ($E38 + 5) < 0, 0, IF(COLUMN() - ($E38 + 5) = 0, $F38, BL38 * (1 - IFERROR(INDEX('Inputs & Assuptions'!$C$13:$C$72, COLUMN() - ($E38 + 5)), 0)) ) )} -> 925.94553
A39: =A38+1 -> 34 | B39: =IF(MOD($A39-1, 12) = 0, $B38 * 1.05, $B38) -> 1653.75 | C39: =$B39*(1-'Inputs & Assuptions'!$C$12) -> 1289.925 | E39: =E38+1 -> 34 | AM39: =$C39 -> 1289.925 | AN39: {=IF(COLUMN() - ($E39 + 5) < 0, 0, IF(COLUMN() - ($E39 + 5) = 0, $F39, AM39 * (1 - IFERROR(INDEX('Inputs & Assuptions'!$C$13:$C$72, COLUMN() - ($E39 + 5)), 0)) ) )} -> 1222.2039 | AO39: {=IF(COLUMN() - ($E39 + 5) < 0, 0, IF(COLUMN() - ($E39 + 5) = 0, $F39, AN39 * (1 - IFERROR(INDEX('Inputs & Assuptions'!$C$13:$C$72, COLUMN() - ($E39 + 5)), 0)) ) )} -> 1173.3158 | AP39: {=IF(COLUMN() - ($E39 + 5) < 0, 0, IF(COLUMN() - ($E39 + 5) = 0, $F39, AO39 * (1 - IFERROR(INDEX('Inputs & Assuptions'!$C$13:$C$72, COLUMN() - ($E39 + 5)), 0)) ) )} -> 1141.0496 | AQ39: {=IF(COLUMN() - ($E39 + 5) < 0, 0, IF(COLUMN() - ($E39 + 5) = 0, $F39, AP39 * (1 - IFERROR(INDEX('Inputs & Assuptions'!$C$13:$C$72, COLUMN() - ($E39 + 5)), 0)) ) )} -> 1112.5234 | AR39: {=IF(COLUMN() - ($E39 + 5) < 0, 0, IF(COLUMN() - ($E39 + 5) = 0, $F39, AQ39 * (1 - IFERROR(INDEX('Inputs & Assuptions'!$C$13:$C$72, COLUMN() - ($E39 + 5)), 0)) ) )} -> 1087.4916 | AS39: {=IF(COLUMN() - ($E39 + 5) < 0, 0, IF(COLUMN() - ($E39 + 5) = 0, $F39, AR39 * (1 - IFERROR(INDEX('Inputs & Assuptions'!$C$13:$C$72, COLUMN() - ($E39 + 5)), 0)) ) )} -> 1065.7417 | AT39: {=IF(COLUMN() - ($E39 + 5) < 0, 0, IF(COLUMN() - ($E39 + 5) = 0, $F39, AS39 * (1 - IFERROR(INDEX('Inputs & Assuptions'!$C$13:$C$72, COLUMN() - ($E39 + 5)), 0)) ) )} -> 1047.0913 | AU39: {=IF(COLUMN() - ($E39 + 5) < 0, 0, IF(COLUMN() - ($E39 + 5) = 0, $F39, AT39 * (1 - IFERROR(INDEX('Inputs & Assuptions'!$C$13:$C$72, COLUMN() - ($E39 + 5)), 0)) ) )} -> 1031.3849 | ... BM39: {=IF(COLUMN() - ($E39 + 5) < 0, 0, IF(COLUMN() - ($E39 + 5) = 0, $F39, BL39 * (1 - IFERROR(INDEX('Inputs & Assuptions'!$C$13:$C$72, COLUMN() - ($E39 + 5)), 0)) ) )} -> 930.59852
